Workbook
Name subscribers_per_cbo: 'Assumptions'!$C$7
Name checkins_per_year: 'Assumptions'!$C$8
Name opening_segments: 'Assumptions'!$C$9
Name followup_segments: 'Assumptions'!$C$10
Name inbound_segments_if_complete: 'Assumptions'!$C$11
Name completion_rate: 'Assumptions'!$C$12
Name pages_per_cbo_month: 'Assumptions'!$C$15
Name refresh_days: 'Assumptions'!$C$16
Name searches_per_refresh: 'Assumptions'!$C$17
Name storage_mb_per_cbo: 'Assumptions'!$C$18
Name cbo_http_requests: 'Assumptions'!$C$19
Name geocode_updates_per_cbo: 'Assumptions'!$C$20
Name firestore_writes_per_cbo: 'Assumptions'!$C$21
Name firestore_reads_per_cbo: 'Assumptions'!$C$22
Name claude_per_cbo: 'Assumptions'!$C$23
Name map_loads_per_funder: 'Assumptions'!$C$26
Name ai_searches_per_funder: 'Assumptions'!$C$27
Name questions_per_funder: 'Assumptions'!$C$28
Name audits_per_funder: 'Assumptions'!$C$29
Name searches_per_audit: 'Assumptions'!$C$30
Name funder_http_requests: 'Assumptions'!$C$31
Name egress_mb_per_funder: 'Assumptions'!$C$32
Name doc_input_tokens: 'Assumptions'!$C$35
Name doc_output_tokens: 'Assumptions'!$C$36
Name research_input_tokens: 'Assumptions'!$C$37
Name research_output_tokens: 'Assumptions'!$C$38
Name interpret_input_tokens: 'Assumptions'!$C$39
Name interpret_output_tokens: 'Assumptions'!$C$40
Name rank_input_tokens: 'Assumptions'!$C$41
Name rank_output_tokens: 'Assumptions'!$C$42
Name question_input_tokens: 'Assumptions'!$C$43
Name question_output_tokens: 'Assumptions'!$C$44
Name sms_input_tokens: 'Assumptions'!$C$45
Name sms_output_tokens: 'Assumptions'!$C$46
Name sms_ai_share: 'Assumptions'!$C$47
Name audit_input_tokens: 'Assumptions'!$C$48
Name audit_output_tokens: 'Assumptions'!$C$49
Name page_vcpu_seconds: 'Assumptions'!$C$50
Name request_vcpu_seconds: 'Assumptions'!$C$51
Name memory_gib: 'Assumptions'!$C$52
Name min_instances: 'Assumptions'!$C$53
Name price_kenya_sms: 'Assumptions'!$C$56
Name price_inbound_sms: 'Assumptions'!$C$57
Name price_phone_number: 'Assumptions'!$C$58
Name phone_numbers: 'Assumptions'!$C$59
Name price_azure_page: 'Assumptions'!$C$60
Name price_gemini_in: 'Assumptions'!$C$61
Name price_gemini_out: 'Assumptions'!$C$62
Name price_openai_in: 'Assumptions'!$C$63
Name price_openai_out: 'Assumptions'!$C$64
Name price_search_1k: 'Assumptions'!$C$65
Name price_map_1k: 'Assumptions'!$C$66
Name price_geocode_1k: 'Assumptions'!$C$67
Name price_storage_gb: 'Assumptions'!$C$68
Name price_egress_gb: 'Assumptions'!$C$69
Name price_vcpu: 'Assumptions'!$C$70
Name price_gib: 'Assumptions'!$C$71
Name price_million_requests: 'Assumptions'!$C$72
Name price_warm_instance: 'Assumptions'!$C$73
Name price_sql_micro: 'Assumptions'!$C$74

Sheet Overview
A1: Kumbu Connect cost projections
A2: Live production, hosted and running. CBO signup is a Google Form or the in-app form, plus one short SMS link (about $0.31, or $0 with a QR code). That saving is on the One-time setup sheet. The monthly totals below are mostly community check-in texts, and those are unchanged. Yellow cells on Assumptions are the only inputs.
A4: Open a sheet
A5: Assumptions | B5: Change panel size, prices, pages, and tiers
A6: Unit costs | B6: What one more CBO costs, and one more funder
A7: Monthly matrix | B7: Full grid of CBO sizes by funder sizes
A8: Matched growth | B8: Both sides grow together, with a chart
A9: Sensitivity | B9: Monthly texts, larger panels, heavier Maps and AI
A10: One-time setup | B10: Cash to onboard up to each tier
A11: Notes | B11: What is included, what is free, what is left out
A13: The slope, at the default settings
A14: Platform floor, before usage | B14: =platform_floor_small | C14: Database plus number, secrets, and domain, while both sides are under 200.
A15: Each additional active CBO | B15: =variable_cost_per_cbo | C15: Almost entirely SMS to the community panel. Documents are a few cents.
A16: Each additional active funder | B16: =variable_cost_per_funder | C16: Search, questions, an occasional audit, and a little data transfer. The map is still free at these volumes.
A18: When both sides are the same size
A19: Active CBOs and funders | B19: Monthly | C19: Annual | D19: Per CBO | E19: SMS share | F19: Database | G19: SMS
A20: =cbo_tier_1 | B20: =SUMIFS(Scenarios!$V$6:$V$41,Scenarios!$A$6:$A$41,cbo_tier_1,Scenarios!$B$6:$B$41,cbo_tier_1) | C20: =B20*12 | D20: =IF(A20=0,NA(),B20/A20) | E20: =IF(B20=0,0,G20/B20) | F20: =SUMIFS(Scenarios!$C$6:$C$41,Scenarios!$A$6:$A$41,cbo_tier_1,Scenarios!$B$6:$B$41,cbo_tier_1) | G20: =(SUMIFS(Scenarios!$I$6:$I$41,Scenarios!$A$6:$A$41,cbo_tier_1,Scenarios!$B$6:$B$41,cbo_tier_1))+(SUMIFS(Scenarios!$J$6:$J$41,Scenarios!$A$6:$A$41,cbo_tier_1,Scenarios!$B$6:$B$41,cbo_tier_1))
A21: =cbo_tier_2 | B21: =SUMIFS(Scenarios!$V$6:$V$41,Scenarios!$A$6:$A$41,cbo_tier_2,Scenarios!$B$6:$B$41,cbo_tier_2) | C21: =B21*12 | D21: =IF(A21=0,NA(),B21/A21) | E21: =IF(B21=0,0,G21/B21) | F21: =SUMIFS(Scenarios!$C$6:$C$41,Scenarios!$A$6:$A$41,cbo_tier_2,Scenarios!$B$6:$B$41,cbo_tier_2) | G21: =(SUMIFS(Scenarios!$I$6:$I$41,Scenarios!$A$6:$A$41,cbo_tier_2,Scenarios!$B$6:$B$41,cbo_tier_2))+(SUMIFS(Scenarios!$J$6:$J$41,Scenarios!$A$6:$A$41,cbo_tier_2,Scenarios!$B$6:$B$41,cbo_tier_2))
A22: =cbo_tier_3 | B22: =SUMIFS(Scenarios!$V$6:$V$41,Scenarios!$A$6:$A$41,cbo_tier_3,Scenarios!$B$6:$B$41,cbo_tier_3) | C22: =B22*12 | D22: =IF(A22=0,NA(),B22/A22) | E22: =IF(B22=0,0,G22/B22) | F22: =SUMIFS(Scenarios!$C$6:$C$41,Scenarios!$A$6:$A$41,cbo_tier_3,Scenarios!$B$6:$B$41,cbo_tier_3) | G22: =(SUMIFS(Scenarios!$I$6:$I$41,Scenarios!$A$6:$A$41,cbo_tier_3,Scenarios!$B$6:$B$41,cbo_tier_3))+(SUMIFS(Scenarios!$J$6:$J$41,Scenarios!$A$6:$A$41,cbo_tier_3,Scenarios!$B$6:$B$41,cbo_tier_3))
A23: =cbo_tier_4 | B23: =SUMIFS(Scenarios!$V$6:$V$41,Scenarios!$A$6:$A$41,cbo_tier_4,Scenarios!$B$6:$B$41,cbo_tier_4) | C23: =B23*12 | D23: =IF(A23=0,NA(),B23/A23) | E23: =IF(B23=0,0,G23/B23) | F23: =SUMIFS(Scenarios!$C$6:$C$41,Scenarios!$A$6:$A$41,cbo_tier_4,Scenarios!$B$6:$B$41,cbo_tier_4) | G23: =(SUMIFS(Scenarios!$I$6:$I$41,Scenarios!$A$6:$A$41,cbo_tier_4,Scenarios!$B$6:$B$41,cbo_tier_4))+(SUMIFS(Scenarios!$J$6:$J$41,Scenarios!$A$6:$A$41,cbo_tier_4,Scenarios!$B$6:$B$41,cbo_tier_4))
A24: =cbo_tier_5 | B24: =SUMIFS(Scenarios!$V$6:$V$41,Scenarios!$A$6:$A$41,cbo_tier_5,Scenarios!$B$6:$B$41,cbo_tier_5) | C24: =B24*12 | D24: =IF(A24=0,NA(),B24/A24) | E24: =IF(B24=0,0,G24/B24) | F24: =SUMIFS(Scenarios!$C$6:$C$41,Scenarios!$A$6:$A$41,cbo_tier_5,Scenarios!$B$6:$B$41,cbo_tier_5) | G24: =(SUMIFS(Scenarios!$I$6:$I$41,Scenarios!$A$6:$A$41,cbo_tier_5,Scenarios!$B$6:$B$41,cbo_tier_5))+(SUMIFS(Scenarios!$J$6:$J$41,Scenarios!$A$6:$A$41,cbo_tier_5,Scenarios!$B$6:$B$41,cbo_tier_5))
A25: =cbo_tier_6 | B25: =SUMIFS(Scenarios!$V$6:$V$41,Scenarios!$A$6:$A$41,cbo_tier_6,Scenarios!$B$6:$B$41,cbo_tier_6) | C25: =B25*12 | D25: =IF(A25=0,NA(),B25/A25) | E25: =IF(B25=0,0,G25/B25) | F25: =SUMIFS(Scenarios!$C$6:$C$41,Scenarios!$A$6:$A$41,cbo_tier_6,Scenarios!$B$6:$B$41,cbo_tier_6) | G25: =(SUMIFS(Scenarios!$I$6:$I$41,Scenarios!$A$6:$A$41,cbo_tier_6,Scenarios!$B$6:$B$41,cbo_tier_6))+(SUMIFS(Scenarios!$J$6:$J$41,Scenarios!$A$6:$A$41,cbo_tier_6,Scenarios!$B$6:$B$41,cbo_tier_6))
A27: Monthly cost for every mix of CBOs and funders
A28: Active funders → | B28: =funder_tier_1 | C28: =funder_tier_2 | D28: =funder_tier_3 | E28: =funder_tier_4 | F28: =funder_tier_5 | G28: =funder_tier_6
A29: =cbo_tier_1 | B29: =SUMIFS(Scenarios!$V$6:$V$41,Scenarios!$A$6:$A$41,cbo_tier_1,Scenarios!$B$6:$B$41,funder_tier_1) | C29: =SUMIFS(Scenarios!$V$6:$V$41,Scenarios!$A$6:$A$41,cbo_tier_1,Scenarios!$B$6:$B$41,funder_tier_2) | D29: =SUMIFS(Scenarios!$V$6:$V$41,Scenarios!$A$6:$A$41,cbo_tier_1,Scenarios!$B$6:$B$41,funder_tier_3) | E29: =SUMIFS(Scenarios!$V$6:$V$41,Scenarios!$A$6:$A$41,cbo_tier_1,Scenarios!$B$6:$B$41,funder_tier_4) | F29: =SUMIFS(Scenarios!$V$6:$V$41,Scenarios!$A$6:$A$41,cbo_tier_1,Scenarios!$B$6:$B$41,funder_tier_5) | G29: =SUMIFS(Scenarios!$V$6:$V$41,Scenarios!$A$6:$A$41,cbo_tier_1,Scenarios!$B$6:$B$41,funder_tier_6)
A30: =cbo_tier_2 | B30: =SUMIFS(Scenarios!$V$6:$V$41,Scenarios!$A$6:$A$41,cbo_tier_2,Scenarios!$B$6:$B$41,funder_tier_1) | C30: =SUMIFS(Scenarios!$V$6:$V$41,Scenarios!$A$6:$A$41,cbo_tier_2,Scenarios!$B$6:$B$41,funder_tier_2) | D30: =SUMIFS(Scenarios!$V$6:$V$41,Scenarios!$A$6:$A$41,cbo_tier_2,Scenarios!$B$6:$B$41,funder_tier_3) | E30: =SUMIFS(Scenarios!$V$6:$V$41,Scenarios!$A$6:$A$41,cbo_tier_2,Scenarios!$B$6:$B$41,funder_tier_4) | F30: =SUMIFS(Scenarios!$V$6:$V$41,Scenarios!$A$6:$A$41,cbo_tier_2,Scenarios!$B$6:$B$41,funder_tier_5) | G30: =SUMIFS(Scenarios!$V$6:$V$41,Scenarios!$A$6:$A$41,cbo_tier_2,Scenarios!$B$6:$B$41,funder_tier_6)
A31: =cbo_tier_3 | B31: =SUMIFS(Scenarios!$V$6:$V$41,Scenarios!$A$6:$A$41,cbo_tier_3,Scenarios!$B$6:$B$41,funder_tier_1) | C31: =SUMIFS(Scenarios!$V$6:$V$41,Scenarios!$A$6:$A$41,cbo_tier_3,Scenarios!$B$6:$B$41,funder_tier_2) | D31: =SUMIFS(Scenarios!$V$6:$V$41,Scenarios!$A$6:$A$41,cbo_tier_3,Scenarios!$B$6:$B$41,funder_tier_3) | E31: =SUMIFS(Scenarios!$V$6:$V$41,Scenarios!$A$6:$A$41,cbo_tier_3,Scenarios!$B$6:$B$41,funder_tier_4) | F31: =SUMIFS(Scenarios!$V$6:$V$41,Scenarios!$A$6:$A$41,cbo_tier_3,Scenarios!$B$6:$B$41,funder_tier_5) | G31: =SUMIFS(Scenarios!$V$6:$V$41,Scenarios!$A$6:$A$41,cbo_tier_3,Scenarios!$B$6:$B$41,funder_tier_6)
A32: =cbo_tier_4 | B32: =SUMIFS(Scenarios!$V$6:$V$41,Scenarios!$A$6:$A$41,cbo_tier_4,Scenarios!$B$6:$B$41,funder_tier_1) | C32: =SUMIFS(Scenarios!$V$6:$V$41,Scenarios!$A$6:$A$41,cbo_tier_4,Scenarios!$B$6:$B$41,funder_tier_2) | D32: =SUMIFS(Scenarios!$V$6:$V$41,Scenarios!$A$6:$A$41,cbo_tier_4,Scenarios!$B$6:$B$41,funder_tier_3) | E32: =SUMIFS(Scenarios!$V$6:$V$41,Scenarios!$A$6:$A$41,cbo_tier_4,Scenarios!$B$6:$B$41,funder_tier_4) | F32: =SUMIFS(Scenarios!$V$6:$V$41,Scenarios!$A$6:$A$41,cbo_tier_4,Scenarios!$B$6:$B$41,funder_tier_5) | G32: =SUMIFS(Scenarios!$V$6:$V$41,Scenarios!$A$6:$A$41,cbo_tier_4,Scenarios!$B$6:$B$41,funder_tier_6)
A33: =cbo_tier_5 | B33: =SUMIFS(Scenarios!$V$6:$V$41,Scenarios!$A$6:$A$41,cbo_tier_5,Scenarios!$B$6:$B$41,funder_tier_1) | C33: =SUMIFS(Scenarios!$V$6:$V$41,Scenarios!$A$6:$A$41,cbo_tier_5,Scenarios!$B$6:$B$41,funder_tier_2) | D33: =SUMIFS(Scenarios!$V$6:$V$41,Scenarios!$A$6:$A$41,cbo_tier_5,Scenarios!$B$6:$B$41,funder_tier_3) | E33: =SUMIFS(Scenarios!$V$6:$V$41,Scenarios!$A$6:$A$41,cbo_tier_5,Scenarios!$B$6:$B$41,funder_tier_4) | F33: =SUMIFS(Scenarios!$V$6:$V$41,Scenarios!$A$6:$A$41,cbo_tier_5,Scenarios!$B$6:$B$41,funder_tier_5) | G33: =SUMIFS(Scenarios!$V$6:$V$41,Scenarios!$A$6:$A$41,cbo_tier_5,Scenarios!$B$6:$B$41,funder_tier_6)
A34: =cbo_tier_6 | B34: =SUMIFS(Scenarios!$V$6:$V$41,Scenarios!$A$6:$A$41,cbo_tier_6,Scenarios!$B$6:$B$41,funder_tier_1) | C34: =SUMIFS(Scenarios!$V$6:$V$41,Scenarios!$A$6:$A$41,cbo_tier_6,Scenarios!$B$6:$B$41,funder_tier_2) | D34: =SUMIFS(Scenarios!$V$6:$V$41,Scenarios!$A$6:$A$41,cbo_tier_6,Scenarios!$B$6:$B$41,funder_tier_3) | E34: =SUMIFS(Scenarios!$V$6:$V$41,Scenarios!$A$6:$A$41,cbo_tier_6,Scenarios!$B$6:$B$41,funder_tier_4) | F34: =SUMIFS(Scenarios!$V$6:$V$41,Scenarios!$A$6:$A$41,cbo_tier_6,Scenarios!$B$6:$B$41,funder_tier_5) | G34: =SUMIFS(Scenarios!$V$6:$V$41,Scenarios!$A$6:$A$41,cbo_tier_6,Scenarios!$B$6:$B$41,funder_tier_6)
A36: How the costs combine
A37: The two sides mostly add. They do not multiply. A large funder base does not make community SMS more expensive, and a large CBO base does not make map loads more expensive. They meet in two places: the database steps up when either side reaches 200, and again at 500, and a few shared allowances (Maps, web search, Cloud Run) are project-wide. Down a column, the bill follows CBOs because of texts to Kenya. Across a row, it stays nearly flat until the funder count crosses a database step. Cost per CBO starts higher at 10 organizations, because the database is a fixed bill, then settles close to the SMS cost per organization. The Sensitivity sheet is where the total stops being modest: monthly check-ins, or a much larger texting panel, multiply the SMS line. Heavier Gemini pricing and busier map use move it much less.

Sheet Assumptions
B1: Assumptions
B2: Yellow cells are the only inputs. Every other sheet reads these values. Tiers are active users in a month, not registered-but-idle accounts.
B4: Input | C4: Value | D4: Unit | E4: What it means
B6: Community SMS
B7: Community texters per CBO | C7: 8 | D7: people | E7: A feedback panel, not every beneficiary. Each person is eligible for the twice-yearly check-in.
B8: Check-ins per texter per year | C8: 2 | D8: campaigns / year | E8: Matches the app: one check-in every 6 months. Monthly check-ins are modeled on Sensitivity.
B9: Opening texts per check-in | C9: 1 | D9: SMS segments | E9: Sent to every texter, even if they never reply. Assumes the prompt fits in one 160-character segment.
B10: Follow-up texts if they finish | C10: 3 | D10: SMS segments | E10: Help-count question, story question, and thank-you. Charged only when someone completes the cycle.
B11: Replies if they finish | C11: 3 | D11: SMS segments | E11: Rating, count, and story coming back to the US number.
B12: Share who finish a check-in | C12: 0.55 | D12: of texters | E12: Everyone else costs only the opening text.
B14: CBO activity each month
B15: Document pages processed | C15: 3 | D15: pages / CBO | E15: Ongoing bookkeeping. The first-time backlog is on One-time setup.
B16: Public-web research interval | C16: 45 | D16: days | E16: The app refreshes a CBO about every 45 days, not on every funder search.
B17: Web searches per refresh | C17: 2 | D17: queries | E17: Results are cached. 100 Google queries a day are free.
B18: Stored files per CBO | C18: 60 | D18: MB | E18: Uploads and photos. The first 5 GB on the project is treated as included.
B19: App requests per CBO | C19: 40 | D19: requests | E19: Logins, saves, and page views. Used for the Cloud Run estimate.
B20: Address changes | C20: 0.02 | D20: per CBO / month | E20: The pin is stored after the first lookup.
B21: Firestore writes | C21: 25 | D21: writes / CBO | E21: Mirrors of SMS and bookkeeping. Free tier covers this through 500 CBOs.
B22: Firestore reads | C22: 50 | D22: reads / CBO | E22: Free tier is 50,000 reads a day.
B23: Optional Claude spend | C23: 0 | D23: USD / CBO / month | E23: Zero keeps the legacy Claude profile step off. Enter a dollar amount to include it.
B25: Funder activity each month
B26: Marketplace map loads | C26: 6 | D26: loads / funder | E26: One load per visit, about weekly. First 10,000 loads a month are free.
B27: AI marketplace searches | C27: 3 | D27: searches / funder | E27: Two model calls each, ranking a shortlist rather than every CBO.
B28: Questions about a CBO | C28: 1 | D28: questions / funder | E28: Asked of a profile that is already on the platform.
B29: Funding-audit checks | C29: 0.2 | D29: audits / funder | E29: About one OpenAI document check per funder every five months.
B30: Web searches per audit | C30: 1 | D30: queries | E30: A single confirmation search, not a fresh crawl.
B31: App requests per funder | C31: 24 | D31: requests | E31: Marketplace, profiles, and in-app messages. Those messages are not SMS.
B32: Data downloaded | C32: 20 | D32: MB / funder | E32: Pages and photos from the US region, with browser caching.
B34: Work done on each model or document call
B35: Document page, input tokens | C35: 4000 | D35: tokens | E35: Gemini normalizes Azure's transcription. It does not re-read the whole scan as the primary path.
B36: Document page, output tokens | C36: 1500 | D36: tokens | E36: Structured rows.
B37: Web-research input tokens | C37: 4500 | D37: tokens | E37: A few page excerpts.
B38: Web-research output tokens | C38: 900 | D38: tokens | E38: Short claims for the CBO to confirm.
B39: Search interpret, input tokens | C39: 1200 | D39: tokens
B40: Search interpret, output tokens | C40: 350 | D40: tokens
B41: Search rank, input tokens | C41: 5000 | D41: tokens | E41: Shortlist only. This cap is what stops funder search from getting expensive as CBOs grow.
B42: Search rank, output tokens | C42: 700 | D42: tokens
B43: CBO question, input tokens | C43: 2500 | D43: tokens
B44: CBO question, output tokens | C44: 500 | D44: tokens
B45: SMS parse, input tokens | C45: 600 | D45: tokens
B46: SMS parse, output tokens | C46: 150 | D46: tokens
B47: Inbound texts that use the model | C47: 0.35 | D47: of replies | E47: Numbers are parsed in code. Stories are the replies that use Gemini.
B48: Funding audit, input tokens | C48: 2000 | D48: tokens | E48: OpenAI, one document.
B49: Funding audit, output tokens | C49: 600 | D49: tokens
B50: Server time per document page | C50: 30 | D50: vCPU-seconds | E50: Includes waiting on Azure and Gemini. Still inside the Cloud Run free tier at these volumes.
B51: Server time per ordinary request | C51: 0.2 | D51: vCPU-seconds
B52: Server memory | C52: 2 | D52: GiB | E52: Same size as the current Cloud Run service.
B53: Always-warm server instances | C53: 0 | D53: instances | E53: Leave at 0 so an idle app is not billed for CPU. Set to 1 only to avoid cold starts.
B55: Prices
B56: SMS to Kenya | C56: 0.3134 | D56: USD / segment | E56: Twilio's posted outbound rate to Kenya. Use the number in your own Twilio console if it differs.
B57: SMS received on the US number | C57: 0.0083 | D57: USD / segment | E57: Replies are billed at US inbound rates.
B58: Twilio number | C58: 1.15 | D58: USD / number / month
B59: Phone numbers in use | C59: 1 | D59: numbers | E59: One US long code covers this volume.
B60: Azure Layout | C60: 0.01 | D60: USD / page | E60: $10 per 1,000 pages. Layout is the model that preserves tables.
B61: Gemini input | C61: 0.3 | D61: USD / 1 million tokens | E61: Efficient Flash-class price. Sensitivity shows a 5× case closer to a higher-priced Flash model.
B62: Gemini output | C62: 2.5 | D62: USD / 1 million tokens
B63: OpenAI input | C63: 2 | D63: USD / 1 million tokens | E63: GPT-4.1 class. Used only on funding audits.
B64: OpenAI output | C64: 8 | D64: USD / 1 million tokens
B65: Google Custom Search | C65: 5 | D65: USD / 1,000 queries | E65: After about 3,000 free queries a month.
B66: Google Maps load | C66: 7 | D66: USD / 1,000 loads | E66: After 10,000 free dynamic map loads a month.
B67: Google Geocoding | C67: 5 | D67: USD / 1,000 lookups | E67: After 10,000 free lookups. Stored pins are not repeated.
B68: File storage | C68: 0.026 | D68: USD / GB-month | E68: After 5 GB.
B69: Data transfer out | C69: 0.12 | D69: USD / GB | E69: From the US hosting region to users.
B70: Cloud Run CPU | C70: 2.4e-05 | D70: USD / vCPU-second | E70: Billed while a request is running, not while the app is idle.
B71: Cloud Run memory | C71: 2.5e-06 | D71: USD / GiB-second
B72: Cloud Run requests | C72: 0.4 | D72: USD / 1 million | E72: After 2 million free requests.
B73: Warm instance, if you keep one on | C73: 18 | D73: USD / month | E73: Added only when always-warm instances is greater than 0.
B74: Database, small | C74: 12 | D74: USD / month | E74: Shared-core Postgres, disk, and backups. Used while both sides are under 200.
B75: Database, medium | C75: 32 | D75: USD / month | E75: Used when either side reaches 200 active users.
B76: Database, large | C76: 65 | D76: USD / month | E76: About 1 vCPU, single zone, with backups. Used when either side reaches 500. A hot standby is not included.
B77: Secrets and image storage | C77: 1.5 | D77: USD / month
B78: Domain and log buffer | C78: 2 | D78: USD / month
B79: Firestore writes | C79: 0.09 | D79: USD / 100,000 | E79: After the free quota.
B80: Firestore reads | C80: 0.03 | D80: USD / 100,000 | E80: After the free quota.
B82: Included allowances and database steps
B83: Custom Search included | C83: 3000 | D83: queries / month | E83: 100 a day.
B84: Map loads included | C84: 10000 | D84: loads / month
B85: Geocodes included | C85: 10000 | D85: lookups / month
B86: Cloud Run CPU included | C86: 180000 | D86: vCPU-seconds / month
B87: Cloud Run memory included | C87: 360000 | D87: GiB-seconds / month
B88: Cloud Run requests included | C88: 2000000 | D88: requests / month
B89: Storage included | C89: 5 | D89: GB
B90: Data transfer included | C90: 0 | D90: GB | E90: None assumed.
B91: Firestore writes included | C91: 600000 | D91: writes / month | E91: 20,000 a day.
B92: Firestore reads included | C92: 1500000 | D92: reads / month | E92: 50,000 a day.
B93: Medium database begins | C93: 200 | D93: active users on either side
B94: Large database begins | C94: 500 | D94: active users on either side | E94: Sized for this tier. If you raise a tier past 500, raise the large-database price too.
B96: One-time cost when a CBO joins
B97: Onboarding texts to the leader | C97: 1 | D97: SMS segments | E97: A Google Form or the in-app form collects the profile. Twilio sends one short text with that link. Set this to 0 if they open a QR code or a link with no text. The old multi-step SMS conversation is not included.
B98: Backlog pages at signup | C98: 10 | D98: pages | E98: Charged once, in addition to the monthly page rate.
B100: Active-user tiers
B101: These six sizes drive every scenario. Edit them and the matrices follow.
C102: CBO tiers | D102: Funder tiers | E102: Both lists use the same steps so the grid is square. You can type different funder sizes.
B103: Tier 1 | C103: 10 | D103: 10
B104: Tier 2 | C104: 25 | D104: 25
B105: Tier 3 | C105: 50 | D105: 50
B106: Tier 4 | C106: 100 | D106: 100
B107: Tier 5 | C107: 200 | D107: 200
B108: Tier 6 | C108: 500 | D108: 500

Sheet Unit costs
B1: Unit costs
B2: These are calculated from Assumptions. They explain the slope of the bill. Shared free tiers are applied later, once per scenario, so they are not subtracted here.
B4: Per active CBO, each month
B5: Outbound SMS segments | C5: =subscribers_per_cbo*(checkins_per_year/12)*(opening_segments+followup_segments*completion_rate) | D5: Opening text for everyone, plus the three follow-ups only for people who finish.
B6: Inbound SMS segments | C6: =subscribers_per_cbo*(checkins_per_year/12)*inbound_segments_if_complete*completion_rate | D6: Replies from people who finish.
B7: Outbound SMS | C7: =sms_out_segments_per_cbo*price_kenya_sms | D7: This is the main per-CBO cost.
B8: Inbound SMS | C8: =sms_in_segments_per_cbo*price_inbound_sms | D8: Small, because replies hit a US number.
B9: Azure document reading | C9: =pages_per_cbo_month*price_azure_page | D9: Layout price per page times monthly pages.
B10: Gemini per document page | C10: =(doc_input_tokens/1000000)*price_gemini_in+(doc_output_tokens/1000000)*price_gemini_out | D10: Token price for one normalized page.
B11: Gemini on monthly documents | C11: =pages_per_cbo_month*gemini_doc_cost_per_page
B12: Research refreshes | C12: =30/refresh_days | D12: Share of CBOs refreshed in a typical month.
B13: Gemini on web research | C13: =refreshes_per_cbo_month*((research_input_tokens/1000000)*price_gemini_in+(research_output_tokens/1000000)*price_gemini_out) | D13: Does not include Google query fees. Those are shared and usually still free.
B14: Gemini on SMS replies | C14: =sms_in_segments_per_cbo*sms_ai_share*((sms_input_tokens/1000000)*price_gemini_in+(sms_output_tokens/1000000)*price_gemini_out) | D14: Only the share of replies marked as needing the model.
B15: Optional Claude | C15: =claude_per_cbo | D15: Zero unless you type a value on Assumptions.
B16: Variable cost of one more active CBO | C16: =sms_out_cost_per_cbo+sms_in_cost_per_cbo+azure_cost_per_cbo+gemini_doc_cost_per_cbo+gemini_research_cost_per_cbo+gemini_sms_cost_per_cbo+claude_cost_per_cbo | D16: Added every month. Storage, Firestore, Maps, and Cloud Run are extra only after a free allowance is used up.
B18: Per active funder, each month
B19: Gemini per marketplace search | C19: =((interpret_input_tokens+rank_input_tokens)/1000000)*price_gemini_in+((interpret_output_tokens+rank_output_tokens)/1000000)*price_gemini_out | D19: Interpret plus a capped ranking call.
B20: Gemini on that funder's searches | C20: =ai_searches_per_funder*gemini_cost_per_search
B21: Gemini on questions | C21: =questions_per_funder*((question_input_tokens/1000000)*price_gemini_in+(question_output_tokens/1000000)*price_gemini_out)
B22: OpenAI funding audits | C22: =audits_per_funder*((audit_input_tokens/1000000)*price_openai_in+(audit_output_tokens/1000000)*price_openai_out)
B23: Data transfer | C23: =(egress_mb_per_funder/1024)*price_egress_gb | D23: Before any included transfer, which this model sets at zero.
B24: Variable cost of one more active funder | C24: =gemini_search_cost_per_funder+gemini_question_cost_per_funder+openai_cost_per_funder+egress_cost_per_funder | D24: Map loads are free until the project passes 10,000 a month, so they are not in this slope.
B26: Platform floor, before usage
B27: Fixed fees | C27: =price_secrets+price_misc+price_phone_number*phone_numbers | D27: Number rental, secrets, domain, and a log buffer. Does not change with users.
B28: Floor while both sides are under the medium-database step | C28: =price_sql_micro+platform_fixed_fees+min_instances*price_warm_instance | D28: What you pay in a quiet month before SMS and documents.
B30: One-time cost to bring one CBO online
B31: Onboarding SMS | C31: =onboard_segments*price_kenya_sms | D31: One link text to the CBO leader. The form itself has no per-signup fee.
B32: First document batch | C32: =initial_pages*(price_azure_page+gemini_doc_cost_per_page) | D32: Azure plus Gemini for the signup backlog.
B33: First web-research pass | C33: =(research_input_tokens/1000000)*price_gemini_in+(research_output_tokens/1000000)*price_gemini_out | D33: Google queries for a few hundred signups still sit inside the free search quota.
B34: One-time total per new CBO | C34: =onboard_sms_per_cbo+initial_docs_per_cbo+initial_research_per_cbo | D34: Paid when they join. It does not repeat. The monthly cost starts on top of this.
B36: A quick reading: monthly cost is about the floor for that database size, plus the per-CBO amount times CBOs, plus the per-funder amount times funders. The scenario sheets are exact, because they also apply free tiers and the database step.

Sheet Scenarios
A1: Every combination
A2: One row is one live month at that size. Totals sum the component columns. Change a yellow input and this table follows.
A4: Scale | C4: Hosting | I4: SMS | K4: Documents and research | N4: Funder intelligence | S4: Maps and search | V4: Totals | AA4: Allowance used
A5: Active CBOs | B5: Active funders | C5: Database | D5: Fixed fees | E5: Cloud Run | F5: File storage | G5: Data transfer | H5: Firestore | I5: SMS to Kenya | J5: SMS replies | K5: Azure pages | L5: Gemini documents | M5: Gemini research | N5: Gemini search | O5: Gemini questions | P5: Gemini SMS | Q5: OpenAI audits | R5: Claude | S5: Web search | T5: Map loads | U5: Geocoding | V5: Monthly total | W5: Annual total | X5: Per CBO | Y5: SMS share | Z5: Hosting share | AA5: Map loads used | AB5: Search queries | AC5: vCPU-seconds | AD5: vCPU left in free tier
A6: =cbo_tier_1 | B6: =funder_tier_1 | C6: =IF(OR(A6>=step_std_at,B6>=step_std_at),price_sql_std,IF(OR(A6>=step_small_at,B6>=step_small_at),price_sql_small,price_sql_micro)) | D6: =platform_fixed_fees | E6: =MAX(0,AC6-free_vcpu)*price_vcpu+MAX(0,AC6*memory_gib-free_gib)*price_gib+MAX(0,(A6*cbo_http_requests+B6*funder_http_requests+A6*sms_in_segments_per_cbo)-free_requests)/1000000*price_million_requests+min_instances*price_warm_instance | F6: =MAX(0,A6*storage_mb_per_cbo/1024-free_storage_gb)*price_storage_gb | G6: =MAX(0,B6*egress_mb_per_funder/1024-free_egress_gb)*price_egress_gb | H6: =MAX(0,A6*firestore_writes_per_cbo-free_fs_writes)/100000*price_fs_write+MAX(0,A6*firestore_reads_per_cbo-free_fs_reads)/100000*price_fs_read | I6: =A6*sms_out_cost_per_cbo | J6: =A6*sms_in_cost_per_cbo | K6: =A6*azure_cost_per_cbo | L6: =A6*gemini_doc_cost_per_cbo | M6: =A6*gemini_research_cost_per_cbo | N6: =B6*gemini_search_cost_per_funder | O6: =B6*gemini_question_cost_per_funder | P6: =A6*gemini_sms_cost_per_cbo | Q6: =B6*openai_cost_per_funder | R6: =A6*claude_cost_per_cbo | S6: =MAX(0,AB6-free_search)/1000*price_search_1k | T6: =MAX(0,AA6-free_maps)/1000*price_map_1k | U6: =MAX(0,A6*geocode_updates_per_cbo-free_geocode)/1000*price_geocode_1k | V6: =SUM(C6:U6) | W6: =V6*12 | X6: =IF(A6=0,NA(),V6/A6) | Y6: =IF(V6=0,0,(I6+J6)/V6) | Z6: =IF(V6=0,0,SUM(C6:H6)/V6) | AA6: =B6*map_loads_per_funder | AB6: =A6*refreshes_per_cbo_month*searches_per_refresh+B6*audits_per_funder*searches_per_audit | AC6: =(A6*cbo_http_requests+B6*funder_http_requests+A6*sms_in_segments_per_cbo)*request_vcpu_seconds+A6*pages_per_cbo_month*page_vcpu_seconds | AD6: =free_vcpu-AC6
A7: =cbo_tier_1 | B7: =funder_tier_2 | C7: =IF(OR(A7>=step_std_at,B7>=step_std_at),price_sql_std,IF(OR(A7>=step_small_at,B7>=step_small_at),price_sql_small,price_sql_micro)) | D7: =platform_fixed_fees | E7: =MAX(0,AC7-free_vcpu)*price_vcpu+MAX(0,AC7*memory_gib-free_gib)*price_gib+MAX(0,(A7*cbo_http_requests+B7*funder_http_requests+A7*sms_in_segments_per_cbo)-free_requests)/1000000*price_million_requests+min_instances*price_warm_instance | F7: =MAX(0,A7*storage_mb_per_cbo/1024-free_storage_gb)*price_storage_gb | G7: =MAX(0,B7*egress_mb_per_funder/1024-free_egress_gb)*price_egress_gb | H7: =MAX(0,A7*firestore_writes_per_cbo-free_fs_writes)/100000*price_fs_write+MAX(0,A7*firestore_reads_per_cbo-free_fs_reads)/100000*price_fs_read | I7: =A7*sms_out_cost_per_cbo | J7: =A7*sms_in_cost_per_cbo | K7: =A7*azure_cost_per_cbo | L7: =A7*gemini_doc_cost_per_cbo | M7: =A7*gemini_research_cost_per_cbo | N7: =B7*gemini_search_cost_per_funder | O7: =B7*gemini_question_cost_per_funder | P7: =A7*gemini_sms_cost_per_cbo | Q7: =B7*openai_cost_per_funder | R7: =A7*claude_cost_per_cbo | S7: =MAX(0,AB7-free_search)/1000*price_search_1k | T7: =MAX(0,AA7-free_maps)/1000*price_map_1k | U7: =MAX(0,A7*geocode_updates_per_cbo-free_geocode)/1000*price_geocode_1k | V7: =SUM(C7:U7) | W7: =V7*12 | X7: =IF(A7=0,NA(),V7/A7) | Y7: =IF(V7=0,0,(I7+J7)/V7) | Z7: =IF(V7=0,0,SUM(C7:H7)/V7) | AA7: =B7*map_loads_per_funder | AB7: =A7*refreshes_per_cbo_month*searches_per_refresh+B7*audits_per_funder*searches_per_audit | AC7: =(A7*cbo_http_requests+B7*funder_http_requests+A7*sms_in_segments_per_cbo)*request_vcpu_seconds+A7*pages_per_cbo_month*page_vcpu_seconds | AD7: =free_vcpu-AC7
A8: =cbo_tier_1 | B8: =funder_tier_3 | C8: =IF(OR(A8>=step_std_at,B8>=step_std_at),price_sql_std,IF(OR(A8>=step_small_at,B8>=step_small_at),price_sql_small,price_sql_micro)) | D8: =platform_fixed_fees | E8: =MAX(0,AC8-free_vcpu)*price_vcpu+MAX(0,AC8*memory_gib-free_gib)*price_gib+MAX(0,(A8*cbo_http_requests+B8*funder_http_requests+A8*sms_in_segments_per_cbo)-free_requests)/1000000*price_million_requests+min_instances*price_warm_instance | F8: =MAX(0,A8*storage_mb_per_cbo/1024-free_storage_gb)*price_storage_gb | G8: =MAX(0,B8*egress_mb_per_funder/1024-free_egress_gb)*price_egress_gb | H8: =MAX(0,A8*firestore_writes_per_cbo-free_fs_writes)/100000*price_fs_write+MAX(0,A8*firestore_reads_per_cbo-free_fs_reads)/100000*price_fs_read | I8: =A8*sms_out_cost_per_cbo | J8: =A8*sms_in_cost_per_cbo | K8: =A8*azure_cost_per_cbo | L8: =A8*gemini_doc_cost_per_cbo | M8: =A8*gemini_research_cost_per_cbo | N8: =B8*gemini_search_cost_per_funder | O8: =B8*gemini_question_cost_per_funder | P8: =A8*gemini_sms_cost_per_cbo | Q8: =B8*openai_cost_per_funder | R8: =A8*claude_cost_per_cbo | S8: =MAX(0,AB8-free_search)/1000*price_search_1k | T8: =MAX(0,AA8-free_maps)/1000*price_map_1k | U8: =MAX(0,A8*geocode_updates_per_cbo-free_geocode)/1000*price_geocode_1k | V8: =SUM(C8:U8) | W8: =V8*12 | X8: =IF(A8=0,NA(),V8/A8) | Y8: =IF(V8=0,0,(I8+J8)/V8) | Z8: =IF(V8=0,0,SUM(C8:H8)/V8) | AA8: =B8*map_loads_per_funder | AB8: =A8*refreshes_per_cbo_month*searches_per_refresh+B8*audits_per_funder*searches_per_audit | AC8: =(A8*cbo_http_requests+B8*funder_http_requests+A8*sms_in_segments_per_cbo)*request_vcpu_seconds+A8*pages_per_cbo_month*page_vcpu_seconds | AD8: =free_vcpu-AC8
A9: =cbo_tier_1 | B9: =funder_tier_4 | C9: =IF(OR(A9>=step_std_at,B9>=step_std_at),price_sql_std,IF(OR(A9>=step_small_at,B9>=step_small_at),price_sql_small,price_sql_micro)) | D9: =platform_fixed_fees | E9: =MAX(0,AC9-free_vcpu)*price_vcpu+MAX(0,AC9*memory_gib-free_gib)*price_gib+MAX(0,(A9*cbo_http_requests+B9*funder_http_requests+A9*sms_in_segments_per_cbo)-free_requests)/1000000*price_million_requests+min_instances*price_warm_instance | F9: =MAX(0,A9*storage_mb_per_cbo/1024-free_storage_gb)*price_storage_gb | G9: =MAX(0,B9*egress_mb_per_funder/1024-free_egress_gb)*price_egress_gb | H9: =MAX(0,A9*firestore_writes_per_cbo-free_fs_writes)/100000*price_fs_write+MAX(0,A9*firestore_reads_per_cbo-free_fs_reads)/100000*price_fs_read | I9: =A9*sms_out_cost_per_cbo | J9: =A9*sms_in_cost_per_cbo | K9: =A9*azure_cost_per_cbo | L9: =A9*gemini_doc_cost_per_cbo | M9: =A9*gemini_research_cost_per_cbo | N9: =B9*gemini_search_cost_per_funder | O9: =B9*gemini_question_cost_per_funder | P9: =A9*gemini_sms_cost_per_cbo | Q9: =B9*openai_cost_per_funder | R9: =A9*claude_cost_per_cbo | S9: =MAX(0,AB9-free_search)/1000*price_search_1k | T9: =MAX(0,AA9-free_maps)/1000*price_map_1k | U9: =MAX(0,A9*geocode_updates_per_cbo-free_geocode)/1000*price_geocode_1k | V9: =SUM(C9:U9) | W9: =V9*12 | X9: =IF(A9=0,NA(),V9/A9) | Y9: =IF(V9=0,0,(I9+J9)/V9) | Z9: =IF(V9=0,0,SUM(C9:H9)/V9) | AA9: =B9*map_loads_per_funder | AB9: =A9*refreshes_per_cbo_month*searches_per_refresh+B9*audits_per_funder*searches_per_audit | AC9: =(A9*cbo_http_requests+B9*funder_http_requests+A9*sms_in_segments_per_cbo)*request_vcpu_seconds+A9*pages_per_cbo_month*page_vcpu_seconds | AD9: =free_vcpu-AC9
A10: =cbo_tier_1 | B10: =funder_tier_5 | C10: =IF(OR(A10>=step_std_at,B10>=step_std_at),price_sql_std,IF(OR(A10>=step_small_at,B10>=step_small_at),price_sql_small,price_sql_micro)) | D10: =platform_fixed_fees | E10: =MAX(0,AC10-free_vcpu)*price_vcpu+MAX(0,AC10*memory_gib-free_gib)*price_gib+MAX(0,(A10*cbo_http_requests+B10*funder_http_requests+A10*sms_in_segments_per_cbo)-free_requests)/1000000*price_million_requests+min_instances*price_warm_instance | F10: =MAX(0,A10*storage_mb_per_cbo/1024-free_storage_gb)*price_storage_gb | G10: =MAX(0,B10*egress_mb_per_funder/1024-free_egress_gb)*price_egress_gb | H10: =MAX(0,A10*firestore_writes_per_cbo-free_fs_writes)/100000*price_fs_write+MAX(0,A10*firestore_reads_per_cbo-free_fs_reads)/100000*price_fs_read | I10: =A10*sms_out_cost_per_cbo | J10: =A10*sms_in_cost_per_cbo | K10: =A10*azure_cost_per_cbo | L10: =A10*gemini_doc_cost_per_cbo | M10: =A10*gemini_research_cost_per_cbo | N10: =B10*gemini_search_cost_per_funder | O10: =B10*gemini_question_cost_per_funder | P10: =A10*gemini_sms_cost_per_cbo | Q10: =B10*openai_cost_per_funder | R10: =A10*claude_cost_per_cbo | S10: =MAX(0,AB10-free_search)/1000*price_search_1k | T10: =MAX(0,AA10-free_maps)/1000*price_map_1k | U10: =MAX(0,A10*geocode_updates_per_cbo-free_geocode)/1000*price_geocode_1k | V10: =SUM(C10:U10) | W10: =V10*12 | X10: =IF(A10=0,NA(),V10/A10) | Y10: =IF(V10=0,0,(I10+J10)/V10) | Z10: =IF(V10=0,0,SUM(C10:H10)/V10) | AA10: =B10*map_loads_per_funder | AB10: =A10*refreshes_per_cbo_month*searches_per_refresh+B10*audits_per_funder*searches_per_audit | AC10: =(A10*cbo_http_requests+B10*funder_http_requests+A10*sms_in_segments_per_cbo)*request_vcpu_seconds+A10*pages_per_cbo_month*page_vcpu_seconds | AD10: =free_vcpu-AC10
A11: =cbo_tier_1 | B11: =funder_tier_6 | C11: =IF(OR(A11>=step_std_at,B11>=step_std_at),price_sql_std,IF(OR(A11>=step_small_at,B11>=step_small_at),price_sql_small,price_sql_micro)) | D11: =platform_fixed_fees | E11: =MAX(0,AC11-free_vcpu)*price_vcpu+MAX(0,AC11*memory_gib-free_gib)*price_gib+MAX(0,(A11*cbo_http_requests+B11*funder_http_requests+A11*sms_in_segments_per_cbo)-free_requests)/1000000*price_million_requests+min_instances*price_warm_instance | F11: =MAX(0,A11*storage_mb_per_cbo/1024-free_storage_gb)*price_storage_gb | G11: =MAX(0,B11*egress_mb_per_funder/1024-free_egress_gb)*price_egress_gb | H11: =MAX(0,A11*firestore_writes_per_cbo-free_fs_writes)/100000*price_fs_write+MAX(0,A11*firestore_reads_per_cbo-free_fs_reads)/100000*price_fs_read | I11: =A11*sms_out_cost_per_cbo | J11: =A11*sms_in_cost_per_cbo | K11: =A11*azure_cost_per_cbo | L11: =A11*gemini_doc_cost_per_cbo | M11: =A11*gemini_research_cost_per_cbo | N11: =B11*gemini_search_cost_per_funder | O11: =B11*gemini_question_cost_per_funder | P11: =A11*gemini_sms_cost_per_cbo | Q11: =B11*openai_cost_per_funder | R11: =A11*claude_cost_per_cbo | S11: =MAX(0,AB11-free_search)/1000*price_search_1k | T11: =MAX(0,AA11-free_maps)/1000*price_map_1k | U11: =MAX(0,A11*geocode_updates_per_cbo-free_geocode)/1000*price_geocode_1k | V11: =SUM(C11:U11) | W11: =V11*12 | X11: =IF(A11=0,NA(),V11/A11) | Y11: =IF(V11=0,0,(I11+J11)/V11) | Z11: =IF(V11=0,0,SUM(C11:H11)/V11) | AA11: =B11*map_loads_per_funder | AB11: =A11*refreshes_per_cbo_month*searches_per_refresh+B11*audits_per_funder*searches_per_audit | AC11: =(A11*cbo_http_requests+B11*funder_http_requests+A11*sms_in_segments_per_cbo)*request_vcpu_seconds+A11*pages_per_cbo_month*page_vcpu_seconds | AD11: =free_vcpu-AC11
A12: =cbo_tier_2 | B12: =funder_tier_1 | C12: =IF(OR(A12>=step_std_at,B12>=step_std_at),price_sql_std,IF(OR(A12>=step_small_at,B12>=step_small_at),price_sql_small,price_sql_micro)) | D12: =platform_fixed_fees | E12: =MAX(0,AC12-free_vcpu)*price_vcpu+MAX(0,AC12*memory_gib-free_gib)*price_gib+MAX(0,(A12*cbo_http_requests+B12*funder_http_requests+A12*sms_in_segments_per_cbo)-free_requests)/1000000*price_million_requests+min_instances*price_warm_instance | F12: =MAX(0,A12*storage_mb_per_cbo/1024-free_storage_gb)*price_storage_gb | G12: =MAX(0,B12*egress_mb_per_funder/1024-free_egress_gb)*price_egress_gb | H12: =MAX(0,A12*firestore_writes_per_cbo-free_fs_writes)/100000*price_fs_write+MAX(0,A12*firestore_reads_per_cbo-free_fs_reads)/100000*price_fs_read | I12: =A12*sms_out_cost_per_cbo | J12: =A12*sms_in_cost_per_cbo | K12: =A12*azure_cost_per_cbo | L12: =A12*gemini_doc_cost_per_cbo | M12: =A12*gemini_research_cost_per_cbo | N12: =B12*gemini_search_cost_per_funder | O12: =B12*gemini_question_cost_per_funder | P12: =A12*gemini_sms_cost_per_cbo | Q12: =B12*openai_cost_per_funder | R12: =A12*claude_cost_per_cbo | S12: =MAX(0,AB12-free_search)/1000*price_search_1k | T12: =MAX(0,AA12-free_maps)/1000*price_map_1k | U12: =MAX(0,A12*geocode_updates_per_cbo-free_geocode)/1000*price_geocode_1k | V12: =SUM(C12:U12) | W12: =V12*12 | X12: =IF(A12=0,NA(),V12/A12) | Y12: =IF(V12=0,0,(I12+J12)/V12) | Z12: =IF(V12=0,0,SUM(C12:H12)/V12) | AA12: =B12*map_loads_per_funder | AB12: =A12*refreshes_per_cbo_month*searches_per_refresh+B12*audits_per_funder*searches_per_audit | AC12: =(A12*cbo_http_requests+B12*funder_http_requests+A12*sms_in_segments_per_cbo)*request_vcpu_seconds+A12*pages_per_cbo_month*page_vcpu_seconds | AD12: =free_vcpu-AC12
A13: =cbo_tier_2 | B13: =funder_tier_2 | C13: =IF(OR(A13>=step_std_at,B13>=step_std_at),price_sql_std,IF(OR(A13>=step_small_at,B13>=step_small_at),price_sql_small,price_sql_micro)) | D13: =platform_fixed_fees | E13: =MAX(0,AC13-free_vcpu)*price_vcpu+MAX(0,AC13*memory_gib-free_gib)*price_gib+MAX(0,(A13*cbo_http_requests+B13*funder_http_requests+A13*sms_in_segments_per_cbo)-free_requests)/1000000*price_million_requests+min_instances*price_warm_instance | F13: =MAX(0,A13*storage_mb_per_cbo/1024-free_storage_gb)*price_storage_gb | G13: =MAX(0,B13*egress_mb_per_funder/1024-free_egress_gb)*price_egress_gb | H13: =MAX(0,A13*firestore_writes_per_cbo-free_fs_writes)/100000*price_fs_write+MAX(0,A13*firestore_reads_per_cbo-free_fs_reads)/100000*price_fs_read | I13: =A13*sms_out_cost_per_cbo | J13: =A13*sms_in_cost_per_cbo | K13: =A13*azure_cost_per_cbo | L13: =A13*gemini_doc_cost_per_cbo | M13: =A13*gemini_research_cost_per_cbo | N13: =B13*gemini_search_cost_per_funder | O13: =B13*gemini_question_cost_per_funder | P13: =A13*gemini_sms_cost_per_cbo | Q13: =B13*openai_cost_per_funder | R13: =A13*claude_cost_per_cbo | S13: =MAX(0,AB13-free_search)/1000*price_search_1k | T13: =MAX(0,AA13-free_maps)/1000*price_map_1k | U13: =MAX(0,A13*geocode_updates_per_cbo-free_geocode)/1000*price_geocode_1k | V13: =SUM(C13:U13) | W13: =V13*12 | X13: =IF(A13=0,NA(),V13/A13) | Y13: =IF(V13=0,0,(I13+J13)/V13) | Z13: =IF(V13=0,0,SUM(C13:H13)/V13) | AA13: =B13*map_loads_per_funder | AB13: =A13*refreshes_per_cbo_month*searches_per_refresh+B13*audits_per_funder*searches_per_audit | AC13: =(A13*cbo_http_requests+B13*funder_http_requests+A13*sms_in_segments_per_cbo)*request_vcpu_seconds+A13*pages_per_cbo_month*page_vcpu_seconds | AD13: =free_vcpu-AC13
A14: =cbo_tier_2 | B14: =funder_tier_3 | C14: =IF(OR(A14>=step_std_at,B14>=step_std_at),price_sql_std,IF(OR(A14>=step_small_at,B14>=step_small_at),price_sql_small,price_sql_micro)) | D14: =platform_fixed_fees | E14: =MAX(0,AC14-free_vcpu)*price_vcpu+MAX(0,AC14*memory_gib-free_gib)*price_gib+MAX(0,(A14*cbo_http_requests+B14*funder_http_requests+A14*sms_in_segments_per_cbo)-free_requests)/1000000*price_million_requests+min_instances*price_warm_instance | F14: =MAX(0,A14*storage_mb_per_cbo/1024-free_storage_gb)*price_storage_gb | G14: =MAX(0,B14*egress_mb_per_funder/1024-free_egress_gb)*price_egress_gb | H14: =MAX(0,A14*firestore_writes_per_cbo-free_fs_writes)/100000*price_fs_write+MAX(0,A14*firestore_reads_per_cbo-free_fs_reads)/100000*price_fs_read | I14: =A14*sms_out_cost_per_cbo | J14: =A14*sms_in_cost_per_cbo | K14: =A14*azure_cost_per_cbo | L14: =A14*gemini_doc_cost_per_cbo | M14: =A14*gemini_research_cost_per_cbo | N14: =B14*gemini_search_cost_per_funder | O14: =B14*gemini_question_cost_per_funder | P14: =A14*gemini_sms_cost_per_cbo | Q14: =B14*openai_cost_per_funder | R14: =A14*claude_cost_per_cbo | S14: =MAX(0,AB14-free_search)/1000*price_search_1k | T14: =MAX(0,AA14-free_maps)/1000*price_map_1k | U14: =MAX(0,A14*geocode_updates_per_cbo-free_geocode)/1000*price_geocode_1k | V14: =SUM(C14:U14) | W14: =V14*12 | X14: =IF(A14=0,NA(),V14/A14) | Y14: =IF(V14=0,0,(I14+J14)/V14) | Z14: =IF(V14=0,0,SUM(C14:H14)/V14) | AA14: =B14*map_loads_per_funder | AB14: =A14*refreshes_per_cbo_month*searches_per_refresh+B14*audits_per_funder*searches_per_audit | AC14: =(A14*cbo_http_requests+B14*funder_http_requests+A14*sms_in_segments_per_cbo)*request_vcpu_seconds+A14*pages_per_cbo_month*page_vcpu_seconds | AD14: =free_vcpu-AC14
A15: =cbo_tier_2 | B15: =funder_tier_4 | C15: =IF(OR(A15>=step_std_at,B15>=step_std_at),price_sql_std,IF(OR(A15>=step_small_at,B15>=step_small_at),price_sql_small,price_sql_micro)) | D15: =platform_fixed_fees | E15: =MAX(0,AC15-free_vcpu)*price_vcpu+MAX(0,AC15*memory_gib-free_gib)*price_gib+MAX(0,(A15*cbo_http_requests+B15*funder_http_requests+A15*sms_in_segments_per_cbo)-free_requests)/1000000*price_million_requests+min_instances*price_warm_instance | F15: =MAX(0,A15*storage_mb_per_cbo/1024-free_storage_gb)*price_storage_gb | G15: =MAX(0,B15*egress_mb_per_funder/1024-free_egress_gb)*price_egress_gb | H15: =MAX(0,A15*firestore_writes_per_cbo-free_fs_writes)/100000*price_fs_write+MAX(0,A15*firestore_reads_per_cbo-free_fs_reads)/100000*price_fs_read | I15: =A15*sms_out_cost_per_cbo | J15: =A15*sms_in_cost_per_cbo | K15: =A15*azure_cost_per_cbo | L15: =A15*gemini_doc_cost_per_cbo | M15: =A15*gemini_research_cost_per_cbo | N15: =B15*gemini_search_cost_per_funder | O15: =B15*gemini_question_cost_per_funder | P15: =A15*gemini_sms_cost_per_cbo | Q15: =B15*openai_cost_per_funder | R15: =A15*claude_cost_per_cbo | S15: =MAX(0,AB15-free_search)/1000*price_search_1k | T15: =MAX(0,AA15-free_maps)/1000*price_map_1k | U15: =MAX(0,A15*geocode_updates_per_cbo-free_geocode)/1000*price_geocode_1k | V15: =SUM(C15:U15) | W15: =V15*12 | X15: =IF(A15=0,NA(),V15/A15) | Y15: =IF(V15=0,0,(I15+J15)/V15) | Z15: =IF(V15=0,0,SUM(C15:H15)/V15) | AA15: =B15*map_loads_per_funder | AB15: =A15*refreshes_per_cbo_month*searches_per_refresh+B15*audits_per_funder*searches_per_audit | AC15: =(A15*cbo_http_requests+B15*funder_http_requests+A15*sms_in_segments_per_cbo)*request_vcpu_seconds+A15*pages_per_cbo_month*page_vcpu_seconds | AD15: =free_vcpu-AC15
A16: =cbo_tier_2 | B16: =funder_tier_5 | C16: =IF(OR(A16>=step_std_at,B16>=step_std_at),price_sql_std,IF(OR(A16>=step_small_at,B16>=step_small_at),price_sql_small,price_sql_micro)) | D16: =platform_fixed_fees | E16: =MAX(0,AC16-free_vcpu)*price_vcpu+MAX(0,AC16*memory_gib-free_gib)*price_gib+MAX(0,(A16*cbo_http_requests+B16*funder_http_requests+A16*sms_in_segments_per_cbo)-free_requests)/1000000*price_million_requests+min_instances*price_warm_instance | F16: =MAX(0,A16*storage_mb_per_cbo/1024-free_storage_gb)*price_storage_gb | G16: =MAX(0,B16*egress_mb_per_funder/1024-free_egress_gb)*price_egress_gb | H16: =MAX(0,A16*firestore_writes_per_cbo-free_fs_writes)/100000*price_fs_write+MAX(0,A16*firestore_reads_per_cbo-free_fs_reads)/100000*price_fs_read | I16: =A16*sms_out_cost_per_cbo | J16: =A16*sms_in_cost_per_cbo | K16: =A16*azure_cost_per_cbo | L16: =A16*gemini_doc_cost_per_cbo | M16: =A16*gemini_research_cost_per_cbo | N16: =B16*gemini_search_cost_per_funder | O16: =B16*gemini_question_cost_per_funder | P16: =A16*gemini_sms_cost_per_cbo | Q16: =B16*openai_cost_per_funder | R16: =A16*claude_cost_per_cbo | S16: =MAX(0,AB16-free_search)/1000*price_search_1k | T16: =MAX(0,AA16-free_maps)/1000*price_map_1k | U16: =MAX(0,A16*geocode_updates_per_cbo-free_geocode)/1000*price_geocode_1k | V16: =SUM(C16:U16) | W16: =V16*12 | X16: =IF(A16=0,NA(),V16/A16) | Y16: =IF(V16=0,0,(I16+J16)/V16) | Z16: =IF(V16=0,0,SUM(C16:H16)/V16) | AA16: =B16*map_loads_per_funder | AB16: =A16*refreshes_per_cbo_month*searches_per_refresh+B16*audits_per_funder*searches_per_audit | AC16: =(A16*cbo_http_requests+B16*funder_http_requests+A16*sms_in_segments_per_cbo)*request_vcpu_seconds+A16*pages_per_cbo_month*page_vcpu_seconds | AD16: =free_vcpu-AC16
A17: =cbo_tier_2 | B17: =funder_tier_6 | C17: =IF(OR(A17>=step_std_at,B17>=step_std_at),price_sql_std,IF(OR(A17>=step_small_at,B17>=step_small_at),price_sql_small,price_sql_micro)) | D17: =platform_fixed_fees | E17: =MAX(0,AC17-free_vcpu)*price_vcpu+MAX(0,AC17*memory_gib-free_gib)*price_gib+MAX(0,(A17*cbo_http_requests+B17*funder_http_requests+A17*sms_in_segments_per_cbo)-free_requests)/1000000*price_million_requests+min_instances*price_warm_instance | F17: =MAX(0,A17*storage_mb_per_cbo/1024-free_storage_gb)*price_storage_gb | G17: =MAX(0,B17*egress_mb_per_funder/1024-free_egress_gb)*price_egress_gb | H17: =MAX(0,A17*firestore_writes_per_cbo-free_fs_writes)/100000*price_fs_write+MAX(0,A17*firestore_reads_per_cbo-free_fs_reads)/100000*price_fs_read | I17: =A17*sms_out_cost_per_cbo | J17: =A17*sms_in_cost_per_cbo | K17: =A17*azure_cost_per_cbo | L17: =A17*gemini_doc_cost_per_cbo | M17: =A17*gemini_research_cost_per_cbo | N17: =B17*gemini_search_cost_per_funder | O17: =B17*gemini_question_cost_per_funder | P17: =A17*gemini_sms_cost_per_cbo | Q17: =B17*openai_cost_per_funder | R17: =A17*claude_cost_per_cbo | S17: =MAX(0,AB17-free_search)/1000*price_search_1k | T17: =MAX(0,AA17-free_maps)/1000*price_map_1k | U17: =MAX(0,A17*geocode_updates_per_cbo-free_geocode)/1000*price_geocode_1k | V17: =SUM(C17:U17) | W17: =V17*12 | X17: =IF(A17=0,NA(),V17/A17) | Y17: =IF(V17=0,0,(I17+J17)/V17) | Z17: =IF(V17=0,0,SUM(C17:H17)/V17) | AA17: =B17*map_loads_per_funder | AB17: =A17*refreshes_per_cbo_month*searches_per_refresh+B17*audits_per_funder*searches_per_audit | AC17: =(A17*cbo_http_requests+B17*funder_http_requests+A17*sms_in_segments_per_cbo)*request_vcpu_seconds+A17*pages_per_cbo_month*page_vcpu_seconds | AD17: =free_vcpu-AC17
A18: =cbo_tier_3 | B18: =funder_tier_1 | C18: =IF(OR(A18>=step_std_at,B18>=step_std_at),price_sql_std,IF(OR(A18>=step_small_at,B18>=step_small_at),price_sql_small,price_sql_micro)) | D18: =platform_fixed_fees | E18: =MAX(0,AC18-free_vcpu)*price_vcpu+MAX(0,AC18*memory_gib-free_gib)*price_gib+MAX(0,(A18*cbo_http_requests+B18*funder_http_requests+A18*sms_in_segments_per_cbo)-free_requests)/1000000*price_million_requests+min_instances*price_warm_instance | F18: =MAX(0,A18*storage_mb_per_cbo/1024-free_storage_gb)*price_storage_gb | G18: =MAX(0,B18*egress_mb_per_funder/1024-free_egress_gb)*price_egress_gb | H18: =MAX(0,A18*firestore_writes_per_cbo-free_fs_writes)/100000*price_fs_write+MAX(0,A18*firestore_reads_per_cbo-free_fs_reads)/100000*price_fs_read | I18: =A18*sms_out_cost_per_cbo | J18: =A18*sms_in_cost_per_cbo | K18: =A18*azure_cost_per_cbo | L18: =A18*gemini_doc_cost_per_cbo | M18: =A18*gemini_research_cost_per_cbo | N18: =B18*gemini_search_cost_per_funder | O18: =B18*gemini_question_cost_per_funder | P18: =A18*gemini_sms_cost_per_cbo | Q18: =B18*openai_cost_per_funder | R18: =A18*claude_cost_per_cbo | S18: =MAX(0,AB18-free_search)/1000*price_search_1k | T18: =MAX(0,AA18-free_maps)/1000*price_map_1k | U18: =MAX(0,A18*geocode_updates_per_cbo-free_geocode)/1000*price_geocode_1k | V18: =SUM(C18:U18) | W18: =V18*12 | X18: =IF(A18=0,NA(),V18/A18) | Y18: =IF(V18=0,0,(I18+J18)/V18) | Z18: =IF(V18=0,0,SUM(C18:H18)/V18) | AA18: =B18*map_loads_per_funder | AB18: =A18*refreshes_per_cbo_month*searches_per_refresh+B18*audits_per_funder*searches_per_audit | AC18: =(A18*cbo_http_requests+B18*funder_http_requests+A18*sms_in_segments_per_cbo)*request_vcpu_seconds+A18*pages_per_cbo_month*page_vcpu_seconds | AD18: =free_vcpu-AC18
A19: =cbo_tier_3 | B19: =funder_tier_2 | C19: =IF(OR(A19>=step_std_at,B19>=step_std_at),price_sql_std,IF(OR(A19>=step_small_at,B19>=step_small_at),price_sql_small,price_sql_micro)) | D19: =platform_fixed_fees | E19: =MAX(0,AC19-free_vcpu)*price_vcpu+MAX(0,AC19*memory_gib-free_gib)*price_gib+MAX(0,(A19*cbo_http_requests+B19*funder_http_requests+A19*sms_in_segments_per_cbo)-free_requests)/1000000*price_million_requests+min_instances*price_warm_instance | F19: =MAX(0,A19*storage_mb_per_cbo/1024-free_storage_gb)*price_storage_gb | G19: =MAX(0,B19*egress_mb_per_funder/1024-free_egress_gb)*price_egress_gb | H19: =MAX(0,A19*firestore_writes_per_cbo-free_fs_writes)/100000*price_fs_write+MAX(0,A19*firestore_reads_per_cbo-free_fs_reads)/100000*price_fs_read | I19: =A19*sms_out_cost_per_cbo | J19: =A19*sms_in_cost_per_cbo | K19: =A19*azure_cost_per_cbo | L19: =A19*gemini_doc_cost_per_cbo | M19: =A19*gemini_research_cost_per_cbo | N19: =B19*gemini_search_cost_per_funder | O19: =B19*gemini_question_cost_per_funder | P19: =A19*gemini_sms_cost_per_cbo | Q19: =B19*openai_cost_per_funder | R19: =A19*claude_cost_per_cbo | S19: =MAX(0,AB19-free_search)/1000*price_search_1k | T19: =MAX(0,AA19-free_maps)/1000*price_map_1k | U19: =MAX(0,A19*geocode_updates_per_cbo-free_geocode)/1000*price_geocode_1k | V19: =SUM(C19:U19) | W19: =V19*12 | X19: =IF(A19=0,NA(),V19/A19) | Y19: =IF(V19=0,0,(I19+J19)/V19) | Z19: =IF(V19=0,0,SUM(C19:H19)/V19) | AA19: =B19*map_loads_per_funder | AB19: =A19*refreshes_per_cbo_month*searches_per_refresh+B19*audits_per_funder*searches_per_audit | AC19: =(A19*cbo_http_requests+B19*funder_http_requests+A19*sms_in_segments_per_cbo)*request_vcpu_seconds+A19*pages_per_cbo_month*page_vcpu_seconds | AD19: =free_vcpu-AC19
A20: =cbo_tier_3 | B20: =funder_tier_3 | C20: =IF(OR(A20>=step_std_at,B20>=step_std_at),price_sql_std,IF(OR(A20>=step_small_at,B20>=step_small_at),price_sql_small,price_sql_micro)) | D20: =platform_fixed_fees | E20: =MAX(0,AC20-free_vcpu)*price_vcpu+MAX(0,AC20*memory_gib-free_gib)*price_gib+MAX(0,(A20*cbo_http_requests+B20*funder_http_requests+A20*sms_in_segments_per_cbo)-free_requests)/1000000*price_million_requests+min_instances*price_warm_instance | F20: =MAX(0,A20*storage_mb_per_cbo/1024-free_storage_gb)*price_storage_gb | G20: =MAX(0,B20*egress_mb_per_funder/1024-free_egress_gb)*price_egress_gb | H20: =MAX(0,A20*firestore_writes_per_cbo-free_fs_writes)/100000*price_fs_write+MAX(0,A20*firestore_reads_per_cbo-free_fs_reads)/100000*price_fs_read | I20: =A20*sms_out_cost_per_cbo | J20: =A20*sms_in_cost_per_cbo | K20: =A20*azure_cost_per_cbo | L20: =A20*gemini_doc_cost_per_cbo | M20: =A20*gemini_research_cost_per_cbo | N20: =B20*gemini_search_cost_per_funder | O20: =B20*gemini_question_cost_per_funder | P20: =A20*gemini_sms_cost_per_cbo | Q20: =B20*openai_cost_per_funder | R20: =A20*claude_cost_per_cbo | S20: =MAX(0,AB20-free_search)/1000*price_search_1k | T20: =MAX(0,AA20-free_maps)/1000*price_map_1k | U20: =MAX(0,A20*geocode_updates_per_cbo-free_geocode)/1000*price_geocode_1k | V20: =SUM(C20:U20) | W20: =V20*12 | X20: =IF(A20=0,NA(),V20/A20) | Y20: =IF(V20=0,0,(I20+J20)/V20) | Z20: =IF(V20=0,0,SUM(C20:H20)/V20) | AA20: =B20*map_loads_per_funder | AB20: =A20*refreshes_per_cbo_month*searches_per_refresh+B20*audits_per_funder*searches_per_audit | AC20: =(A20*cbo_http_requests+B20*funder_http_requests+A20*sms_in_segments_per_cbo)*request_vcpu_seconds+A20*pages_per_cbo_month*page_vcpu_seconds | AD20: =free_vcpu-AC20
A21: =cbo_tier_3 | B21: =funder_tier_4 | C21: =IF(OR(A21>=step_std_at,B21>=step_std_at),price_sql_std,IF(OR(A21>=step_small_at,B21>=step_small_at),price_sql_small,price_sql_micro)) | D21: =platform_fixed_fees | E21: =MAX(0,AC21-free_vcpu)*price_vcpu+MAX(0,AC21*memory_gib-free_gib)*price_gib+MAX(0,(A21*cbo_http_requests+B21*funder_http_requests+A21*sms_in_segments_per_cbo)-free_requests)/1000000*price_million_requests+min_instances*price_warm_instance | F21: =MAX(0,A21*storage_mb_per_cbo/1024-free_storage_gb)*price_storage_gb | G21: =MAX(0,B21*egress_mb_per_funder/1024-free_egress_gb)*price_egress_gb | H21: =MAX(0,A21*firestore_writes_per_cbo-free_fs_writes)/100000*price_fs_write+MAX(0,A21*firestore_reads_per_cbo-free_fs_reads)/100000*price_fs_read | I21: =A21*sms_out_cost_per_cbo | J21: =A21*sms_in_cost_per_cbo | K21: =A21*azure_cost_per_cbo | L21: =A21*gemini_doc_cost_per_cbo | M21: =A21*gemini_research_cost_per_cbo | N21: =B21*gemini_search_cost_per_funder | O21: =B21*gemini_question_cost_per_funder | P21: =A21*gemini_sms_cost_per_cbo | Q21: =B21*openai_cost_per_funder | R21: =A21*claude_cost_per_cbo | S21: =MAX(0,AB21-free_search)/1000*price_search_1k | T21: =MAX(0,AA21-free_maps)/1000*price_map_1k | U21: =MAX(0,A21*geocode_updates_per_cbo-free_geocode)/1000*price_geocode_1k | V21: =SUM(C21:U21) | W21: =V21*12 | X21: =IF(A21=0,NA(),V21/A21) | Y21: =IF(V21=0,0,(I21+J21)/V21) | Z21: =IF(V21=0,0,SUM(C21:H21)/V21) | AA21: =B21*map_loads_per_funder | AB21: =A21*refreshes_per_cbo_month*searches_per_refresh+B21*audits_per_funder*searches_per_audit | AC21: =(A21*cbo_http_requests+B21*funder_http_requests+A21*sms_in_segments_per_cbo)*request_vcpu_seconds+A21*pages_per_cbo_month*page_vcpu_seconds | AD21: =free_vcpu-AC21
A22: =cbo_tier_3 | B22: =funder_tier_5 | C22: =IF(OR(A22>=step_std_at,B22>=step_std_at),price_sql_std,IF(OR(A22>=step_small_at,B22>=step_small_at),price_sql_small,price_sql_micro)) | D22: =platform_fixed_fees | E22: =MAX(0,AC22-free_vcpu)*price_vcpu+MAX(0,AC22*memory_gib-free_gib)*price_gib+MAX(0,(A22*cbo_http_requests+B22*funder_http_requests+A22*sms_in_segments_per_cbo)-free_requests)/1000000*price_million_requests+min_instances*price_warm_instance | F22: =MAX(0,A22*storage_mb_per_cbo/1024-free_storage_gb)*price_storage_gb | G22: =MAX(0,B22*egress_mb_per_funder/1024-free_egress_gb)*price_egress_gb | H22: =MAX(0,A22*firestore_writes_per_cbo-free_fs_writes)/100000*price_fs_write+MAX(0,A22*firestore_reads_per_cbo-free_fs_reads)/100000*price_fs_read | I22: =A22*sms_out_cost_per_cbo | J22: =A22*sms_in_cost_per_cbo | K22: =A22*azure_cost_per_cbo | L22: =A22*gemini_doc_cost_per_cbo | M22: =A22*gemini_research_cost_per_cbo | N22: =B22*gemini_search_cost_per_funder | O22: =B22*gemini_question_cost_per_funder | P22: =A22*gemini_sms_cost_per_cbo | Q22: =B22*openai_cost_per_funder | R22: =A22*claude_cost_per_cbo | S22: =MAX(0,AB22-free_search)/1000*price_search_1k | T22: =MAX(0,AA22-free_maps)/1000*price_map_1k | U22: =MAX(0,A22*geocode_updates_per_cbo-free_geocode)/1000*price_geocode_1k | V22: =SUM(C22:U22) | W22: =V22*12 | X22: =IF(A22=0,NA(),V22/A22) | Y22: =IF(V22=0,0,(I22+J22)/V22) | Z22: =IF(V22=0,0,SUM(C22:H22)/V22) | AA22: =B22*map_loads_per_funder | AB22: =A22*refreshes_per_cbo_month*searches_per_refresh+B22*audits_per_funder*searches_per_audit | AC22: =(A22*cbo_http_requests+B22*funder_http_requests+A22*sms_in_segments_per_cbo)*request_vcpu_seconds+A22*pages_per_cbo_month*page_vcpu_seconds | AD22: =free_vcpu-AC22
A23: =cbo_tier_3 | B23: =funder_tier_6 | C23: =IF(OR(A23>=step_std_at,B23>=step_std_at),price_sql_std,IF(OR(A23>=step_small_at,B23>=step_small_at),price_sql_small,price_sql_micro)) | D23: =platform_fixed_fees | E23: =MAX(0,AC23-free_vcpu)*price_vcpu+MAX(0,AC23*memory_gib-free_gib)*price_gib+MAX(0,(A23*cbo_http_requests+B23*funder_http_requests+A23*sms_in_segments_per_cbo)-free_requests)/1000000*price_million_requests+min_instances*price_warm_instance | F23: =MAX(0,A23*storage_mb_per_cbo/1024-free_storage_gb)*price_storage_gb | G23: =MAX(0,B23*egress_mb_per_funder/1024-free_egress_gb)*price_egress_gb | H23: =MAX(0,A23*firestore_writes_per_cbo-free_fs_writes)/100000*price_fs_write+MAX(0,A23*firestore_reads_per_cbo-free_fs_reads)/100000*price_fs_read | I23: =A23*sms_out_cost_per_cbo | J23: =A23*sms_in_cost_per_cbo | K23: =A23*azure_cost_per_cbo | L23: =A23*gemini_doc_cost_per_cbo | M23: =A23*gemini_research_cost_per_cbo | N23: =B23*gemini_search_cost_per_funder | O23: =B23*gemini_question_cost_per_funder | P23: =A23*gemini_sms_cost_per_cbo | Q23: =B23*openai_cost_per_funder | R23: =A23*claude_cost_per_cbo | S23: =MAX(0,AB23-free_search)/1000*price_search_1k | T23: =MAX(0,AA23-free_maps)/1000*price_map_1k | U23: =MAX(0,A23*geocode_updates_per_cbo-free_geocode)/1000*price_geocode_1k | V23: =SUM(C23:U23) | W23: =V23*12 | X23: =IF(A23=0,NA(),V23/A23) | Y23: =IF(V23=0,0,(I23+J23)/V23) | Z23: =IF(V23=0,0,SUM(C23:H23)/V23) | AA23: =B23*map_loads_per_funder | AB23: =A23*refreshes_per_cbo_month*searches_per_refresh+B23*audits_per_funder*searches_per_audit | AC23: =(A23*cbo_http_requests+B23*funder_http_requests+A23*sms_in_segments_per_cbo)*request_vcpu_seconds+A23*pages_per_cbo_month*page_vcpu_seconds | AD23: =free_vcpu-AC23
A24: =cbo_tier_4 | B24: =funder_tier_1 | C24: =IF(OR(A24>=step_std_at,B24>=step_std_at),price_sql_std,IF(OR(A24>=step_small_at,B24>=step_small_at),price_sql_small,price_sql_micro)) | D24: =platform_fixed_fees | E24: =MAX(0,AC24-free_vcpu)*price_vcpu+MAX(0,AC24*memory_gib-free_gib)*price_gib+MAX(0,(A24*cbo_http_requests+B24*funder_http_requests+A24*sms_in_segments_per_cbo)-free_requests)/1000000*price_million_requests+min_instances*price_warm_instance | F24: =MAX(0,A24*storage_mb_per_cbo/1024-free_storage_gb)*price_storage_gb | G24: =MAX(0,B24*egress_mb_per_funder/1024-free_egress_gb)*price_egress_gb | H24: =MAX(0,A24*firestore_writes_per_cbo-free_fs_writes)/100000*price_fs_write+MAX(0,A24*firestore_reads_per_cbo-free_fs_reads)/100000*price_fs_read | I24: =A24*sms_out_cost_per_cbo | J24: =A24*sms_in_cost_per_cbo | K24: =A24*azure_cost_per_cbo | L24: =A24*gemini_doc_cost_per_cbo | M24: =A24*gemini_research_cost_per_cbo | N24: =B24*gemini_search_cost_per_funder | O24: =B24*gemini_question_cost_per_funder | P24: =A24*gemini_sms_cost_per_cbo | Q24: =B24*openai_cost_per_funder | R24: =A24*claude_cost_per_cbo | S24: =MAX(0,AB24-free_search)/1000*price_search_1k | T24: =MAX(0,AA24-free_maps)/1000*price_map_1k | U24: =MAX(0,A24*geocode_updates_per_cbo-free_geocode)/1000*price_geocode_1k | V24: =SUM(C24:U24) | W24: =V24*12 | X24: =IF(A24=0,NA(),V24/A24) | Y24: =IF(V24=0,0,(I24+J24)/V24) | Z24: =IF(V24=0,0,SUM(C24:H24)/V24) | AA24: =B24*map_loads_per_funder | AB24: =A24*refreshes_per_cbo_month*searches_per_refresh+B24*audits_per_funder*searches_per_audit | AC24: =(A24*cbo_http_requests+B24*funder_http_requests+A24*sms_in_segments_per_cbo)*request_vcpu_seconds+A24*pages_per_cbo_month*page_vcpu_seconds | AD24: =free_vcpu-AC24
A25: =cbo_tier_4 | B25: =funder_tier_2 | C25: =IF(OR(A25>=step_std_at,B25>=step_std_at),price_sql_std,IF(OR(A25>=step_small_at,B25>=step_small_at),price_sql_small,price_sql_micro)) | D25: =platform_fixed_fees | E25: =MAX(0,AC25-free_vcpu)*price_vcpu+MAX(0,AC25*memory_gib-free_gib)*price_gib+MAX(0,(A25*cbo_http_requests+B25*funder_http_requests+A25*sms_in_segments_per_cbo)-free_requests)/1000000*price_million_requests+min_instances*price_warm_instance | F25: =MAX(0,A25*storage_mb_per_cbo/1024-free_storage_gb)*price_storage_gb | G25: =MAX(0,B25*egress_mb_per_funder/1024-free_egress_gb)*price_egress_gb | H25: =MAX(0,A25*firestore_writes_per_cbo-free_fs_writes)/100000*price_fs_write+MAX(0,A25*firestore_reads_per_cbo-free_fs_reads)/100000*price_fs_read | I25: =A25*sms_out_cost_per_cbo | J25: =A25*sms_in_cost_per_cbo | K25: =A25*azure_cost_per_cbo | L25: =A25*gemini_doc_cost_per_cbo | M25: =A25*gemini_research_cost_per_cbo | N25: =B25*gemini_search_cost_per_funder | O25: =B25*gemini_question_cost_per_funder | P25: =A25*gemini_sms_cost_per_cbo | Q25: =B25*openai_cost_per_funder | R25: =A25*claude_cost_per_cbo | S25: =MAX(0,AB25-free_search)/1000*price_search_1k | T25: =MAX(0,AA25-free_maps)/1000*price_map_1k | U25: =MAX(0,A25*geocode_updates_per_cbo-free_geocode)/1000*price_geocode_1k | V25: =SUM(C25:U25) | W25: =V25*12 | X25: =IF(A25=0,NA(),V25/A25) | Y25: =IF(V25=0,0,(I25+J25)/V25) | Z25: =IF(V25=0,0,SUM(C25:H25)/V25) | AA25: =B25*map_loads_per_funder | AB25: =A25*refreshes_per_cbo_month*searches_per_refresh+B25*audits_per_funder*searches_per_audit | AC25: =(A25*cbo_http_requests+B25*funder_http_requests+A25*sms_in_segments_per_cbo)*request_vcpu_seconds+A25*pages_per_cbo_month*page_vcpu_seconds | AD25: =free_vcpu-AC25
A26: =cbo_tier_4 | B26: =funder_tier_3 | C26: =IF(OR(A26>=step_std_at,B26>=step_std_at),price_sql_std,IF(OR(A26>=step_small_at,B26>=step_small_at),price_sql_small,price_sql_micro)) | D26: =platform_fixed_fees | E26: =MAX(0,AC26-free_vcpu)*price_vcpu+MAX(0,AC26*memory_gib-free_gib)*price_gib+MAX(0,(A26*cbo_http_requests+B26*funder_http_requests+A26*sms_in_segments_per_cbo)-free_requests)/1000000*price_million_requests+min_instances*price_warm_instance | F26: =MAX(0,A26*storage_mb_per_cbo/1024-free_storage_gb)*price_storage_gb | G26: =MAX(0,B26*egress_mb_per_funder/1024-free_egress_gb)*price_egress_gb | H26: =MAX(0,A26*firestore_writes_per_cbo-free_fs_writes)/100000*price_fs_write+MAX(0,A26*firestore_reads_per_cbo-free_fs_reads)/100000*price_fs_read | I26: =A26*sms_out_cost_per_cbo | J26: =A26*sms_in_cost_per_cbo | K26: =A26*azure_cost_per_cbo | L26: =A26*gemini_doc_cost_per_cbo | M26: =A26*gemini_research_cost_per_cbo | N26: =B26*gemini_search_cost_per_funder | O26: =B26*gemini_question_cost_per_funder | P26: =A26*gemini_sms_cost_per_cbo | Q26: =B26*openai_cost_per_funder | R26: =A26*claude_cost_per_cbo | S26: =MAX(0,AB26-free_search)/1000*price_search_1k | T26: =MAX(0,AA26-free_maps)/1000*price_map_1k | U26: =MAX(0,A26*geocode_updates_per_cbo-free_geocode)/1000*price_geocode_1k | V26: =SUM(C26:U26) | W26: =V26*12 | X26: =IF(A26=0,NA(),V26/A26) | Y26: =IF(V26=0,0,(I26+J26)/V26) | Z26: =IF(V26=0,0,SUM(C26:H26)/V26) | AA26: =B26*map_loads_per_funder | AB26: =A26*refreshes_per_cbo_month*searches_per_refresh+B26*audits_per_funder*searches_per_audit | AC26: =(A26*cbo_http_requests+B26*funder_http_requests+A26*sms_in_segments_per_cbo)*request_vcpu_seconds+A26*pages_per_cbo_month*page_vcpu_seconds | AD26: =free_vcpu-AC26
A27: =cbo_tier_4 | B27: =funder_tier_4 | C27: =IF(OR(A27>=step_std_at,B27>=step_std_at),price_sql_std,IF(OR(A27>=step_small_at,B27>=step_small_at),price_sql_small,price_sql_micro)) | D27: =platform_fixed_fees | E27: =MAX(0,AC27-free_vcpu)*price_vcpu+MAX(0,AC27*memory_gib-free_gib)*price_gib+MAX(0,(A27*cbo_http_requests+B27*funder_http_requests+A27*sms_in_segments_per_cbo)-free_requests)/1000000*price_million_requests+min_instances*price_warm_instance | F27: =MAX(0,A27*storage_mb_per_cbo/1024-free_storage_gb)*price_storage_gb | G27: =MAX(0,B27*egress_mb_per_funder/1024-free_egress_gb)*price_egress_gb | H27: =MAX(0,A27*firestore_writes_per_cbo-free_fs_writes)/100000*price_fs_write+MAX(0,A27*firestore_reads_per_cbo-free_fs_reads)/100000*price_fs_read | I27: =A27*sms_out_cost_per_cbo | J27: =A27*sms_in_cost_per_cbo | K27: =A27*azure_cost_per_cbo | L27: =A27*gemini_doc_cost_per_cbo | M27: =A27*gemini_research_cost_per_cbo | N27: =B27*gemini_search_cost_per_funder | O27: =B27*gemini_question_cost_per_funder | P27: =A27*gemini_sms_cost_per_cbo | Q27: =B27*openai_cost_per_funder | R27: =A27*claude_cost_per_cbo | S27: =MAX(0,AB27-free_search)/1000*price_search_1k | T27: =MAX(0,AA27-free_maps)/1000*price_map_1k | U27: =MAX(0,A27*geocode_updates_per_cbo-free_geocode)/1000*price_geocode_1k | V27: =SUM(C27:U27) | W27: =V27*12 | X27: =IF(A27=0,NA(),V27/A27) | Y27: =IF(V27=0,0,(I27+J27)/V27) | Z27: =IF(V27=0,0,SUM(C27:H27)/V27) | AA27: =B27*map_loads_per_funder | AB27: =A27*refreshes_per_cbo_month*searches_per_refresh+B27*audits_per_funder*searches_per_audit | AC27: =(A27*cbo_http_requests+B27*funder_http_requests+A27*sms_in_segments_per_cbo)*request_vcpu_seconds+A27*pages_per_cbo_month*page_vcpu_seconds | AD27: =free_vcpu-AC27
A28: =cbo_tier_4 | B28: =funder_tier_5 | C28: =IF(OR(A28>=step_std_at,B28>=step_std_at),price_sql_std,IF(OR(A28>=step_small_at,B28>=step_small_at),price_sql_small,price_sql_micro)) | D28: =platform_fixed_fees | E28: =MAX(0,AC28-free_vcpu)*price_vcpu+MAX(0,AC28*memory_gib-free_gib)*price_gib+MAX(0,(A28*cbo_http_requests+B28*funder_http_requests+A28*sms_in_segments_per_cbo)-free_requests)/1000000*price_million_requests+min_instances*price_warm_instance | F28: =MAX(0,A28*storage_mb_per_cbo/1024-free_storage_gb)*price_storage_gb | G28: =MAX(0,B28*egress_mb_per_funder/1024-free_egress_gb)*price_egress_gb | H28: =MAX(0,A28*firestore_writes_per_cbo-free_fs_writes)/100000*price_fs_write+MAX(0,A28*firestore_reads_per_cbo-free_fs_reads)/100000*price_fs_read | I28: =A28*sms_out_cost_per_cbo | J28: =A28*sms_in_cost_per_cbo | K28: =A28*azure_cost_per_cbo | L28: =A28*gemini_doc_cost_per_cbo | M28: =A28*gemini_research_cost_per_cbo | N28: =B28*gemini_search_cost_per_funder | O28: =B28*gemini_question_cost_per_funder | P28: =A28*gemini_sms_cost_per_cbo | Q28: =B28*openai_cost_per_funder | R28: =A28*claude_cost_per_cbo | S28: =MAX(0,AB28-free_search)/1000*price_search_1k | T28: =MAX(0,AA28-free_maps)/1000*price_map_1k | U28: =MAX(0,A28*geocode_updates_per_cbo-free_geocode)/1000*price_geocode_1k | V28: =SUM(C28:U28) | W28: =V28*12 | X28: =IF(A28=0,NA(),V28/A28) | Y28: =IF(V28=0,0,(I28+J28)/V28) | Z28: =IF(V28=0,0,SUM(C28:H28)/V28) | AA28: =B28*map_loads_per_funder | AB28: =A28*refreshes_per_cbo_month*searches_per_refresh+B28*audits_per_funder*searches_per_audit | AC28: =(A28*cbo_http_requests+B28*funder_http_requests+A28*sms_in_segments_per_cbo)*request_vcpu_seconds+A28*pages_per_cbo_month*page_vcpu_seconds | AD28: =free_vcpu-AC28
A29: =cbo_tier_4 | B29: =funder_tier_6 | C29: =IF(OR(A29>=step_std_at,B29>=step_std_at),price_sql_std,IF(OR(A29>=step_small_at,B29>=step_small_at),price_sql_small,price_sql_micro)) | D29: =platform_fixed_fees | E29: =MAX(0,AC29-free_vcpu)*price_vcpu+MAX(0,AC29*memory_gib-free_gib)*price_gib+MAX(0,(A29*cbo_http_requests+B29*funder_http_requests+A29*sms_in_segments_per_cbo)-free_requests)/1000000*price_million_requests+min_instances*price_warm_instance | F29: =MAX(0,A29*storage_mb_per_cbo/1024-free_storage_gb)*price_storage_gb | G29: =MAX(0,B29*egress_mb_per_funder/1024-free_egress_gb)*price_egress_gb | H29: =MAX(0,A29*firestore_writes_per_cbo-free_fs_writes)/100000*price_fs_write+MAX(0,A29*firestore_reads_per_cbo-free_fs_reads)/100000*price_fs_read | I29: =A29*sms_out_cost_per_cbo | J29: =A29*sms_in_cost_per_cbo | K29: =A29*azure_cost_per_cbo | L29: =A29*gemini_doc_cost_per_cbo | M29: =A29*gemini_research_cost_per_cbo | N29: =B29*gemini_search_cost_per_funder | O29: =B29*gemini_question_cost_per_funder | P29: =A29*gemini_sms_cost_per_cbo | Q29: =B29*openai_cost_per_funder | R29: =A29*claude_cost_per_cbo | S29: =MAX(0,AB29-free_search)/1000*price_search_1k | T29: =MAX(0,AA29-free_maps)/1000*price_map_1k | U29: =MAX(0,A29*geocode_updates_per_cbo-free_geocode)/1000*price_geocode_1k | V29: =SUM(C29:U29) | W29: =V29*12 | X29: =IF(A29=0,NA(),V29/A29) | Y29: =IF(V29=0,0,(I29+J29)/V29) | Z29: =IF(V29=0,0,SUM(C29:H29)/V29) | AA29: =B29*map_loads_per_funder | AB29: =A29*refreshes_per_cbo_month*searches_per_refresh+B29*audits_per_funder*searches_per_audit | AC29: =(A29*cbo_http_requests+B29*funder_http_requests+A29*sms_in_segments_per_cbo)*request_vcpu_seconds+A29*pages_per_cbo_month*page_vcpu_seconds | AD29: =free_vcpu-AC29
A30: =cbo_tier_5 | B30: =funder_tier_1 | C30: =IF(OR(A30>=step_std_at,B30>=step_std_at),price_sql_std,IF(OR(A30>=step_small_at,B30>=step_small_at),price_sql_small,price_sql_micro)) | D30: =platform_fixed_fees | E30: =MAX(0,AC30-free_vcpu)*price_vcpu+MAX(0,AC30*memory_gib-free_gib)*price_gib+MAX(0,(A30*cbo_http_requests+B30*funder_http_requests+A30*sms_in_segments_per_cbo)-free_requests)/1000000*price_million_requests+min_instances*price_warm_instance | F30: =MAX(0,A30*storage_mb_per_cbo/1024-free_storage_gb)*price_storage_gb | G30: =MAX(0,B30*egress_mb_per_funder/1024-free_egress_gb)*price_egress_gb | H30: =MAX(0,A30*firestore_writes_per_cbo-free_fs_writes)/100000*price_fs_write+MAX(0,A30*firestore_reads_per_cbo-free_fs_reads)/100000*price_fs_read | I30: =A30*sms_out_cost_per_cbo | J30: =A30*sms_in_cost_per_cbo | K30: =A30*azure_cost_per_cbo | L30: =A30*gemini_doc_cost_per_cbo | M30: =A30*gemini_research_cost_per_cbo | N30: =B30*gemini_search_cost_per_funder | O30: =B30*gemini_question_cost_per_funder | P30: =A30*gemini_sms_cost_per_cbo | Q30: =B30*openai_cost_per_funder | R30: =A30*claude_cost_per_cbo | S30: =MAX(0,AB30-free_search)/1000*price_search_1k | T30: =MAX(0,AA30-free_maps)/1000*price_map_1k | U30: =MAX(0,A30*geocode_updates_per_cbo-free_geocode)/1000*price_geocode_1k | V30: =SUM(C30:U30) | W30: =V30*12 | X30: =IF(A30=0,NA(),V30/A30) | Y30: =IF(V30=0,0,(I30+J30)/V30) | Z30: =IF(V30=0,0,SUM(C30:H30)/V30) | AA30: =B30*map_loads_per_funder | AB30: =A30*refreshes_per_cbo_month*searches_per_refresh+B30*audits_per_funder*searches_per_audit | AC30: =(A30*cbo_http_requests+B30*funder_http_requests+A30*sms_in_segments_per_cbo)*request_vcpu_seconds+A30*pages_per_cbo_month*page_vcpu_seconds | AD30: =free_vcpu-AC30
A31: =cbo_tier_5 | B31: =funder_tier_2 | C31: =IF(OR(A31>=step_std_at,B31>=step_std_at),price_sql_std,IF(OR(A31>=step_small_at,B31>=step_small_at),price_sql_small,price_sql_micro)) | D31: =platform_fixed_fees | E31: =MAX(0,AC31-free_vcpu)*price_vcpu+MAX(0,AC31*memory_gib-free_gib)*price_gib+MAX(0,(A31*cbo_http_requests+B31*funder_http_requests+A31*sms_in_segments_per_cbo)-free_requests)/1000000*price_million_requests+min_instances*price_warm_instance | F31: =MAX(0,A31*storage_mb_per_cbo/1024-free_storage_gb)*price_storage_gb | G31: =MAX(0,B31*egress_mb_per_funder/1024-free_egress_gb)*price_egress_gb | H31: =MAX(0,A31*firestore_writes_per_cbo-free_fs_writes)/100000*price_fs_write+MAX(0,A31*firestore_reads_per_cbo-free_fs_reads)/100000*price_fs_read | I31: =A31*sms_out_cost_per_cbo | J31: =A31*sms_in_cost_per_cbo | K31: =A31*azure_cost_per_cbo | L31: =A31*gemini_doc_cost_per_cbo | M31: =A31*gemini_research_cost_per_cbo | N31: =B31*gemini_search_cost_per_funder | O31: =B31*gemini_question_cost_per_funder | P31: =A31*gemini_sms_cost_per_cbo | Q31: =B31*openai_cost_per_funder | R31: =A31*claude_cost_per_cbo | S31: =MAX(0,AB31-free_search)/1000*price_search_1k | T31: =MAX(0,AA31-free_maps)/1000*price_map_1k | U31: =MAX(0,A31*geocode_updates_per_cbo-free_geocode)/1000*price_geocode_1k | V31: =SUM(C31:U31) | W31: =V31*12 | X31: =IF(A31=0,NA(),V31/A31) | Y31: =IF(V31=0,0,(I31+J31)/V31) | Z31: =IF(V31=0,0,SUM(C31:H31)/V31) | AA31: =B31*map_loads_per_funder | AB31: =A31*refreshes_per_cbo_month*searches_per_refresh+B31*audits_per_funder*searches_per_audit | AC31: =(A31*cbo_http_requests+B31*funder_http_requests+A31*sms_in_segments_per_cbo)*request_vcpu_seconds+A31*pages_per_cbo_month*page_vcpu_seconds | AD31: =free_vcpu-AC31
A32: =cbo_tier_5 | B32: =funder_tier_3 | C32: =IF(OR(A32>=step_std_at,B32>=step_std_at),price_sql_std,IF(OR(A32>=step_small_at,B32>=step_small_at),price_sql_small,price_sql_micro)) | D32: =platform_fixed_fees | E32: =MAX(0,AC32-free_vcpu)*price_vcpu+MAX(0,AC32*memory_gib-free_gib)*price_gib+MAX(0,(A32*cbo_http_requests+B32*funder_http_requests+A32*sms_in_segments_per_cbo)-free_requests)/1000000*price_million_requests+min_instances*price_warm_instance | F32: =MAX(0,A32*storage_mb_per_cbo/1024-free_storage_gb)*price_storage_gb | G32: =MAX(0,B32*egress_mb_per_funder/1024-free_egress_gb)*price_egress_gb | H32: =MAX(0,A32*firestore_writes_per_cbo-free_fs_writes)/100000*price_fs_write+MAX(0,A32*firestore_reads_per_cbo-free_fs_reads)/100000*price_fs_read | I32: =A32*sms_out_cost_per_cbo | J32: =A32*sms_in_cost_per_cbo | K32: =A32*azure_cost_per_cbo | L32: =A32*gemini_doc_cost_per_cbo | M32: =A32*gemini_research_cost_per_cbo | N32: =B32*gemini_search_cost_per_funder | O32: =B32*gemini_question_cost_per_funder | P32: =A32*gemini_sms_cost_per_cbo | Q32: =B32*openai_cost_per_funder | R32: =A32*claude_cost_per_cbo | S32: =MAX(0,AB32-free_search)/1000*price_search_1k | T32: =MAX(0,AA32-free_maps)/1000*price_map_1k | U32: =MAX(0,A32*geocode_updates_per_cbo-free_geocode)/1000*price_geocode_1k | V32: =SUM(C32:U32) | W32: =V32*12 | X32: =IF(A32=0,NA(),V32/A32) | Y32: =IF(V32=0,0,(I32+J32)/V32) | Z32: =IF(V32=0,0,SUM(C32:H32)/V32) | AA32: =B32*map_loads_per_funder | AB32: =A32*refreshes_per_cbo_month*searches_per_refresh+B32*audits_per_funder*searches_per_audit | AC32: =(A32*cbo_http_requests+B32*funder_http_requests+A32*sms_in_segments_per_cbo)*request_vcpu_seconds+A32*pages_per_cbo_month*page_vcpu_seconds | AD32: =free_vcpu-AC32
A33: =cbo_tier_5 | B33: =funder_tier_4 | C33: =IF(OR(A33>=step_std_at,B33>=step_std_at),price_sql_std,IF(OR(A33>=step_small_at,B33>=step_small_at),price_sql_small,price_sql_micro)) | D33: =platform_fixed_fees | E33: =MAX(0,AC33-free_vcpu)*price_vcpu+MAX(0,AC33*memory_gib-free_gib)*price_gib+MAX(0,(A33*cbo_http_requests+B33*funder_http_requests+A33*sms_in_segments_per_cbo)-free_requests)/1000000*price_million_requests+min_instances*price_warm_instance | F33: =MAX(0,A33*storage_mb_per_cbo/1024-free_storage_gb)*price_storage_gb | G33: =MAX(0,B33*egress_mb_per_funder/1024-free_egress_gb)*price_egress_gb | H33: =MAX(0,A33*firestore_writes_per_cbo-free_fs_writes)/100000*price_fs_write+MAX(0,A33*firestore_reads_per_cbo-free_fs_reads)/100000*price_fs_read | I33: =A33*sms_out_cost_per_cbo | J33: =A33*sms_in_cost_per_cbo | K33: =A33*azure_cost_per_cbo | L33: =A33*gemini_doc_cost_per_cbo | M33: =A33*gemini_research_cost_per_cbo | N33: =B33*gemini_search_cost_per_funder | O33: =B33*gemini_question_cost_per_funder | P33: =A33*gemini_sms_cost_per_cbo | Q33: =B33*openai_cost_per_funder | R33: =A33*claude_cost_per_cbo | S33: =MAX(0,AB33-free_search)/1000*price_search_1k | T33: =MAX(0,AA33-free_maps)/1000*price_map_1k | U33: =MAX(0,A33*geocode_updates_per_cbo-free_geocode)/1000*price_geocode_1k | V33: =SUM(C33:U33) | W33: =V33*12 | X33: =IF(A33=0,NA(),V33/A33) | Y33: =IF(V33=0,0,(I33+J33)/V33) | Z33: =IF(V33=0,0,SUM(C33:H33)/V33) | AA33: =B33*map_loads_per_funder | AB33: =A33*refreshes_per_cbo_month*searches_per_refresh+B33*audits_per_funder*searches_per_audit | AC33: =(A33*cbo_http_requests+B33*funder_http_requests+A33*sms_in_segments_per_cbo)*request_vcpu_seconds+A33*pages_per_cbo_month*page_vcpu_seconds | AD33: =free_vcpu-AC33
A34: =cbo_tier_5 | B34: =funder_tier_5 | C34: =IF(OR(A34>=step_std_at,B34>=step_std_at),price_sql_std,IF(OR(A34>=step_small_at,B34>=step_small_at),price_sql_small,price_sql_micro)) | D34: =platform_fixed_fees | E34: =MAX(0,AC34-free_vcpu)*price_vcpu+MAX(0,AC34*memory_gib-free_gib)*price_gib+MAX(0,(A34*cbo_http_requests+B34*funder_http_requests+A34*sms_in_segments_per_cbo)-free_requests)/1000000*price_million_requests+min_instances*price_warm_instance | F34: =MAX(0,A34*storage_mb_per_cbo/1024-free_storage_gb)*price_storage_gb | G34: =MAX(0,B34*egress_mb_per_funder/1024-free_egress_gb)*price_egress_gb | H34: =MAX(0,A34*firestore_writes_per_cbo-free_fs_writes)/100000*price_fs_write+MAX(0,A34*firestore_reads_per_cbo-free_fs_reads)/100000*price_fs_read | I34: =A34*sms_out_cost_per_cbo | J34: =A34*sms_in_cost_per_cbo | K34: =A34*azure_cost_per_cbo | L34: =A34*gemini_doc_cost_per_cbo | M34: =A34*gemini_research_cost_per_cbo | N34: =B34*gemini_search_cost_per_funder | O34: =B34*gemini_question_cost_per_funder | P34: =A34*gemini_sms_cost_per_cbo | Q34: =B34*openai_cost_per_funder | R34: =A34*claude_cost_per_cbo | S34: =MAX(0,AB34-free_search)/1000*price_search_1k | T34: =MAX(0,AA34-free_maps)/1000*price_map_1k | U34: =MAX(0,A34*geocode_updates_per_cbo-free_geocode)/1000*price_geocode_1k | V34: =SUM(C34:U34) | W34: =V34*12 | X34: =IF(A34=0,NA(),V34/A34) | Y34: =IF(V34=0,0,(I34+J34)/V34) | Z34: =IF(V34=0,0,SUM(C34:H34)/V34) | AA34: =B34*map_loads_per_funder | AB34: =A34*refreshes_per_cbo_month*searches_per_refresh+B34*audits_per_funder*searches_per_audit | AC34: =(A34*cbo_http_requests+B34*funder_http_requests+A34*sms_in_segments_per_cbo)*request_vcpu_seconds+A34*pages_per_cbo_month*page_vcpu_seconds | AD34: =free_vcpu-AC34
A35: =cbo_tier_5 | B35: =funder_tier_6 | C35: =IF(OR(A35>=step_std_at,B35>=step_std_at),price_sql_std,IF(OR(A35>=step_small_at,B35>=step_small_at),price_sql_small,price_sql_micro)) | D35: =platform_fixed_fees | E35: =MAX(0,AC35-free_vcpu)*price_vcpu+MAX(0,AC35*memory_gib-free_gib)*price_gib+MAX(0,(A35*cbo_http_requests+B35*funder_http_requests+A35*sms_in_segments_per_cbo)-free_requests)/1000000*price_million_requests+min_instances*price_warm_instance | F35: =MAX(0,A35*storage_mb_per_cbo/1024-free_storage_gb)*price_storage_gb | G35: =MAX(0,B35*egress_mb_per_funder/1024-free_egress_gb)*price_egress_gb | H35: =MAX(0,A35*firestore_writes_per_cbo-free_fs_writes)/100000*price_fs_write+MAX(0,A35*firestore_reads_per_cbo-free_fs_reads)/100000*price_fs_read | I35: =A35*sms_out_cost_per_cbo | J35: =A35*sms_in_cost_per_cbo | K35: =A35*azure_cost_per_cbo | L35: =A35*gemini_doc_cost_per_cbo | M35: =A35*gemini_research_cost_per_cbo | N35: =B35*gemini_search_cost_per_funder | O35: =B35*gemini_question_cost_per_funder | P35: =A35*gemini_sms_cost_per_cbo | Q35: =B35*openai_cost_per_funder | R35: =A35*claude_cost_per_cbo | S35: =MAX(0,AB35-free_search)/1000*price_search_1k | T35: =MAX(0,AA35-free_maps)/1000*price_map_1k | U35: =MAX(0,A35*geocode_updates_per_cbo-free_geocode)/1000*price_geocode_1k | V35: =SUM(C35:U35) | W35: =V35*12 | X35: =IF(A35=0,NA(),V35/A35) | Y35: =IF(V35=0,0,(I35+J35)/V35) | Z35: =IF(V35=0,0,SUM(C35:H35)/V35) | AA35: =B35*map_loads_per_funder | AB35: =A35*refreshes_per_cbo_month*searches_per_refresh+B35*audits_per_funder*searches_per_audit | AC35: =(A35*cbo_http_requests+B35*funder_http_requests+A35*sms_in_segments_per_cbo)*request_vcpu_seconds+A35*pages_per_cbo_month*page_vcpu_seconds | AD35: =free_vcpu-AC35
A36: =cbo_tier_6 | B36: =funder_tier_1 | C36: =IF(OR(A36>=step_std_at,B36>=step_std_at),price_sql_std,IF(OR(A36>=step_small_at,B36>=step_small_at),price_sql_small,price_sql_micro)) | D36: =platform_fixed_fees | E36: =MAX(0,AC36-free_vcpu)*price_vcpu+MAX(0,AC36*memory_gib-free_gib)*price_gib+MAX(0,(A36*cbo_http_requests+B36*funder_http_requests+A36*sms_in_segments_per_cbo)-free_requests)/1000000*price_million_requests+min_instances*price_warm_instance | F36: =MAX(0,A36*storage_mb_per_cbo/1024-free_storage_gb)*price_storage_gb | G36: =MAX(0,B36*egress_mb_per_funder/1024-free_egress_gb)*price_egress_gb | H36: =MAX(0,A36*firestore_writes_per_cbo-free_fs_writes)/100000*price_fs_write+MAX(0,A36*firestore_reads_per_cbo-free_fs_reads)/100000*price_fs_read | I36: =A36*sms_out_cost_per_cbo | J36: =A36*sms_in_cost_per_cbo | K36: =A36*azure_cost_per_cbo | L36: =A36*gemini_doc_cost_per_cbo | M36: =A36*gemini_research_cost_per_cbo | N36: =B36*gemini_search_cost_per_funder | O36: =B36*gemini_question_cost_per_funder | P36: =A36*gemini_sms_cost_per_cbo | Q36: =B36*openai_cost_per_funder | R36: =A36*claude_cost_per_cbo | S36: =MAX(0,AB36-free_search)/1000*price_search_1k | T36: =MAX(0,AA36-free_maps)/1000*price_map_1k | U36: =MAX(0,A36*geocode_updates_per_cbo-free_geocode)/1000*price_geocode_1k | V36: =SUM(C36:U36) | W36: =V36*12 | X36: =IF(A36=0,NA(),V36/A36) | Y36: =IF(V36=0,0,(I36+J36)/V36) | Z36: =IF(V36=0,0,SUM(C36:H36)/V36) | AA36: =B36*map_loads_per_funder | AB36: =A36*refreshes_per_cbo_month*searches_per_refresh+B36*audits_per_funder*searches_per_audit | AC36: =(A36*cbo_http_requests+B36*funder_http_requests+A36*sms_in_segments_per_cbo)*request_vcpu_seconds+A36*pages_per_cbo_month*page_vcpu_seconds | AD36: =free_vcpu-AC36
A37: =cbo_tier_6 | B37: =funder_tier_2 | C37: =IF(OR(A37>=step_std_at,B37>=step_std_at),price_sql_std,IF(OR(A37>=step_small_at,B37>=step_small_at),price_sql_small,price_sql_micro)) | D37: =platform_fixed_fees | E37: =MAX(0,AC37-free_vcpu)*price_vcpu+MAX(0,AC37*memory_gib-free_gib)*price_gib+MAX(0,(A37*cbo_http_requests+B37*funder_http_requests+A37*sms_in_segments_per_cbo)-free_requests)/1000000*price_million_requests+min_instances*price_warm_instance | F37: =MAX(0,A37*storage_mb_per_cbo/1024-free_storage_gb)*price_storage_gb | G37: =MAX(0,B37*egress_mb_per_funder/1024-free_egress_gb)*price_egress_gb | H37: =MAX(0,A37*firestore_writes_per_cbo-free_fs_writes)/100000*price_fs_write+MAX(0,A37*firestore_reads_per_cbo-free_fs_reads)/100000*price_fs_read | I37: =A37*sms_out_cost_per_cbo | J37: =A37*sms_in_cost_per_cbo | K37: =A37*azure_cost_per_cbo | L37: =A37*gemini_doc_cost_per_cbo | M37: =A37*gemini_research_cost_per_cbo | N37: =B37*gemini_search_cost_per_funder | O37: =B37*gemini_question_cost_per_funder | P37: =A37*gemini_sms_cost_per_cbo | Q37: =B37*openai_cost_per_funder | R37: =A37*claude_cost_per_cbo | S37: =MAX(0,AB37-free_search)/1000*price_search_1k | T37: =MAX(0,AA37-free_maps)/1000*price_map_1k | U37: =MAX(0,A37*geocode_updates_per_cbo-free_geocode)/1000*price_geocode_1k | V37: =SUM(C37:U37) | W37: =V37*12 | X37: =IF(A37=0,NA(),V37/A37) | Y37: =IF(V37=0,0,(I37+J37)/V37) | Z37: =IF(V37=0,0,SUM(C37:H37)/V37) | AA37: =B37*map_loads_per_funder | AB37: =A37*refreshes_per_cbo_month*searches_per_refresh+B37*audits_per_funder*searches_per_audit | AC37: =(A37*cbo_http_requests+B37*funder_http_requests+A37*sms_in_segments_per_cbo)*request_vcpu_seconds+A37*pages_per_cbo_month*page_vcpu_seconds | AD37: =free_vcpu-AC37
A38: =cbo_tier_6 | B38: =funder_tier_3 | C38: =IF(OR(A38>=step_std_at,B38>=step_std_at),price_sql_std,IF(OR(A38>=step_small_at,B38>=step_small_at),price_sql_small,price_sql_micro)) | D38: =platform_fixed_fees | E38: =MAX(0,AC38-free_vcpu)*price_vcpu+MAX(0,AC38*memory_gib-free_gib)*price_gib+MAX(0,(A38*cbo_http_requests+B38*funder_http_requests+A38*sms_in_segments_per_cbo)-free_requests)/1000000*price_million_requests+min_instances*price_warm_instance | F38: =MAX(0,A38*storage_mb_per_cbo/1024-free_storage_gb)*price_storage_gb | G38: =MAX(0,B38*egress_mb_per_funder/1024-free_egress_gb)*price_egress_gb | H38: =MAX(0,A38*firestore_writes_per_cbo-free_fs_writes)/100000*price_fs_write+MAX(0,A38*firestore_reads_per_cbo-free_fs_reads)/100000*price_fs_read | I38: =A38*sms_out_cost_per_cbo | J38: =A38*sms_in_cost_per_cbo | K38: =A38*azure_cost_per_cbo | L38: =A38*gemini_doc_cost_per_cbo | M38: =A38*gemini_research_cost_per_cbo | N38: =B38*gemini_search_cost_per_funder | O38: =B38*gemini_question_cost_per_funder | P38: =A38*gemini_sms_cost_per_cbo | Q38: =B38*openai_cost_per_funder | R38: =A38*claude_cost_per_cbo | S38: =MAX(0,AB38-free_search)/1000*price_search_1k | T38: =MAX(0,AA38-free_maps)/1000*price_map_1k | U38: =MAX(0,A38*geocode_updates_per_cbo-free_geocode)/1000*price_geocode_1k | V38: =SUM(C38:U38) | W38: =V38*12 | X38: =IF(A38=0,NA(),V38/A38) | Y38: =IF(V38=0,0,(I38+J38)/V38) | Z38: =IF(V38=0,0,SUM(C38:H38)/V38) | AA38: =B38*map_loads_per_funder | AB38: =A38*refreshes_per_cbo_month*searches_per_refresh+B38*audits_per_funder*searches_per_audit | AC38: =(A38*cbo_http_requests+B38*funder_http_requests+A38*sms_in_segments_per_cbo)*request_vcpu_seconds+A38*pages_per_cbo_month*page_vcpu_seconds | AD38: =free_vcpu-AC38
A39: =cbo_tier_6 | B39: =funder_tier_4 | C39: =IF(OR(A39>=step_std_at,B39>=step_std_at),price_sql_std,IF(OR(A39>=step_small_at,B39>=step_small_at),price_sql_small,price_sql_micro)) | D39: =platform_fixed_fees | E39: =MAX(0,AC39-free_vcpu)*price_vcpu+MAX(0,AC39*memory_gib-free_gib)*price_gib+MAX(0,(A39*cbo_http_requests+B39*funder_http_requests+A39*sms_in_segments_per_cbo)-free_requests)/1000000*price_million_requests+min_instances*price_warm_instance | F39: =MAX(0,A39*storage_mb_per_cbo/1024-free_storage_gb)*price_storage_gb | G39: =MAX(0,B39*egress_mb_per_funder/1024-free_egress_gb)*price_egress_gb | H39: =MAX(0,A39*firestore_writes_per_cbo-free_fs_writes)/100000*price_fs_write+MAX(0,A39*firestore_reads_per_cbo-free_fs_reads)/100000*price_fs_read | I39: =A39*sms_out_cost_per_cbo | J39: =A39*sms_in_cost_per_cbo | K39: =A39*azure_cost_per_cbo | L39: =A39*gemini_doc_cost_per_cbo | M39: =A39*gemini_research_cost_per_cbo | N39: =B39*gemini_search_cost_per_funder | O39: =B39*gemini_question_cost_per_funder | P39: =A39*gemini_sms_cost_per_cbo | Q39: =B39*openai_cost_per_funder | R39: =A39*claude_cost_per_cbo | S39: =MAX(0,AB39-free_search)/1000*price_search_1k | T39: =MAX(0,AA39-free_maps)/1000*price_map_1k | U39: =MAX(0,A39*geocode_updates_per_cbo-free_geocode)/1000*price_geocode_1k | V39: =SUM(C39:U39) | W39: =V39*12 | X39: =IF(A39=0,NA(),V39/A39) | Y39: =IF(V39=0,0,(I39+J39)/V39) | Z39: =IF(V39=0,0,SUM(C39:H39)/V39) | AA39: =B39*map_loads_per_funder | AB39: =A39*refreshes_per_cbo_month*searches_per_refresh+B39*audits_per_funder*searches_per_audit | AC39: =(A39*cbo_http_requests+B39*funder_http_requests+A39*sms_in_segments_per_cbo)*request_vcpu_seconds+A39*pages_per_cbo_month*page_vcpu_seconds | AD39: =free_vcpu-AC39
A40: =cbo_tier_6 | B40: =funder_tier_5 | C40: =IF(OR(A40>=step_std_at,B40>=step_std_at),price_sql_std,IF(OR(A40>=step_small_at,B40>=step_small_at),price_sql_small,price_sql_micro)) | D40: =platform_fixed_fees | E40: =MAX(0,AC40-free_vcpu)*price_vcpu+MAX(0,AC40*memory_gib-free_gib)*price_gib+MAX(0,(A40*cbo_http_requests+B40*funder_http_requests+A40*sms_in_segments_per_cbo)-free_requests)/1000000*price_million_requests+min_instances*price_warm_instance | F40: =MAX(0,A40*storage_mb_per_cbo/1024-free_storage_gb)*price_storage_gb | G40: =MAX(0,B40*egress_mb_per_funder/1024-free_egress_gb)*price_egress_gb | H40: =MAX(0,A40*firestore_writes_per_cbo-free_fs_writes)/100000*price_fs_write+MAX(0,A40*firestore_reads_per_cbo-free_fs_reads)/100000*price_fs_read | I40: =A40*sms_out_cost_per_cbo | J40: =A40*sms_in_cost_per_cbo | K40: =A40*azure_cost_per_cbo | L40: =A40*gemini_doc_cost_per_cbo | M40: =A40*gemini_research_cost_per_cbo | N40: =B40*gemini_search_cost_per_funder | O40: =B40*gemini_question_cost_per_funder | P40: =A40*gemini_sms_cost_per_cbo | Q40: =B40*openai_cost_per_funder | R40: =A40*claude_cost_per_cbo | S40: =MAX(0,AB40-free_search)/1000*price_search_1k | T40: =MAX(0,AA40-free_maps)/1000*price_map_1k | U40: =MAX(0,A40*geocode_updates_per_cbo-free_geocode)/1000*price_geocode_1k | V40: =SUM(C40:U40) | W40: =V40*12 | X40: =IF(A40=0,NA(),V40/A40) | Y40: =IF(V40=0,0,(I40+J40)/V40) | Z40: =IF(V40=0,0,SUM(C40:H40)/V40) | AA40: =B40*map_loads_per_funder | AB40: =A40*refreshes_per_cbo_month*searches_per_refresh+B40*audits_per_funder*searches_per_audit | AC40: =(A40*cbo_http_requests+B40*funder_http_requests+A40*sms_in_segments_per_cbo)*request_vcpu_seconds+A40*pages_per_cbo_month*page_vcpu_seconds | AD40: =free_vcpu-AC40
A41: =cbo_tier_6 | B41: =funder_tier_6 | C41: =IF(OR(A41>=step_std_at,B41>=step_std_at),price_sql_std,IF(OR(A41>=step_small_at,B41>=step_small_at),price_sql_small,price_sql_micro)) | D41: =platform_fixed_fees | E41: =MAX(0,AC41-free_vcpu)*price_vcpu+MAX(0,AC41*memory_gib-free_gib)*price_gib+MAX(0,(A41*cbo_http_requests+B41*funder_http_requests+A41*sms_in_segments_per_cbo)-free_requests)/1000000*price_million_requests+min_instances*price_warm_instance | F41: =MAX(0,A41*storage_mb_per_cbo/1024-free_storage_gb)*price_storage_gb | G41: =MAX(0,B41*egress_mb_per_funder/1024-free_egress_gb)*price_egress_gb | H41: =MAX(0,A41*firestore_writes_per_cbo-free_fs_writes)/100000*price_fs_write+MAX(0,A41*firestore_reads_per_cbo-free_fs_reads)/100000*price_fs_read | I41: =A41*sms_out_cost_per_cbo | J41: =A41*sms_in_cost_per_cbo | K41: =A41*azure_cost_per_cbo | L41: =A41*gemini_doc_cost_per_cbo | M41: =A41*gemini_research_cost_per_cbo | N41: =B41*gemini_search_cost_per_funder | O41: =B41*gemini_question_cost_per_funder | P41: =A41*gemini_sms_cost_per_cbo | Q41: =B41*openai_cost_per_funder | R41: =A41*claude_cost_per_cbo | S41: =MAX(0,AB41-free_search)/1000*price_search_1k | T41: =MAX(0,AA41-free_maps)/1000*price_map_1k | U41: =MAX(0,A41*geocode_updates_per_cbo-free_geocode)/1000*price_geocode_1k | V41: =SUM(C41:U41) | W41: =V41*12 | X41: =IF(A41=0,NA(),V41/A41) | Y41: =IF(V41=0,0,(I41+J41)/V41) | Z41: =IF(V41=0,0,SUM(C41:H41)/V41) | AA41: =B41*map_loads_per_funder | AB41: =A41*refreshes_per_cbo_month*searches_per_refresh+B41*audits_per_funder*searches_per_audit | AC41: =(A41*cbo_http_requests+B41*funder_http_requests+A41*sms_in_segments_per_cbo)*request_vcpu_seconds+A41*pages_per_cbo_month*page_vcpu_seconds | AD41: =free_vcpu-AC41

Sheet Monthly matrix
A1: Monthly cost
A2: Read across for more funders, and down for more CBOs. The jump at 200 and at 500 is the database step, triggered by whichever side gets there first.
A4: Active funders → | B4: =funder_tier_1 | C4: =funder_tier_2 | D4: =funder_tier_3 | E4: =funder_tier_4 | F4: =funder_tier_5 | G4: =funder_tier_6
A5: Active CBOs ↓ | B5: USD / month | C5: USD / month | D5: USD / month | E5: USD / month | F5: USD / month | G5: USD / month
A6: =cbo_tier_1 | B6: =SUMIFS(Scenarios!$V$6:$V$41,Scenarios!$A$6:$A$41,cbo_tier_1,Scenarios!$B$6:$B$41,funder_tier_1) | C6: =SUMIFS(Scenarios!$V$6:$V$41,Scenarios!$A$6:$A$41,cbo_tier_1,Scenarios!$B$6:$B$41,funder_tier_2) | D6: =SUMIFS(Scenarios!$V$6:$V$41,Scenarios!$A$6:$A$41,cbo_tier_1,Scenarios!$B$6:$B$41,funder_tier_3) | E6: =SUMIFS(Scenarios!$V$6:$V$41,Scenarios!$A$6:$A$41,cbo_tier_1,Scenarios!$B$6:$B$41,funder_tier_4) | F6: =SUMIFS(Scenarios!$V$6:$V$41,Scenarios!$A$6:$A$41,cbo_tier_1,Scenarios!$B$6:$B$41,funder_tier_5) | G6: =SUMIFS(Scenarios!$V$6:$V$41,Scenarios!$A$6:$A$41,cbo_tier_1,Scenarios!$B$6:$B$41,funder_tier_6)
A7: =cbo_tier_2 | B7: =SUMIFS(Scenarios!$V$6:$V$41,Scenarios!$A$6:$A$41,cbo_tier_2,Scenarios!$B$6:$B$41,funder_tier_1) | C7: =SUMIFS(Scenarios!$V$6:$V$41,Scenarios!$A$6:$A$41,cbo_tier_2,Scenarios!$B$6:$B$41,funder_tier_2) | D7: =SUMIFS(Scenarios!$V$6:$V$41,Scenarios!$A$6:$A$41,cbo_tier_2,Scenarios!$B$6:$B$41,funder_tier_3) | E7: =SUMIFS(Scenarios!$V$6:$V$41,Scenarios!$A$6:$A$41,cbo_tier_2,Scenarios!$B$6:$B$41,funder_tier_4) | F7: =SUMIFS(Scenarios!$V$6:$V$41,Scenarios!$A$6:$A$41,cbo_tier_2,Scenarios!$B$6:$B$41,funder_tier_5) | G7: =SUMIFS(Scenarios!$V$6:$V$41,Scenarios!$A$6:$A$41,cbo_tier_2,Scenarios!$B$6:$B$41,funder_tier_6)
A8: =cbo_tier_3 | B8: =SUMIFS(Scenarios!$V$6:$V$41,Scenarios!$A$6:$A$41,cbo_tier_3,Scenarios!$B$6:$B$41,funder_tier_1) | C8: =SUMIFS(Scenarios!$V$6:$V$41,Scenarios!$A$6:$A$41,cbo_tier_3,Scenarios!$B$6:$B$41,funder_tier_2) | D8: =SUMIFS(Scenarios!$V$6:$V$41,Scenarios!$A$6:$A$41,cbo_tier_3,Scenarios!$B$6:$B$41,funder_tier_3) | E8: =SUMIFS(Scenarios!$V$6:$V$41,Scenarios!$A$6:$A$41,cbo_tier_3,Scenarios!$B$6:$B$41,funder_tier_4) | F8: =SUMIFS(Scenarios!$V$6:$V$41,Scenarios!$A$6:$A$41,cbo_tier_3,Scenarios!$B$6:$B$41,funder_tier_5) | G8: =SUMIFS(Scenarios!$V$6:$V$41,Scenarios!$A$6:$A$41,cbo_tier_3,Scenarios!$B$6:$B$41,funder_tier_6)
A9: =cbo_tier_4 | B9: =SUMIFS(Scenarios!$V$6:$V$41,Scenarios!$A$6:$A$41,cbo_tier_4,Scenarios!$B$6:$B$41,funder_tier_1) | C9: =SUMIFS(Scenarios!$V$6:$V$41,Scenarios!$A$6:$A$41,cbo_tier_4,Scenarios!$B$6:$B$41,funder_tier_2) | D9: =SUMIFS(Scenarios!$V$6:$V$41,Scenarios!$A$6:$A$41,cbo_tier_4,Scenarios!$B$6:$B$41,funder_tier_3) | E9: =SUMIFS(Scenarios!$V$6:$V$41,Scenarios!$A$6:$A$41,cbo_tier_4,Scenarios!$B$6:$B$41,funder_tier_4) | F9: =SUMIFS(Scenarios!$V$6:$V$41,Scenarios!$A$6:$A$41,cbo_tier_4,Scenarios!$B$6:$B$41,funder_tier_5) | G9: =SUMIFS(Scenarios!$V$6:$V$41,Scenarios!$A$6:$A$41,cbo_tier_4,Scenarios!$B$6:$B$41,funder_tier_6)
A10: =cbo_tier_5 | B10: =SUMIFS(Scenarios!$V$6:$V$41,Scenarios!$A$6:$A$41,cbo_tier_5,Scenarios!$B$6:$B$41,funder_tier_1) | C10: =SUMIFS(Scenarios!$V$6:$V$41,Scenarios!$A$6:$A$41,cbo_tier_5,Scenarios!$B$6:$B$41,funder_tier_2) | D10: =SUMIFS(Scenarios!$V$6:$V$41,Scenarios!$A$6:$A$41,cbo_tier_5,Scenarios!$B$6:$B$41,funder_tier_3) | E10: =SUMIFS(Scenarios!$V$6:$V$41,Scenarios!$A$6:$A$41,cbo_tier_5,Scenarios!$B$6:$B$41,funder_tier_4) | F10: =SUMIFS(Scenarios!$V$6:$V$41,Scenarios!$A$6:$A$41,cbo_tier_5,Scenarios!$B$6:$B$41,funder_tier_5) | G10: =SUMIFS(Scenarios!$V$6:$V$41,Scenarios!$A$6:$A$41,cbo_tier_5,Scenarios!$B$6:$B$41,funder_tier_6)
A11: =cbo_tier_6 | B11: =SUMIFS(Scenarios!$V$6:$V$41,Scenarios!$A$6:$A$41,cbo_tier_6,Scenarios!$B$6:$B$41,funder_tier_1) | C11: =SUMIFS(Scenarios!$V$6:$V$41,Scenarios!$A$6:$A$41,cbo_tier_6,Scenarios!$B$6:$B$41,funder_tier_2) | D11: =SUMIFS(Scenarios!$V$6:$V$41,Scenarios!$A$6:$A$41,cbo_tier_6,Scenarios!$B$6:$B$41,funder_tier_3) | E11: =SUMIFS(Scenarios!$V$6:$V$41,Scenarios!$A$6:$A$41,cbo_tier_6,Scenarios!$B$6:$B$41,funder_tier_4) | F11: =SUMIFS(Scenarios!$V$6:$V$41,Scenarios!$A$6:$A$41,cbo_tier_6,Scenarios!$B$6:$B$41,funder_tier_5) | G11: =SUMIFS(Scenarios!$V$6:$V$41,Scenarios!$A$6:$A$41,cbo_tier_6,Scenarios!$B$6:$B$41,funder_tier_6)
A13: Monthly cost per active CBO
A14: The cost per organization falls as the fixed database bill is spread out, then levels off near the SMS cost. More funders barely change the cost per CBO until they force a larger database.
A16: Active funders → | B16: =funder_tier_1 | C16: =funder_tier_2 | D16: =funder_tier_3 | E16: =funder_tier_4 | F16: =funder_tier_5 | G16: =funder_tier_6
A17: =cbo_tier_1 | B17: =IF(A17=0,NA(),B6/A17) | C17: =IF(A17=0,NA(),C6/A17) | D17: =IF(A17=0,NA(),D6/A17) | E17: =IF(A17=0,NA(),E6/A17) | F17: =IF(A17=0,NA(),F6/A17) | G17: =IF(A17=0,NA(),G6/A17)
A18: =cbo_tier_2 | B18: =IF(A18=0,NA(),B7/A18) | C18: =IF(A18=0,NA(),C7/A18) | D18: =IF(A18=0,NA(),D7/A18) | E18: =IF(A18=0,NA(),E7/A18) | F18: =IF(A18=0,NA(),F7/A18) | G18: =IF(A18=0,NA(),G7/A18)
A19: =cbo_tier_3 | B19: =IF(A19=0,NA(),B8/A19) | C19: =IF(A19=0,NA(),C8/A19) | D19: =IF(A19=0,NA(),D8/A19) | E19: =IF(A19=0,NA(),E8/A19) | F19: =IF(A19=0,NA(),F8/A19) | G19: =IF(A19=0,NA(),G8/A19)
A20: =cbo_tier_4 | B20: =IF(A20=0,NA(),B9/A20) | C20: =IF(A20=0,NA(),C9/A20) | D20: =IF(A20=0,NA(),D9/A20) | E20: =IF(A20=0,NA(),E9/A20) | F20: =IF(A20=0,NA(),F9/A20) | G20: =IF(A20=0,NA(),G9/A20)
A21: =cbo_tier_5 | B21: =IF(A21=0,NA(),B10/A21) | C21: =IF(A21=0,NA(),C10/A21) | D21: =IF(A21=0,NA(),D10/A21) | E21: =IF(A21=0,NA(),E10/A21) | F21: =IF(A21=0,NA(),F10/A21) | G21: =IF(A21=0,NA(),G10/A21)
A22: =cbo_tier_6 | B22: =IF(A22=0,NA(),B11/A22) | C22: =IF(A22=0,NA(),C11/A22) | D22: =IF(A22=0,NA(),D11/A22) | E22: =IF(A22=0,NA(),E11/A22) | F22: =IF(A22=0,NA(),F11/A22) | G22: =IF(A22=0,NA(),G11/A22)

Sheet Annual matrix
A1: Annual cost
A2: Same active-funder count in each column, same active-CBO count in each row. Annual figures are the monthly run-rate times 12. They are not a growth path.
A4: Active funders → | B4: =funder_tier_1 | C4: =funder_tier_2 | D4: =funder_tier_3 | E4: =funder_tier_4 | F4: =funder_tier_5 | G4: =funder_tier_6
A5: Active CBOs ↓ | B5: USD / year | C5: USD / year | D5: USD / year | E5: USD / year | F5: USD / year | G5: USD / year
A6: =cbo_tier_1 | B6: =SUMIFS(Scenarios!$W$6:$W$41,Scenarios!$A$6:$A$41,cbo_tier_1,Scenarios!$B$6:$B$41,funder_tier_1) | C6: =SUMIFS(Scenarios!$W$6:$W$41,Scenarios!$A$6:$A$41,cbo_tier_1,Scenarios!$B$6:$B$41,funder_tier_2) | D6: =SUMIFS(Scenarios!$W$6:$W$41,Scenarios!$A$6:$A$41,cbo_tier_1,Scenarios!$B$6:$B$41,funder_tier_3) | E6: =SUMIFS(Scenarios!$W$6:$W$41,Scenarios!$A$6:$A$41,cbo_tier_1,Scenarios!$B$6:$B$41,funder_tier_4) | F6: =SUMIFS(Scenarios!$W$6:$W$41,Scenarios!$A$6:$A$41,cbo_tier_1,Scenarios!$B$6:$B$41,funder_tier_5) | G6: =SUMIFS(Scenarios!$W$6:$W$41,Scenarios!$A$6:$A$41,cbo_tier_1,Scenarios!$B$6:$B$41,funder_tier_6)
A7: =cbo_tier_2 | B7: =SUMIFS(Scenarios!$W$6:$W$41,Scenarios!$A$6:$A$41,cbo_tier_2,Scenarios!$B$6:$B$41,funder_tier_1) | C7: =SUMIFS(Scenarios!$W$6:$W$41,Scenarios!$A$6:$A$41,cbo_tier_2,Scenarios!$B$6:$B$41,funder_tier_2) | D7: =SUMIFS(Scenarios!$W$6:$W$41,Scenarios!$A$6:$A$41,cbo_tier_2,Scenarios!$B$6:$B$41,funder_tier_3) | E7: =SUMIFS(Scenarios!$W$6:$W$41,Scenarios!$A$6:$A$41,cbo_tier_2,Scenarios!$B$6:$B$41,funder_tier_4) | F7: =SUMIFS(Scenarios!$W$6:$W$41,Scenarios!$A$6:$A$41,cbo_tier_2,Scenarios!$B$6:$B$41,funder_tier_5) | G7: =SUMIFS(Scenarios!$W$6:$W$41,Scenarios!$A$6:$A$41,cbo_tier_2,Scenarios!$B$6:$B$41,funder_tier_6)
A8: =cbo_tier_3 | B8: =SUMIFS(Scenarios!$W$6:$W$41,Scenarios!$A$6:$A$41,cbo_tier_3,Scenarios!$B$6:$B$41,funder_tier_1) | C8: =SUMIFS(Scenarios!$W$6:$W$41,Scenarios!$A$6:$A$41,cbo_tier_3,Scenarios!$B$6:$B$41,funder_tier_2) | D8: =SUMIFS(Scenarios!$W$6:$W$41,Scenarios!$A$6:$A$41,cbo_tier_3,Scenarios!$B$6:$B$41,funder_tier_3) | E8: =SUMIFS(Scenarios!$W$6:$W$41,Scenarios!$A$6:$A$41,cbo_tier_3,Scenarios!$B$6:$B$41,funder_tier_4) | F8: =SUMIFS(Scenarios!$W$6:$W$41,Scenarios!$A$6:$A$41,cbo_tier_3,Scenarios!$B$6:$B$41,funder_tier_5) | G8: =SUMIFS(Scenarios!$W$6:$W$41,Scenarios!$A$6:$A$41,cbo_tier_3,Scenarios!$B$6:$B$41,funder_tier_6)
A9: =cbo_tier_4 | B9: =SUMIFS(Scenarios!$W$6:$W$41,Scenarios!$A$6:$A$41,cbo_tier_4,Scenarios!$B$6:$B$41,funder_tier_1) | C9: =SUMIFS(Scenarios!$W$6:$W$41,Scenarios!$A$6:$A$41,cbo_tier_4,Scenarios!$B$6:$B$41,funder_tier_2) | D9: =SUMIFS(Scenarios!$W$6:$W$41,Scenarios!$A$6:$A$41,cbo_tier_4,Scenarios!$B$6:$B$41,funder_tier_3) | E9: =SUMIFS(Scenarios!$W$6:$W$41,Scenarios!$A$6:$A$41,cbo_tier_4,Scenarios!$B$6:$B$41,funder_tier_4) | F9: =SUMIFS(Scenarios!$W$6:$W$41,Scenarios!$A$6:$A$41,cbo_tier_4,Scenarios!$B$6:$B$41,funder_tier_5) | G9: =SUMIFS(Scenarios!$W$6:$W$41,Scenarios!$A$6:$A$41,cbo_tier_4,Scenarios!$B$6:$B$41,funder_tier_6)
A10: =cbo_tier_5 | B10: =SUMIFS(Scenarios!$W$6:$W$41,Scenarios!$A$6:$A$41,cbo_tier_5,Scenarios!$B$6:$B$41,funder_tier_1) | C10: =SUMIFS(Scenarios!$W$6:$W$41,Scenarios!$A$6:$A$41,cbo_tier_5,Scenarios!$B$6:$B$41,funder_tier_2) | D10: =SUMIFS(Scenarios!$W$6:$W$41,Scenarios!$A$6:$A$41,cbo_tier_5,Scenarios!$B$6:$B$41,funder_tier_3) | E10: =SUMIFS(Scenarios!$W$6:$W$41,Scenarios!$A$6:$A$41,cbo_tier_5,Scenarios!$B$6:$B$41,funder_tier_4) | F10: =SUMIFS(Scenarios!$W$6:$W$41,Scenarios!$A$6:$A$41,cbo_tier_5,Scenarios!$B$6:$B$41,funder_tier_5) | G10: =SUMIFS(Scenarios!$W$6:$W$41,Scenarios!$A$6:$A$41,cbo_tier_5,Scenarios!$B$6:$B$41,funder_tier_6)
A11: =cbo_tier_6 | B11: =SUMIFS(Scenarios!$W$6:$W$41,Scenarios!$A$6:$A$41,cbo_tier_6,Scenarios!$B$6:$B$41,funder_tier_1) | C11: =SUMIFS(Scenarios!$W$6:$W$41,Scenarios!$A$6:$A$41,cbo_tier_6,Scenarios!$B$6:$B$41,funder_tier_2) | D11: =SUMIFS(Scenarios!$W$6:$W$41,Scenarios!$A$6:$A$41,cbo_tier_6,Scenarios!$B$6:$B$41,funder_tier_3) | E11: =SUMIFS(Scenarios!$W$6:$W$41,Scenarios!$A$6:$A$41,cbo_tier_6,Scenarios!$B$6:$B$41,funder_tier_4) | F11: =SUMIFS(Scenarios!$W$6:$W$41,Scenarios!$A$6:$A$41,cbo_tier_6,Scenarios!$B$6:$B$41,funder_tier_5) | G11: =SUMIFS(Scenarios!$W$6:$W$41,Scenarios!$A$6:$A$41,cbo_tier_6,Scenarios!$B$6:$B$41,funder_tier_6)
A13: Annual cost per active CBO
A14: The cost per organization falls as the fixed database bill is spread out, then levels off near the SMS cost. More funders barely change the cost per CBO until they force a larger database.
A16: Active funders → | B16: =funder_tier_1 | C16: =funder_tier_2 | D16: =funder_tier_3 | E16: =funder_tier_4 | F16: =funder_tier_5 | G16: =funder_tier_6
A17: =cbo_tier_1 | B17: =IF(A17=0,NA(),B6/A17) | C17: =IF(A17=0,NA(),C6/A17) | D17: =IF(A17=0,NA(),D6/A17) | E17: =IF(A17=0,NA(),E6/A17) | F17: =IF(A17=0,NA(),F6/A17) | G17: =IF(A17=0,NA(),G6/A17)
A18: =cbo_tier_2 | B18: =IF(A18=0,NA(),B7/A18) | C18: =IF(A18=0,NA(),C7/A18) | D18: =IF(A18=0,NA(),D7/A18) | E18: =IF(A18=0,NA(),E7/A18) | F18: =IF(A18=0,NA(),F7/A18) | G18: =IF(A18=0,NA(),G7/A18)
A19: =cbo_tier_3 | B19: =IF(A19=0,NA(),B8/A19) | C19: =IF(A19=0,NA(),C8/A19) | D19: =IF(A19=0,NA(),D8/A19) | E19: =IF(A19=0,NA(),E8/A19) | F19: =IF(A19=0,NA(),F8/A19) | G19: =IF(A19=0,NA(),G8/A19)
A20: =cbo_tier_4 | B20: =IF(A20=0,NA(),B9/A20) | C20: =IF(A20=0,NA(),C9/A20) | D20: =IF(A20=0,NA(),D9/A20) | E20: =IF(A20=0,NA(),E9/A20) | F20: =IF(A20=0,NA(),F9/A20) | G20: =IF(A20=0,NA(),G9/A20)
A21: =cbo_tier_5 | B21: =IF(A21=0,NA(),B10/A21) | C21: =IF(A21=0,NA(),C10/A21) | D21: =IF(A21=0,NA(),D10/A21) | E21: =IF(A21=0,NA(),E10/A21) | F21: =IF(A21=0,NA(),F10/A21) | G21: =IF(A21=0,NA(),G10/A21)
A22: =cbo_tier_6 | B22: =IF(A22=0,NA(),B11/A22) | C22: =IF(A22=0,NA(),C11/A22) | D22: =IF(A22=0,NA(),D11/A22) | E22: =IF(A22=0,NA(),E11/A22) | F22: =IF(A22=0,NA(),F11/A22) | G22: =IF(A22=0,NA(),G11/A22)

Sheet Matched growth
A1: Matched growth
A2: Both sides grow together: 10 funders with 10 CBOs, then 25 with 25, and so on. This is the simplest reading of the full grid.
A4: Active on each side | B4: Database | C4: Rest of hosting | D4: SMS | E4: Documents | F4: Funder tools and research | G4: Monthly total | H4: Annual total | I4: Per CBO | J4: SMS share | K4: Increase from prior tier | L4: Map loads | M4: Search queries | N4: vCPU-seconds used
A5: =cbo_tier_1 | B5: =SUMIFS(Scenarios!$C$6:$C$41,Scenarios!$A$6:$A$41,cbo_tier_1,Scenarios!$B$6:$B$41,cbo_tier_1) | C5: =(SUMIFS(Scenarios!$D$6:$D$41,Scenarios!$A$6:$A$41,cbo_tier_1,Scenarios!$B$6:$B$41,cbo_tier_1))+(SUMIFS(Scenarios!$E$6:$E$41,Scenarios!$A$6:$A$41,cbo_tier_1,Scenarios!$B$6:$B$41,cbo_tier_1))+(SUMIFS(Scenarios!$F$6:$F$41,Scenarios!$A$6:$A$41,cbo_tier_1,Scenarios!$B$6:$B$41,cbo_tier_1))+(SUMIFS(Scenarios!$G$6:$G$41,Scenarios!$A$6:$A$41,cbo_tier_1,Scenarios!$B$6:$B$41,cbo_tier_1))+(SUMIFS(Scenarios!$H$6:$H$41,Scenarios!$A$6:$A$41,cbo_tier_1,Scenarios!$B$6:$B$41,cbo_tier_1)) | D5: =(SUMIFS(Scenarios!$I$6:$I$41,Scenarios!$A$6:$A$41,cbo_tier_1,Scenarios!$B$6:$B$41,cbo_tier_1))+(SUMIFS(Scenarios!$J$6:$J$41,Scenarios!$A$6:$A$41,cbo_tier_1,Scenarios!$B$6:$B$41,cbo_tier_1)) | E5: =(SUMIFS(Scenarios!$K$6:$K$41,Scenarios!$A$6:$A$41,cbo_tier_1,Scenarios!$B$6:$B$41,cbo_tier_1))+(SUMIFS(Scenarios!$L$6:$L$41,Scenarios!$A$6:$A$41,cbo_tier_1,Scenarios!$B$6:$B$41,cbo_tier_1)) | F5: =(SUMIFS(Scenarios!$M$6:$M$41,Scenarios!$A$6:$A$41,cbo_tier_1,Scenarios!$B$6:$B$41,cbo_tier_1))+(SUMIFS(Scenarios!$N$6:$N$41,Scenarios!$A$6:$A$41,cbo_tier_1,Scenarios!$B$6:$B$41,cbo_tier_1))+(SUMIFS(Scenarios!$O$6:$O$41,Scenarios!$A$6:$A$41,cbo_tier_1,Scenarios!$B$6:$B$41,cbo_tier_1))+(SUMIFS(Scenarios!$P$6:$P$41,Scenarios!$A$6:$A$41,cbo_tier_1,Scenarios!$B$6:$B$41,cbo_tier_1))+(SUMIFS(Scenarios!$Q$6:$Q$41,Scenarios!$A$6:$A$41,cbo_tier_1,Scenarios!$B$6:$B$41,cbo_tier_1))+(SUMIFS(Scenarios!$R$6:$R$41,Scenarios!$A$6:$A$41,cbo_tier_1,Scenarios!$B$6:$B$41,cbo_tier_1))+(SUMIFS(Scenarios!$S$6:$S$41,Scenarios!$A$6:$A$41,cbo_tier_1,Scenarios!$B$6:$B$41,cbo_tier_1))+(SUMIFS(Scenarios!$T$6:$T$41,Scenarios!$A$6:$A$41,cbo_tier_1,Scenarios!$B$6:$B$41,cbo_tier_1))+(SUMIFS(Scenarios!$U$6:$U$41,Scenarios!$A$6:$A$41,cbo_tier_1,Scenarios!$B$6:$B$41,cbo_tier_1)) | G5: =SUM(B5:F5) | H5: =G5*12 | I5: =IF(A5=0,NA(),G5/A5) | J5: =IF(G5=0,0,D5/G5) | K5: — | L5: SUMIFS(Scenarios!$AA$6:$AA$41,Scenarios!$A$6:$A$41,cbo_tier_1,Scenarios!$B$6:$B$41,cbo_tier_1) | M5: SUMIFS(Scenarios!$AB$6:$AB$41,Scenarios!$A$6:$A$41,cbo_tier_1,Scenarios!$B$6:$B$41,cbo_tier_1) | N5: SUMIFS(Scenarios!$AC$6:$AC$41,Scenarios!$A$6:$A$41,cbo_tier_1,Scenarios!$B$6:$B$41,cbo_tier_1)
A6: =cbo_tier_2 | B6: =SUMIFS(Scenarios!$C$6:$C$41,Scenarios!$A$6:$A$41,cbo_tier_2,Scenarios!$B$6:$B$41,cbo_tier_2) | C6: =(SUMIFS(Scenarios!$D$6:$D$41,Scenarios!$A$6:$A$41,cbo_tier_2,Scenarios!$B$6:$B$41,cbo_tier_2))+(SUMIFS(Scenarios!$E$6:$E$41,Scenarios!$A$6:$A$41,cbo_tier_2,Scenarios!$B$6:$B$41,cbo_tier_2))+(SUMIFS(Scenarios!$F$6:$F$41,Scenarios!$A$6:$A$41,cbo_tier_2,Scenarios!$B$6:$B$41,cbo_tier_2))+(SUMIFS(Scenarios!$G$6:$G$41,Scenarios!$A$6:$A$41,cbo_tier_2,Scenarios!$B$6:$B$41,cbo_tier_2))+(SUMIFS(Scenarios!$H$6:$H$41,Scenarios!$A$6:$A$41,cbo_tier_2,Scenarios!$B$6:$B$41,cbo_tier_2)) | D6: =(SUMIFS(Scenarios!$I$6:$I$41,Scenarios!$A$6:$A$41,cbo_tier_2,Scenarios!$B$6:$B$41,cbo_tier_2))+(SUMIFS(Scenarios!$J$6:$J$41,Scenarios!$A$6:$A$41,cbo_tier_2,Scenarios!$B$6:$B$41,cbo_tier_2)) | E6: =(SUMIFS(Scenarios!$K$6:$K$41,Scenarios!$A$6:$A$41,cbo_tier_2,Scenarios!$B$6:$B$41,cbo_tier_2))+(SUMIFS(Scenarios!$L$6:$L$41,Scenarios!$A$6:$A$41,cbo_tier_2,Scenarios!$B$6:$B$41,cbo_tier_2)) | F6: =(SUMIFS(Scenarios!$M$6:$M$41,Scenarios!$A$6:$A$41,cbo_tier_2,Scenarios!$B$6:$B$41,cbo_tier_2))+(SUMIFS(Scenarios!$N$6:$N$41,Scenarios!$A$6:$A$41,cbo_tier_2,Scenarios!$B$6:$B$41,cbo_tier_2))+(SUMIFS(Scenarios!$O$6:$O$41,Scenarios!$A$6:$A$41,cbo_tier_2,Scenarios!$B$6:$B$41,cbo_tier_2))+(SUMIFS(Scenarios!$P$6:$P$41,Scenarios!$A$6:$A$41,cbo_tier_2,Scenarios!$B$6:$B$41,cbo_tier_2))+(SUMIFS(Scenarios!$Q$6:$Q$41,Scenarios!$A$6:$A$41,cbo_tier_2,Scenarios!$B$6:$B$41,cbo_tier_2))+(SUMIFS(Scenarios!$R$6:$R$41,Scenarios!$A$6:$A$41,cbo_tier_2,Scenarios!$B$6:$B$41,cbo_tier_2))+(SUMIFS(Scenarios!$S$6:$S$41,Scenarios!$A$6:$A$41,cbo_tier_2,Scenarios!$B$6:$B$41,cbo_tier_2))+(SUMIFS(Scenarios!$T$6:$T$41,Scenarios!$A$6:$A$41,cbo_tier_2,Scenarios!$B$6:$B$41,cbo_tier_2))+(SUMIFS(Scenarios!$U$6:$U$41,Scenarios!$A$6:$A$41,cbo_tier_2,Scenarios!$B$6:$B$41,cbo_tier_2)) | G6: =SUM(B6:F6) | H6: =G6*12 | I6: =IF(A6=0,NA(),G6/A6) | J6: =IF(G6=0,0,D6/G6) | K6: =G6-G5 | L6: SUMIFS(Scenarios!$AA$6:$AA$41,Scenarios!$A$6:$A$41,cbo_tier_2,Scenarios!$B$6:$B$41,cbo_tier_2) | M6: SUMIFS(Scenarios!$AB$6:$AB$41,Scenarios!$A$6:$A$41,cbo_tier_2,Scenarios!$B$6:$B$41,cbo_tier_2) | N6: SUMIFS(Scenarios!$AC$6:$AC$41,Scenarios!$A$6:$A$41,cbo_tier_2,Scenarios!$B$6:$B$41,cbo_tier_2)
A7: =cbo_tier_3 | B7: =SUMIFS(Scenarios!$C$6:$C$41,Scenarios!$A$6:$A$41,cbo_tier_3,Scenarios!$B$6:$B$41,cbo_tier_3) | C7: =(SUMIFS(Scenarios!$D$6:$D$41,Scenarios!$A$6:$A$41,cbo_tier_3,Scenarios!$B$6:$B$41,cbo_tier_3))+(SUMIFS(Scenarios!$E$6:$E$41,Scenarios!$A$6:$A$41,cbo_tier_3,Scenarios!$B$6:$B$41,cbo_tier_3))+(SUMIFS(Scenarios!$F$6:$F$41,Scenarios!$A$6:$A$41,cbo_tier_3,Scenarios!$B$6:$B$41,cbo_tier_3))+(SUMIFS(Scenarios!$G$6:$G$41,Scenarios!$A$6:$A$41,cbo_tier_3,Scenarios!$B$6:$B$41,cbo_tier_3))+(SUMIFS(Scenarios!$H$6:$H$41,Scenarios!$A$6:$A$41,cbo_tier_3,Scenarios!$B$6:$B$41,cbo_tier_3)) | D7: =(SUMIFS(Scenarios!$I$6:$I$41,Scenarios!$A$6:$A$41,cbo_tier_3,Scenarios!$B$6:$B$41,cbo_tier_3))+(SUMIFS(Scenarios!$J$6:$J$41,Scenarios!$A$6:$A$41,cbo_tier_3,Scenarios!$B$6:$B$41,cbo_tier_3)) | E7: =(SUMIFS(Scenarios!$K$6:$K$41,Scenarios!$A$6:$A$41,cbo_tier_3,Scenarios!$B$6:$B$41,cbo_tier_3))+(SUMIFS(Scenarios!$L$6:$L$41,Scenarios!$A$6:$A$41,cbo_tier_3,Scenarios!$B$6:$B$41,cbo_tier_3)) | F7: =(SUMIFS(Scenarios!$M$6:$M$41,Scenarios!$A$6:$A$41,cbo_tier_3,Scenarios!$B$6:$B$41,cbo_tier_3))+(SUMIFS(Scenarios!$N$6:$N$41,Scenarios!$A$6:$A$41,cbo_tier_3,Scenarios!$B$6:$B$41,cbo_tier_3))+(SUMIFS(Scenarios!$O$6:$O$41,Scenarios!$A$6:$A$41,cbo_tier_3,Scenarios!$B$6:$B$41,cbo_tier_3))+(SUMIFS(Scenarios!$P$6:$P$41,Scenarios!$A$6:$A$41,cbo_tier_3,Scenarios!$B$6:$B$41,cbo_tier_3))+(SUMIFS(Scenarios!$Q$6:$Q$41,Scenarios!$A$6:$A$41,cbo_tier_3,Scenarios!$B$6:$B$41,cbo_tier_3))+(SUMIFS(Scenarios!$R$6:$R$41,Scenarios!$A$6:$A$41,cbo_tier_3,Scenarios!$B$6:$B$41,cbo_tier_3))+(SUMIFS(Scenarios!$S$6:$S$41,Scenarios!$A$6:$A$41,cbo_tier_3,Scenarios!$B$6:$B$41,cbo_tier_3))+(SUMIFS(Scenarios!$T$6:$T$41,Scenarios!$A$6:$A$41,cbo_tier_3,Scenarios!$B$6:$B$41,cbo_tier_3))+(SUMIFS(Scenarios!$U$6:$U$41,Scenarios!$A$6:$A$41,cbo_tier_3,Scenarios!$B$6:$B$41,cbo_tier_3)) | G7: =SUM(B7:F7) | H7: =G7*12 | I7: =IF(A7=0,NA(),G7/A7) | J7: =IF(G7=0,0,D7/G7) | K7: =G7-G6 | L7: SUMIFS(Scenarios!$AA$6:$AA$41,Scenarios!$A$6:$A$41,cbo_tier_3,Scenarios!$B$6:$B$41,cbo_tier_3) | M7: SUMIFS(Scenarios!$AB$6:$AB$41,Scenarios!$A$6:$A$41,cbo_tier_3,Scenarios!$B$6:$B$41,cbo_tier_3) | N7: SUMIFS(Scenarios!$AC$6:$AC$41,Scenarios!$A$6:$A$41,cbo_tier_3,Scenarios!$B$6:$B$41,cbo_tier_3)
A8: =cbo_tier_4 | B8: =SUMIFS(Scenarios!$C$6:$C$41,Scenarios!$A$6:$A$41,cbo_tier_4,Scenarios!$B$6:$B$41,cbo_tier_4) | C8: =(SUMIFS(Scenarios!$D$6:$D$41,Scenarios!$A$6:$A$41,cbo_tier_4,Scenarios!$B$6:$B$41,cbo_tier_4))+(SUMIFS(Scenarios!$E$6:$E$41,Scenarios!$A$6:$A$41,cbo_tier_4,Scenarios!$B$6:$B$41,cbo_tier_4))+(SUMIFS(Scenarios!$F$6:$F$41,Scenarios!$A$6:$A$41,cbo_tier_4,Scenarios!$B$6:$B$41,cbo_tier_4))+(SUMIFS(Scenarios!$G$6:$G$41,Scenarios!$A$6:$A$41,cbo_tier_4,Scenarios!$B$6:$B$41,cbo_tier_4))+(SUMIFS(Scenarios!$H$6:$H$41,Scenarios!$A$6:$A$41,cbo_tier_4,Scenarios!$B$6:$B$41,cbo_tier_4)) | D8: =(SUMIFS(Scenarios!$I$6:$I$41,Scenarios!$A$6:$A$41,cbo_tier_4,Scenarios!$B$6:$B$41,cbo_tier_4))+(SUMIFS(Scenarios!$J$6:$J$41,Scenarios!$A$6:$A$41,cbo_tier_4,Scenarios!$B$6:$B$41,cbo_tier_4)) | E8: =(SUMIFS(Scenarios!$K$6:$K$41,Scenarios!$A$6:$A$41,cbo_tier_4,Scenarios!$B$6:$B$41,cbo_tier_4))+(SUMIFS(Scenarios!$L$6:$L$41,Scenarios!$A$6:$A$41,cbo_tier_4,Scenarios!$B$6:$B$41,cbo_tier_4)) | F8: =(SUMIFS(Scenarios!$M$6:$M$41,Scenarios!$A$6:$A$41,cbo_tier_4,Scenarios!$B$6:$B$41,cbo_tier_4))+(SUMIFS(Scenarios!$N$6:$N$41,Scenarios!$A$6:$A$41,cbo_tier_4,Scenarios!$B$6:$B$41,cbo_tier_4))+(SUMIFS(Scenarios!$O$6:$O$41,Scenarios!$A$6:$A$41,cbo_tier_4,Scenarios!$B$6:$B$41,cbo_tier_4))+(SUMIFS(Scenarios!$P$6:$P$41,Scenarios!$A$6:$A$41,cbo_tier_4,Scenarios!$B$6:$B$41,cbo_tier_4))+(SUMIFS(Scenarios!$Q$6:$Q$41,Scenarios!$A$6:$A$41,cbo_tier_4,Scenarios!$B$6:$B$41,cbo_tier_4))+(SUMIFS(Scenarios!$R$6:$R$41,Scenarios!$A$6:$A$41,cbo_tier_4,Scenarios!$B$6:$B$41,cbo_tier_4))+(SUMIFS(Scenarios!$S$6:$S$41,Scenarios!$A$6:$A$41,cbo_tier_4,Scenarios!$B$6:$B$41,cbo_tier_4))+(SUMIFS(Scenarios!$T$6:$T$41,Scenarios!$A$6:$A$41,cbo_tier_4,Scenarios!$B$6:$B$41,cbo_tier_4))+(SUMIFS(Scenarios!$U$6:$U$41,Scenarios!$A$6:$A$41,cbo_tier_4,Scenarios!$B$6:$B$41,cbo_tier_4)) | G8: =SUM(B8:F8) | H8: =G8*12 | I8: =IF(A8=0,NA(),G8/A8) | J8: =IF(G8=0,0,D8/G8) | K8: =G8-G7 | L8: SUMIFS(Scenarios!$AA$6:$AA$41,Scenarios!$A$6:$A$41,cbo_tier_4,Scenarios!$B$6:$B$41,cbo_tier_4) | M8: SUMIFS(Scenarios!$AB$6:$AB$41,Scenarios!$A$6:$A$41,cbo_tier_4,Scenarios!$B$6:$B$41,cbo_tier_4) | N8: SUMIFS(Scenarios!$AC$6:$AC$41,Scenarios!$A$6:$A$41,cbo_tier_4,Scenarios!$B$6:$B$41,cbo_tier_4)
A9: =cbo_tier_5 | B9: =SUMIFS(Scenarios!$C$6:$C$41,Scenarios!$A$6:$A$41,cbo_tier_5,Scenarios!$B$6:$B$41,cbo_tier_5) | C9: =(SUMIFS(Scenarios!$D$6:$D$41,Scenarios!$A$6:$A$41,cbo_tier_5,Scenarios!$B$6:$B$41,cbo_tier_5))+(SUMIFS(Scenarios!$E$6:$E$41,Scenarios!$A$6:$A$41,cbo_tier_5,Scenarios!$B$6:$B$41,cbo_tier_5))+(SUMIFS(Scenarios!$F$6:$F$41,Scenarios!$A$6:$A$41,cbo_tier_5,Scenarios!$B$6:$B$41,cbo_tier_5))+(SUMIFS(Scenarios!$G$6:$G$41,Scenarios!$A$6:$A$41,cbo_tier_5,Scenarios!$B$6:$B$41,cbo_tier_5))+(SUMIFS(Scenarios!$H$6:$H$41,Scenarios!$A$6:$A$41,cbo_tier_5,Scenarios!$B$6:$B$41,cbo_tier_5)) | D9: =(SUMIFS(Scenarios!$I$6:$I$41,Scenarios!$A$6:$A$41,cbo_tier_5,Scenarios!$B$6:$B$41,cbo_tier_5))+(SUMIFS(Scenarios!$J$6:$J$41,Scenarios!$A$6:$A$41,cbo_tier_5,Scenarios!$B$6:$B$41,cbo_tier_5)) | E9: =(SUMIFS(Scenarios!$K$6:$K$41,Scenarios!$A$6:$A$41,cbo_tier_5,Scenarios!$B$6:$B$41,cbo_tier_5))+(SUMIFS(Scenarios!$L$6:$L$41,Scenarios!$A$6:$A$41,cbo_tier_5,Scenarios!$B$6:$B$41,cbo_tier_5)) | F9: =(SUMIFS(Scenarios!$M$6:$M$41,Scenarios!$A$6:$A$41,cbo_tier_5,Scenarios!$B$6:$B$41,cbo_tier_5))+(SUMIFS(Scenarios!$N$6:$N$41,Scenarios!$A$6:$A$41,cbo_tier_5,Scenarios!$B$6:$B$41,cbo_tier_5))+(SUMIFS(Scenarios!$O$6:$O$41,Scenarios!$A$6:$A$41,cbo_tier_5,Scenarios!$B$6:$B$41,cbo_tier_5))+(SUMIFS(Scenarios!$P$6:$P$41,Scenarios!$A$6:$A$41,cbo_tier_5,Scenarios!$B$6:$B$41,cbo_tier_5))+(SUMIFS(Scenarios!$Q$6:$Q$41,Scenarios!$A$6:$A$41,cbo_tier_5,Scenarios!$B$6:$B$41,cbo_tier_5))+(SUMIFS(Scenarios!$R$6:$R$41,Scenarios!$A$6:$A$41,cbo_tier_5,Scenarios!$B$6:$B$41,cbo_tier_5))+(SUMIFS(Scenarios!$S$6:$S$41,Scenarios!$A$6:$A$41,cbo_tier_5,Scenarios!$B$6:$B$41,cbo_tier_5))+(SUMIFS(Scenarios!$T$6:$T$41,Scenarios!$A$6:$A$41,cbo_tier_5,Scenarios!$B$6:$B$41,cbo_tier_5))+(SUMIFS(Scenarios!$U$6:$U$41,Scenarios!$A$6:$A$41,cbo_tier_5,Scenarios!$B$6:$B$41,cbo_tier_5)) | G9: =SUM(B9:F9) | H9: =G9*12 | I9: =IF(A9=0,NA(),G9/A9) | J9: =IF(G9=0,0,D9/G9) | K9: =G9-G8 | L9: SUMIFS(Scenarios!$AA$6:$AA$41,Scenarios!$A$6:$A$41,cbo_tier_5,Scenarios!$B$6:$B$41,cbo_tier_5) | M9: SUMIFS(Scenarios!$AB$6:$AB$41,Scenarios!$A$6:$A$41,cbo_tier_5,Scenarios!$B$6:$B$41,cbo_tier_5) | N9: SUMIFS(Scenarios!$AC$6:$AC$41,Scenarios!$A$6:$A$41,cbo_tier_5,Scenarios!$B$6:$B$41,cbo_tier_5)
A10: =cbo_tier_6 | B10: =SUMIFS(Scenarios!$C$6:$C$41,Scenarios!$A$6:$A$41,cbo_tier_6,Scenarios!$B$6:$B$41,cbo_tier_6) | C10: =(SUMIFS(Scenarios!$D$6:$D$41,Scenarios!$A$6:$A$41,cbo_tier_6,Scenarios!$B$6:$B$41,cbo_tier_6))+(SUMIFS(Scenarios!$E$6:$E$41,Scenarios!$A$6:$A$41,cbo_tier_6,Scenarios!$B$6:$B$41,cbo_tier_6))+(SUMIFS(Scenarios!$F$6:$F$41,Scenarios!$A$6:$A$41,cbo_tier_6,Scenarios!$B$6:$B$41,cbo_tier_6))+(SUMIFS(Scenarios!$G$6:$G$41,Scenarios!$A$6:$A$41,cbo_tier_6,Scenarios!$B$6:$B$41,cbo_tier_6))+(SUMIFS(Scenarios!$H$6:$H$41,Scenarios!$A$6:$A$41,cbo_tier_6,Scenarios!$B$6:$B$41,cbo_tier_6)) | D10: =(SUMIFS(Scenarios!$I$6:$I$41,Scenarios!$A$6:$A$41,cbo_tier_6,Scenarios!$B$6:$B$41,cbo_tier_6))+(SUMIFS(Scenarios!$J$6:$J$41,Scenarios!$A$6:$A$41,cbo_tier_6,Scenarios!$B$6:$B$41,cbo_tier_6)) | E10: =(SUMIFS(Scenarios!$K$6:$K$41,Scenarios!$A$6:$A$41,cbo_tier_6,Scenarios!$B$6:$B$41,cbo_tier_6))+(SUMIFS(Scenarios!$L$6:$L$41,Scenarios!$A$6:$A$41,cbo_tier_6,Scenarios!$B$6:$B$41,cbo_tier_6)) | F10: =(SUMIFS(Scenarios!$M$6:$M$41,Scenarios!$A$6:$A$41,cbo_tier_6,Scenarios!$B$6:$B$41,cbo_tier_6))+(SUMIFS(Scenarios!$N$6:$N$41,Scenarios!$A$6:$A$41,cbo_tier_6,Scenarios!$B$6:$B$41,cbo_tier_6))+(SUMIFS(Scenarios!$O$6:$O$41,Scenarios!$A$6:$A$41,cbo_tier_6,Scenarios!$B$6:$B$41,cbo_tier_6))+(SUMIFS(Scenarios!$P$6:$P$41,Scenarios!$A$6:$A$41,cbo_tier_6,Scenarios!$B$6:$B$41,cbo_tier_6))+(SUMIFS(Scenarios!$Q$6:$Q$41,Scenarios!$A$6:$A$41,cbo_tier_6,Scenarios!$B$6:$B$41,cbo_tier_6))+(SUMIFS(Scenarios!$R$6:$R$41,Scenarios!$A$6:$A$41,cbo_tier_6,Scenarios!$B$6:$B$41,cbo_tier_6))+(SUMIFS(Scenarios!$S$6:$S$41,Scenarios!$A$6:$A$41,cbo_tier_6,Scenarios!$B$6:$B$41,cbo_tier_6))+(SUMIFS(Scenarios!$T$6:$T$41,Scenarios!$A$6:$A$41,cbo_tier_6,Scenarios!$B$6:$B$41,cbo_tier_6))+(SUMIFS(Scenarios!$U$6:$U$41,Scenarios!$A$6:$A$41,cbo_tier_6,Scenarios!$B$6:$B$41,cbo_tier_6)) | G10: =SUM(B10:F10) | H10: =G10*12 | I10: =IF(A10=0,NA(),G10/A10) | J10: =IF(G10=0,0,D10/G10) | K10: =G10-G9 | L10: SUMIFS(Scenarios!$AA$6:$AA$41,Scenarios!$A$6:$A$41,cbo_tier_6,Scenarios!$B$6:$B$41,cbo_tier_6) | M10: SUMIFS(Scenarios!$AB$6:$AB$41,Scenarios!$A$6:$A$41,cbo_tier_6,Scenarios!$B$6:$B$41,cbo_tier_6) | N10: SUMIFS(Scenarios!$AC$6:$AC$41,Scenarios!$A$6:$A$41,cbo_tier_6,Scenarios!$B$6:$B$41,cbo_tier_6)
A32: How to read the steps
A33: From 10 to 100, the bill climbs almost in line with CBOs, because each organization adds the same SMS and document cost and the database does not change. Crossing 200 raises the database even if the other costs only double. Crossing 500 raises it again. Funder search, Maps, and Cloud Run stay small on this path: map loads at 500 funders are 500 times 6, which is under the 10,000 free loads, and web research stays under the free search quota.

Sheet Sensitivity
A1: What changes the bill
A2: These cases change one behavior at a time, for the matched tiers only. They do not change Assumptions. Yellow cells are the alternate settings.
A3: Alternate setting | B3: Value | C3: Note
A4: Check-ins per year in the heavy case | B4: 12 | C4: The app default is 2.
A5: Texters per CBO in the heavy case | B5: 25 | C5: The base case uses the Assumptions panel size.
A6: If each text runs long | B6: 1.5 | C6: 1.5 means the average text takes one and a half segments.
A7: Map loads per funder | B7: 30 | C7: Base case is 6. Thirty is about a visit most weekdays. 500 funders then pass the free Maps allowance.
A8: AI searches per funder | B8: 15 | C8: Base case is 3.
A9: Gemini price multiple | B9: 5 | C9: 5× stands in for a higher-priced Flash model than the efficient rate.
A11: Active on each side | B11: Base monthly | C11: Check-ins at the heavy rate | D11: More texters per CBO | E11: Heavy check-ins and more texters | F11: Longer texts | G11: Heavier map use | H11: Heavier AI search | I11: Higher Gemini price
A12: =cbo_tier_1 | B12: =SUMIFS(Scenarios!$V$6:$V$41,Scenarios!$A$6:$A$41,cbo_tier_1,Scenarios!$B$6:$B$41,cbo_tier_1) | C12: =SUMIFS(Scenarios!$V$6:$V$41,Scenarios!$A$6:$A$41,cbo_tier_1,Scenarios!$B$6:$B$41,cbo_tier_1)-(SUMIFS(Scenarios!$I$6:$I$41,Scenarios!$A$6:$A$41,cbo_tier_1,Scenarios!$B$6:$B$41,cbo_tier_1)+SUMIFS(Scenarios!$J$6:$J$41,Scenarios!$A$6:$A$41,cbo_tier_1,Scenarios!$B$6:$B$41,cbo_tier_1)+SUMIFS(Scenarios!$P$6:$P$41,Scenarios!$A$6:$A$41,cbo_tier_1,Scenarios!$B$6:$B$41,cbo_tier_1))+(SUMIFS(Scenarios!$I$6:$I$41,Scenarios!$A$6:$A$41,cbo_tier_1,Scenarios!$B$6:$B$41,cbo_tier_1)+SUMIFS(Scenarios!$J$6:$J$41,Scenarios!$A$6:$A$41,cbo_tier_1,Scenarios!$B$6:$B$41,cbo_tier_1)+SUMIFS(Scenarios!$P$6:$P$41,Scenarios!$A$6:$A$41,cbo_tier_1,Scenarios!$B$6:$B$41,cbo_tier_1))*(sens_checkins/checkins_per_year) | D12: =SUMIFS(Scenarios!$V$6:$V$41,Scenarios!$A$6:$A$41,cbo_tier_1,Scenarios!$B$6:$B$41,cbo_tier_1)-(SUMIFS(Scenarios!$I$6:$I$41,Scenarios!$A$6:$A$41,cbo_tier_1,Scenarios!$B$6:$B$41,cbo_tier_1)+SUMIFS(Scenarios!$J$6:$J$41,Scenarios!$A$6:$A$41,cbo_tier_1,Scenarios!$B$6:$B$41,cbo_tier_1)+SUMIFS(Scenarios!$P$6:$P$41,Scenarios!$A$6:$A$41,cbo_tier_1,Scenarios!$B$6:$B$41,cbo_tier_1))+(SUMIFS(Scenarios!$I$6:$I$41,Scenarios!$A$6:$A$41,cbo_tier_1,Scenarios!$B$6:$B$41,cbo_tier_1)+SUMIFS(Scenarios!$J$6:$J$41,Scenarios!$A$6:$A$41,cbo_tier_1,Scenarios!$B$6:$B$41,cbo_tier_1)+SUMIFS(Scenarios!$P$6:$P$41,Scenarios!$A$6:$A$41,cbo_tier_1,Scenarios!$B$6:$B$41,cbo_tier_1))*(sens_subscribers/subscribers_per_cbo) | E12: =SUMIFS(Scenarios!$V$6:$V$41,Scenarios!$A$6:$A$41,cbo_tier_1,Scenarios!$B$6:$B$41,cbo_tier_1)-(SUMIFS(Scenarios!$I$6:$I$41,Scenarios!$A$6:$A$41,cbo_tier_1,Scenarios!$B$6:$B$41,cbo_tier_1)+SUMIFS(Scenarios!$J$6:$J$41,Scenarios!$A$6:$A$41,cbo_tier_1,Scenarios!$B$6:$B$41,cbo_tier_1)+SUMIFS(Scenarios!$P$6:$P$41,Scenarios!$A$6:$A$41,cbo_tier_1,Scenarios!$B$6:$B$41,cbo_tier_1))+(SUMIFS(Scenarios!$I$6:$I$41,Scenarios!$A$6:$A$41,cbo_tier_1,Scenarios!$B$6:$B$41,cbo_tier_1)+SUMIFS(Scenarios!$J$6:$J$41,Scenarios!$A$6:$A$41,cbo_tier_1,Scenarios!$B$6:$B$41,cbo_tier_1)+SUMIFS(Scenarios!$P$6:$P$41,Scenarios!$A$6:$A$41,cbo_tier_1,Scenarios!$B$6:$B$41,cbo_tier_1))*(sens_checkins/checkins_per_year)*(sens_subscribers/subscribers_per_cbo) | F12: =SUMIFS(Scenarios!$V$6:$V$41,Scenarios!$A$6:$A$41,cbo_tier_1,Scenarios!$B$6:$B$41,cbo_tier_1)-(SUMIFS(Scenarios!$I$6:$I$41,Scenarios!$A$6:$A$41,cbo_tier_1,Scenarios!$B$6:$B$41,cbo_tier_1)+SUMIFS(Scenarios!$J$6:$J$41,Scenarios!$A$6:$A$41,cbo_tier_1,Scenarios!$B$6:$B$41,cbo_tier_1))+(SUMIFS(Scenarios!$I$6:$I$41,Scenarios!$A$6:$A$41,cbo_tier_1,Scenarios!$B$6:$B$41,cbo_tier_1)+SUMIFS(Scenarios!$J$6:$J$41,Scenarios!$A$6:$A$41,cbo_tier_1,Scenarios!$B$6:$B$41,cbo_tier_1))*sens_segment_factor | G12: =SUMIFS(Scenarios!$V$6:$V$41,Scenarios!$A$6:$A$41,cbo_tier_1,Scenarios!$B$6:$B$41,cbo_tier_1)-SUMIFS(Scenarios!$T$6:$T$41,Scenarios!$A$6:$A$41,cbo_tier_1,Scenarios!$B$6:$B$41,cbo_tier_1)+MAX(0,cbo_tier_1*sens_map_loads-free_maps)/1000*price_map_1k | H12: =IF(ai_searches_per_funder=0,SUMIFS(Scenarios!$V$6:$V$41,Scenarios!$A$6:$A$41,cbo_tier_1,Scenarios!$B$6:$B$41,cbo_tier_1),SUMIFS(Scenarios!$V$6:$V$41,Scenarios!$A$6:$A$41,cbo_tier_1,Scenarios!$B$6:$B$41,cbo_tier_1)-SUMIFS(Scenarios!$N$6:$N$41,Scenarios!$A$6:$A$41,cbo_tier_1,Scenarios!$B$6:$B$41,cbo_tier_1)+SUMIFS(Scenarios!$N$6:$N$41,Scenarios!$A$6:$A$41,cbo_tier_1,Scenarios!$B$6:$B$41,cbo_tier_1)*(sens_searches/ai_searches_per_funder)) | I12: =SUMIFS(Scenarios!$V$6:$V$41,Scenarios!$A$6:$A$41,cbo_tier_1,Scenarios!$B$6:$B$41,cbo_tier_1)-(SUMIFS(Scenarios!$L$6:$L$41,Scenarios!$A$6:$A$41,cbo_tier_1,Scenarios!$B$6:$B$41,cbo_tier_1)+SUMIFS(Scenarios!$M$6:$M$41,Scenarios!$A$6:$A$41,cbo_tier_1,Scenarios!$B$6:$B$41,cbo_tier_1)+SUMIFS(Scenarios!$N$6:$N$41,Scenarios!$A$6:$A$41,cbo_tier_1,Scenarios!$B$6:$B$41,cbo_tier_1)+SUMIFS(Scenarios!$O$6:$O$41,Scenarios!$A$6:$A$41,cbo_tier_1,Scenarios!$B$6:$B$41,cbo_tier_1)+SUMIFS(Scenarios!$P$6:$P$41,Scenarios!$A$6:$A$41,cbo_tier_1,Scenarios!$B$6:$B$41,cbo_tier_1))+(SUMIFS(Scenarios!$L$6:$L$41,Scenarios!$A$6:$A$41,cbo_tier_1,Scenarios!$B$6:$B$41,cbo_tier_1)+SUMIFS(Scenarios!$M$6:$M$41,Scenarios!$A$6:$A$41,cbo_tier_1,Scenarios!$B$6:$B$41,cbo_tier_1)+SUMIFS(Scenarios!$N$6:$N$41,Scenarios!$A$6:$A$41,cbo_tier_1,Scenarios!$B$6:$B$41,cbo_tier_1)+SUMIFS(Scenarios!$O$6:$O$41,Scenarios!$A$6:$A$41,cbo_tier_1,Scenarios!$B$6:$B$41,cbo_tier_1)+SUMIFS(Scenarios!$P$6:$P$41,Scenarios!$A$6:$A$41,cbo_tier_1,Scenarios!$B$6:$B$41,cbo_tier_1))*sens_gemini_mult
A13: =cbo_tier_2 | B13: =SUMIFS(Scenarios!$V$6:$V$41,Scenarios!$A$6:$A$41,cbo_tier_2,Scenarios!$B$6:$B$41,cbo_tier_2) | C13: =SUMIFS(Scenarios!$V$6:$V$41,Scenarios!$A$6:$A$41,cbo_tier_2,Scenarios!$B$6:$B$41,cbo_tier_2)-(SUMIFS(Scenarios!$I$6:$I$41,Scenarios!$A$6:$A$41,cbo_tier_2,Scenarios!$B$6:$B$41,cbo_tier_2)+SUMIFS(Scenarios!$J$6:$J$41,Scenarios!$A$6:$A$41,cbo_tier_2,Scenarios!$B$6:$B$41,cbo_tier_2)+SUMIFS(Scenarios!$P$6:$P$41,Scenarios!$A$6:$A$41,cbo_tier_2,Scenarios!$B$6:$B$41,cbo_tier_2))+(SUMIFS(Scenarios!$I$6:$I$41,Scenarios!$A$6:$A$41,cbo_tier_2,Scenarios!$B$6:$B$41,cbo_tier_2)+SUMIFS(Scenarios!$J$6:$J$41,Scenarios!$A$6:$A$41,cbo_tier_2,Scenarios!$B$6:$B$41,cbo_tier_2)+SUMIFS(Scenarios!$P$6:$P$41,Scenarios!$A$6:$A$41,cbo_tier_2,Scenarios!$B$6:$B$41,cbo_tier_2))*(sens_checkins/checkins_per_year) | D13: =SUMIFS(Scenarios!$V$6:$V$41,Scenarios!$A$6:$A$41,cbo_tier_2,Scenarios!$B$6:$B$41,cbo_tier_2)-(SUMIFS(Scenarios!$I$6:$I$41,Scenarios!$A$6:$A$41,cbo_tier_2,Scenarios!$B$6:$B$41,cbo_tier_2)+SUMIFS(Scenarios!$J$6:$J$41,Scenarios!$A$6:$A$41,cbo_tier_2,Scenarios!$B$6:$B$41,cbo_tier_2)+SUMIFS(Scenarios!$P$6:$P$41,Scenarios!$A$6:$A$41,cbo_tier_2,Scenarios!$B$6:$B$41,cbo_tier_2))+(SUMIFS(Scenarios!$I$6:$I$41,Scenarios!$A$6:$A$41,cbo_tier_2,Scenarios!$B$6:$B$41,cbo_tier_2)+SUMIFS(Scenarios!$J$6:$J$41,Scenarios!$A$6:$A$41,cbo_tier_2,Scenarios!$B$6:$B$41,cbo_tier_2)+SUMIFS(Scenarios!$P$6:$P$41,Scenarios!$A$6:$A$41,cbo_tier_2,Scenarios!$B$6:$B$41,cbo_tier_2))*(sens_subscribers/subscribers_per_cbo) | E13: =SUMIFS(Scenarios!$V$6:$V$41,Scenarios!$A$6:$A$41,cbo_tier_2,Scenarios!$B$6:$B$41,cbo_tier_2)-(SUMIFS(Scenarios!$I$6:$I$41,Scenarios!$A$6:$A$41,cbo_tier_2,Scenarios!$B$6:$B$41,cbo_tier_2)+SUMIFS(Scenarios!$J$6:$J$41,Scenarios!$A$6:$A$41,cbo_tier_2,Scenarios!$B$6:$B$41,cbo_tier_2)+SUMIFS(Scenarios!$P$6:$P$41,Scenarios!$A$6:$A$41,cbo_tier_2,Scenarios!$B$6:$B$41,cbo_tier_2))+(SUMIFS(Scenarios!$I$6:$I$41,Scenarios!$A$6:$A$41,cbo_tier_2,Scenarios!$B$6:$B$41,cbo_tier_2)+SUMIFS(Scenarios!$J$6:$J$41,Scenarios!$A$6:$A$41,cbo_tier_2,Scenarios!$B$6:$B$41,cbo_tier_2)+SUMIFS(Scenarios!$P$6:$P$41,Scenarios!$A$6:$A$41,cbo_tier_2,Scenarios!$B$6:$B$41,cbo_tier_2))*(sens_checkins/checkins_per_year)*(sens_subscribers/subscribers_per_cbo) | F13: =SUMIFS(Scenarios!$V$6:$V$41,Scenarios!$A$6:$A$41,cbo_tier_2,Scenarios!$B$6:$B$41,cbo_tier_2)-(SUMIFS(Scenarios!$I$6:$I$41,Scenarios!$A$6:$A$41,cbo_tier_2,Scenarios!$B$6:$B$41,cbo_tier_2)+SUMIFS(Scenarios!$J$6:$J$41,Scenarios!$A$6:$A$41,cbo_tier_2,Scenarios!$B$6:$B$41,cbo_tier_2))+(SUMIFS(Scenarios!$I$6:$I$41,Scenarios!$A$6:$A$41,cbo_tier_2,Scenarios!$B$6:$B$41,cbo_tier_2)+SUMIFS(Scenarios!$J$6:$J$41,Scenarios!$A$6:$A$41,cbo_tier_2,Scenarios!$B$6:$B$41,cbo_tier_2))*sens_segment_factor | G13: =SUMIFS(Scenarios!$V$6:$V$41,Scenarios!$A$6:$A$41,cbo_tier_2,Scenarios!$B$6:$B$41,cbo_tier_2)-SUMIFS(Scenarios!$T$6:$T$41,Scenarios!$A$6:$A$41,cbo_tier_2,Scenarios!$B$6:$B$41,cbo_tier_2)+MAX(0,cbo_tier_2*sens_map_loads-free_maps)/1000*price_map_1k | H13: =IF(ai_searches_per_funder=0,SUMIFS(Scenarios!$V$6:$V$41,Scenarios!$A$6:$A$41,cbo_tier_2,Scenarios!$B$6:$B$41,cbo_tier_2),SUMIFS(Scenarios!$V$6:$V$41,Scenarios!$A$6:$A$41,cbo_tier_2,Scenarios!$B$6:$B$41,cbo_tier_2)-SUMIFS(Scenarios!$N$6:$N$41,Scenarios!$A$6:$A$41,cbo_tier_2,Scenarios!$B$6:$B$41,cbo_tier_2)+SUMIFS(Scenarios!$N$6:$N$41,Scenarios!$A$6:$A$41,cbo_tier_2,Scenarios!$B$6:$B$41,cbo_tier_2)*(sens_searches/ai_searches_per_funder)) | I13: =SUMIFS(Scenarios!$V$6:$V$41,Scenarios!$A$6:$A$41,cbo_tier_2,Scenarios!$B$6:$B$41,cbo_tier_2)-(SUMIFS(Scenarios!$L$6:$L$41,Scenarios!$A$6:$A$41,cbo_tier_2,Scenarios!$B$6:$B$41,cbo_tier_2)+SUMIFS(Scenarios!$M$6:$M$41,Scenarios!$A$6:$A$41,cbo_tier_2,Scenarios!$B$6:$B$41,cbo_tier_2)+SUMIFS(Scenarios!$N$6:$N$41,Scenarios!$A$6:$A$41,cbo_tier_2,Scenarios!$B$6:$B$41,cbo_tier_2)+SUMIFS(Scenarios!$O$6:$O$41,Scenarios!$A$6:$A$41,cbo_tier_2,Scenarios!$B$6:$B$41,cbo_tier_2)+SUMIFS(Scenarios!$P$6:$P$41,Scenarios!$A$6:$A$41,cbo_tier_2,Scenarios!$B$6:$B$41,cbo_tier_2))+(SUMIFS(Scenarios!$L$6:$L$41,Scenarios!$A$6:$A$41,cbo_tier_2,Scenarios!$B$6:$B$41,cbo_tier_2)+SUMIFS(Scenarios!$M$6:$M$41,Scenarios!$A$6:$A$41,cbo_tier_2,Scenarios!$B$6:$B$41,cbo_tier_2)+SUMIFS(Scenarios!$N$6:$N$41,Scenarios!$A$6:$A$41,cbo_tier_2,Scenarios!$B$6:$B$41,cbo_tier_2)+SUMIFS(Scenarios!$O$6:$O$41,Scenarios!$A$6:$A$41,cbo_tier_2,Scenarios!$B$6:$B$41,cbo_tier_2)+SUMIFS(Scenarios!$P$6:$P$41,Scenarios!$A$6:$A$41,cbo_tier_2,Scenarios!$B$6:$B$41,cbo_tier_2))*sens_gemini_mult
A14: =cbo_tier_3 | B14: =SUMIFS(Scenarios!$V$6:$V$41,Scenarios!$A$6:$A$41,cbo_tier_3,Scenarios!$B$6:$B$41,cbo_tier_3) | C14: =SUMIFS(Scenarios!$V$6:$V$41,Scenarios!$A$6:$A$41,cbo_tier_3,Scenarios!$B$6:$B$41,cbo_tier_3)-(SUMIFS(Scenarios!$I$6:$I$41,Scenarios!$A$6:$A$41,cbo_tier_3,Scenarios!$B$6:$B$41,cbo_tier_3)+SUMIFS(Scenarios!$J$6:$J$41,Scenarios!$A$6:$A$41,cbo_tier_3,Scenarios!$B$6:$B$41,cbo_tier_3)+SUMIFS(Scenarios!$P$6:$P$41,Scenarios!$A$6:$A$41,cbo_tier_3,Scenarios!$B$6:$B$41,cbo_tier_3))+(SUMIFS(Scenarios!$I$6:$I$41,Scenarios!$A$6:$A$41,cbo_tier_3,Scenarios!$B$6:$B$41,cbo_tier_3)+SUMIFS(Scenarios!$J$6:$J$41,Scenarios!$A$6:$A$41,cbo_tier_3,Scenarios!$B$6:$B$41,cbo_tier_3)+SUMIFS(Scenarios!$P$6:$P$41,Scenarios!$A$6:$A$41,cbo_tier_3,Scenarios!$B$6:$B$41,cbo_tier_3))*(sens_checkins/checkins_per_year) | D14: =SUMIFS(Scenarios!$V$6:$V$41,Scenarios!$A$6:$A$41,cbo_tier_3,Scenarios!$B$6:$B$41,cbo_tier_3)-(SUMIFS(Scenarios!$I$6:$I$41,Scenarios!$A$6:$A$41,cbo_tier_3,Scenarios!$B$6:$B$41,cbo_tier_3)+SUMIFS(Scenarios!$J$6:$J$41,Scenarios!$A$6:$A$41,cbo_tier_3,Scenarios!$B$6:$B$41,cbo_tier_3)+SUMIFS(Scenarios!$P$6:$P$41,Scenarios!$A$6:$A$41,cbo_tier_3,Scenarios!$B$6:$B$41,cbo_tier_3))+(SUMIFS(Scenarios!$I$6:$I$41,Scenarios!$A$6:$A$41,cbo_tier_3,Scenarios!$B$6:$B$41,cbo_tier_3)+SUMIFS(Scenarios!$J$6:$J$41,Scenarios!$A$6:$A$41,cbo_tier_3,Scenarios!$B$6:$B$41,cbo_tier_3)+SUMIFS(Scenarios!$P$6:$P$41,Scenarios!$A$6:$A$41,cbo_tier_3,Scenarios!$B$6:$B$41,cbo_tier_3))*(sens_subscribers/subscribers_per_cbo) | E14: =SUMIFS(Scenarios!$V$6:$V$41,Scenarios!$A$6:$A$41,cbo_tier_3,Scenarios!$B$6:$B$41,cbo_tier_3)-(SUMIFS(Scenarios!$I$6:$I$41,Scenarios!$A$6:$A$41,cbo_tier_3,Scenarios!$B$6:$B$41,cbo_tier_3)+SUMIFS(Scenarios!$J$6:$J$41,Scenarios!$A$6:$A$41,cbo_tier_3,Scenarios!$B$6:$B$41,cbo_tier_3)+SUMIFS(Scenarios!$P$6:$P$41,Scenarios!$A$6:$A$41,cbo_tier_3,Scenarios!$B$6:$B$41,cbo_tier_3))+(SUMIFS(Scenarios!$I$6:$I$41,Scenarios!$A$6:$A$41,cbo_tier_3,Scenarios!$B$6:$B$41,cbo_tier_3)+SUMIFS(Scenarios!$J$6:$J$41,Scenarios!$A$6:$A$41,cbo_tier_3,Scenarios!$B$6:$B$41,cbo_tier_3)+SUMIFS(Scenarios!$P$6:$P$41,Scenarios!$A$6:$A$41,cbo_tier_3,Scenarios!$B$6:$B$41,cbo_tier_3))*(sens_checkins/checkins_per_year)*(sens_subscribers/subscribers_per_cbo) | F14: =SUMIFS(Scenarios!$V$6:$V$41,Scenarios!$A$6:$A$41,cbo_tier_3,Scenarios!$B$6:$B$41,cbo_tier_3)-(SUMIFS(Scenarios!$I$6:$I$41,Scenarios!$A$6:$A$41,cbo_tier_3,Scenarios!$B$6:$B$41,cbo_tier_3)+SUMIFS(Scenarios!$J$6:$J$41,Scenarios!$A$6:$A$41,cbo_tier_3,Scenarios!$B$6:$B$41,cbo_tier_3))+(SUMIFS(Scenarios!$I$6:$I$41,Scenarios!$A$6:$A$41,cbo_tier_3,Scenarios!$B$6:$B$41,cbo_tier_3)+SUMIFS(Scenarios!$J$6:$J$41,Scenarios!$A$6:$A$41,cbo_tier_3,Scenarios!$B$6:$B$41,cbo_tier_3))*sens_segment_factor | G14: =SUMIFS(Scenarios!$V$6:$V$41,Scenarios!$A$6:$A$41,cbo_tier_3,Scenarios!$B$6:$B$41,cbo_tier_3)-SUMIFS(Scenarios!$T$6:$T$41,Scenarios!$A$6:$A$41,cbo_tier_3,Scenarios!$B$6:$B$41,cbo_tier_3)+MAX(0,cbo_tier_3*sens_map_loads-free_maps)/1000*price_map_1k | H14: =IF(ai_searches_per_funder=0,SUMIFS(Scenarios!$V$6:$V$41,Scenarios!$A$6:$A$41,cbo_tier_3,Scenarios!$B$6:$B$41,cbo_tier_3),SUMIFS(Scenarios!$V$6:$V$41,Scenarios!$A$6:$A$41,cbo_tier_3,Scenarios!$B$6:$B$41,cbo_tier_3)-SUMIFS(Scenarios!$N$6:$N$41,Scenarios!$A$6:$A$41,cbo_tier_3,Scenarios!$B$6:$B$41,cbo_tier_3)+SUMIFS(Scenarios!$N$6:$N$41,Scenarios!$A$6:$A$41,cbo_tier_3,Scenarios!$B$6:$B$41,cbo_tier_3)*(sens_searches/ai_searches_per_funder)) | I14: =SUMIFS(Scenarios!$V$6:$V$41,Scenarios!$A$6:$A$41,cbo_tier_3,Scenarios!$B$6:$B$41,cbo_tier_3)-(SUMIFS(Scenarios!$L$6:$L$41,Scenarios!$A$6:$A$41,cbo_tier_3,Scenarios!$B$6:$B$41,cbo_tier_3)+SUMIFS(Scenarios!$M$6:$M$41,Scenarios!$A$6:$A$41,cbo_tier_3,Scenarios!$B$6:$B$41,cbo_tier_3)+SUMIFS(Scenarios!$N$6:$N$41,Scenarios!$A$6:$A$41,cbo_tier_3,Scenarios!$B$6:$B$41,cbo_tier_3)+SUMIFS(Scenarios!$O$6:$O$41,Scenarios!$A$6:$A$41,cbo_tier_3,Scenarios!$B$6:$B$41,cbo_tier_3)+SUMIFS(Scenarios!$P$6:$P$41,Scenarios!$A$6:$A$41,cbo_tier_3,Scenarios!$B$6:$B$41,cbo_tier_3))+(SUMIFS(Scenarios!$L$6:$L$41,Scenarios!$A$6:$A$41,cbo_tier_3,Scenarios!$B$6:$B$41,cbo_tier_3)+SUMIFS(Scenarios!$M$6:$M$41,Scenarios!$A$6:$A$41,cbo_tier_3,Scenarios!$B$6:$B$41,cbo_tier_3)+SUMIFS(Scenarios!$N$6:$N$41,Scenarios!$A$6:$A$41,cbo_tier_3,Scenarios!$B$6:$B$41,cbo_tier_3)+SUMIFS(Scenarios!$O$6:$O$41,Scenarios!$A$6:$A$41,cbo_tier_3,Scenarios!$B$6:$B$41,cbo_tier_3)+SUMIFS(Scenarios!$P$6:$P$41,Scenarios!$A$6:$A$41,cbo_tier_3,Scenarios!$B$6:$B$41,cbo_tier_3))*sens_gemini_mult
A15: =cbo_tier_4 | B15: =SUMIFS(Scenarios!$V$6:$V$41,Scenarios!$A$6:$A$41,cbo_tier_4,Scenarios!$B$6:$B$41,cbo_tier_4) | C15: =SUMIFS(Scenarios!$V$6:$V$41,Scenarios!$A$6:$A$41,cbo_tier_4,Scenarios!$B$6:$B$41,cbo_tier_4)-(SUMIFS(Scenarios!$I$6:$I$41,Scenarios!$A$6:$A$41,cbo_tier_4,Scenarios!$B$6:$B$41,cbo_tier_4)+SUMIFS(Scenarios!$J$6:$J$41,Scenarios!$A$6:$A$41,cbo_tier_4,Scenarios!$B$6:$B$41,cbo_tier_4)+SUMIFS(Scenarios!$P$6:$P$41,Scenarios!$A$6:$A$41,cbo_tier_4,Scenarios!$B$6:$B$41,cbo_tier_4))+(SUMIFS(Scenarios!$I$6:$I$41,Scenarios!$A$6:$A$41,cbo_tier_4,Scenarios!$B$6:$B$41,cbo_tier_4)+SUMIFS(Scenarios!$J$6:$J$41,Scenarios!$A$6:$A$41,cbo_tier_4,Scenarios!$B$6:$B$41,cbo_tier_4)+SUMIFS(Scenarios!$P$6:$P$41,Scenarios!$A$6:$A$41,cbo_tier_4,Scenarios!$B$6:$B$41,cbo_tier_4))*(sens_checkins/checkins_per_year) | D15: =SUMIFS(Scenarios!$V$6:$V$41,Scenarios!$A$6:$A$41,cbo_tier_4,Scenarios!$B$6:$B$41,cbo_tier_4)-(SUMIFS(Scenarios!$I$6:$I$41,Scenarios!$A$6:$A$41,cbo_tier_4,Scenarios!$B$6:$B$41,cbo_tier_4)+SUMIFS(Scenarios!$J$6:$J$41,Scenarios!$A$6:$A$41,cbo_tier_4,Scenarios!$B$6:$B$41,cbo_tier_4)+SUMIFS(Scenarios!$P$6:$P$41,Scenarios!$A$6:$A$41,cbo_tier_4,Scenarios!$B$6:$B$41,cbo_tier_4))+(SUMIFS(Scenarios!$I$6:$I$41,Scenarios!$A$6:$A$41,cbo_tier_4,Scenarios!$B$6:$B$41,cbo_tier_4)+SUMIFS(Scenarios!$J$6:$J$41,Scenarios!$A$6:$A$41,cbo_tier_4,Scenarios!$B$6:$B$41,cbo_tier_4)+SUMIFS(Scenarios!$P$6:$P$41,Scenarios!$A$6:$A$41,cbo_tier_4,Scenarios!$B$6:$B$41,cbo_tier_4))*(sens_subscribers/subscribers_per_cbo) | E15: =SUMIFS(Scenarios!$V$6:$V$41,Scenarios!$A$6:$A$41,cbo_tier_4,Scenarios!$B$6:$B$41,cbo_tier_4)-(SUMIFS(Scenarios!$I$6:$I$41,Scenarios!$A$6:$A$41,cbo_tier_4,Scenarios!$B$6:$B$41,cbo_tier_4)+SUMIFS(Scenarios!$J$6:$J$41,Scenarios!$A$6:$A$41,cbo_tier_4,Scenarios!$B$6:$B$41,cbo_tier_4)+SUMIFS(Scenarios!$P$6:$P$41,Scenarios!$A$6:$A$41,cbo_tier_4,Scenarios!$B$6:$B$41,cbo_tier_4))+(SUMIFS(Scenarios!$I$6:$I$41,Scenarios!$A$6:$A$41,cbo_tier_4,Scenarios!$B$6:$B$41,cbo_tier_4)+SUMIFS(Scenarios!$J$6:$J$41,Scenarios!$A$6:$A$41,cbo_tier_4,Scenarios!$B$6:$B$41,cbo_tier_4)+SUMIFS(Scenarios!$P$6:$P$41,Scenarios!$A$6:$A$41,cbo_tier_4,Scenarios!$B$6:$B$41,cbo_tier_4))*(sens_checkins/checkins_per_year)*(sens_subscribers/subscribers_per_cbo) | F15: =SUMIFS(Scenarios!$V$6:$V$41,Scenarios!$A$6:$A$41,cbo_tier_4,Scenarios!$B$6:$B$41,cbo_tier_4)-(SUMIFS(Scenarios!$I$6:$I$41,Scenarios!$A$6:$A$41,cbo_tier_4,Scenarios!$B$6:$B$41,cbo_tier_4)+SUMIFS(Scenarios!$J$6:$J$41,Scenarios!$A$6:$A$41,cbo_tier_4,Scenarios!$B$6:$B$41,cbo_tier_4))+(SUMIFS(Scenarios!$I$6:$I$41,Scenarios!$A$6:$A$41,cbo_tier_4,Scenarios!$B$6:$B$41,cbo_tier_4)+SUMIFS(Scenarios!$J$6:$J$41,Scenarios!$A$6:$A$41,cbo_tier_4,Scenarios!$B$6:$B$41,cbo_tier_4))*sens_segment_factor | G15: =SUMIFS(Scenarios!$V$6:$V$41,Scenarios!$A$6:$A$41,cbo_tier_4,Scenarios!$B$6:$B$41,cbo_tier_4)-SUMIFS(Scenarios!$T$6:$T$41,Scenarios!$A$6:$A$41,cbo_tier_4,Scenarios!$B$6:$B$41,cbo_tier_4)+MAX(0,cbo_tier_4*sens_map_loads-free_maps)/1000*price_map_1k | H15: =IF(ai_searches_per_funder=0,SUMIFS(Scenarios!$V$6:$V$41,Scenarios!$A$6:$A$41,cbo_tier_4,Scenarios!$B$6:$B$41,cbo_tier_4),SUMIFS(Scenarios!$V$6:$V$41,Scenarios!$A$6:$A$41,cbo_tier_4,Scenarios!$B$6:$B$41,cbo_tier_4)-SUMIFS(Scenarios!$N$6:$N$41,Scenarios!$A$6:$A$41,cbo_tier_4,Scenarios!$B$6:$B$41,cbo_tier_4)+SUMIFS(Scenarios!$N$6:$N$41,Scenarios!$A$6:$A$41,cbo_tier_4,Scenarios!$B$6:$B$41,cbo_tier_4)*(sens_searches/ai_searches_per_funder)) | I15: =SUMIFS(Scenarios!$V$6:$V$41,Scenarios!$A$6:$A$41,cbo_tier_4,Scenarios!$B$6:$B$41,cbo_tier_4)-(SUMIFS(Scenarios!$L$6:$L$41,Scenarios!$A$6:$A$41,cbo_tier_4,Scenarios!$B$6:$B$41,cbo_tier_4)+SUMIFS(Scenarios!$M$6:$M$41,Scenarios!$A$6:$A$41,cbo_tier_4,Scenarios!$B$6:$B$41,cbo_tier_4)+SUMIFS(Scenarios!$N$6:$N$41,Scenarios!$A$6:$A$41,cbo_tier_4,Scenarios!$B$6:$B$41,cbo_tier_4)+SUMIFS(Scenarios!$O$6:$O$41,Scenarios!$A$6:$A$41,cbo_tier_4,Scenarios!$B$6:$B$41,cbo_tier_4)+SUMIFS(Scenarios!$P$6:$P$41,Scenarios!$A$6:$A$41,cbo_tier_4,Scenarios!$B$6:$B$41,cbo_tier_4))+(SUMIFS(Scenarios!$L$6:$L$41,Scenarios!$A$6:$A$41,cbo_tier_4,Scenarios!$B$6:$B$41,cbo_tier_4)+SUMIFS(Scenarios!$M$6:$M$41,Scenarios!$A$6:$A$41,cbo_tier_4,Scenarios!$B$6:$B$41,cbo_tier_4)+SUMIFS(Scenarios!$N$6:$N$41,Scenarios!$A$6:$A$41,cbo_tier_4,Scenarios!$B$6:$B$41,cbo_tier_4)+SUMIFS(Scenarios!$O$6:$O$41,Scenarios!$A$6:$A$41,cbo_tier_4,Scenarios!$B$6:$B$41,cbo_tier_4)+SUMIFS(Scenarios!$P$6:$P$41,Scenarios!$A$6:$A$41,cbo_tier_4,Scenarios!$B$6:$B$41,cbo_tier_4))*sens_gemini_mult
A16: =cbo_tier_5 | B16: =SUMIFS(Scenarios!$V$6:$V$41,Scenarios!$A$6:$A$41,cbo_tier_5,Scenarios!$B$6:$B$41,cbo_tier_5) | C16: =SUMIFS(Scenarios!$V$6:$V$41,Scenarios!$A$6:$A$41,cbo_tier_5,Scenarios!$B$6:$B$41,cbo_tier_5)-(SUMIFS(Scenarios!$I$6:$I$41,Scenarios!$A$6:$A$41,cbo_tier_5,Scenarios!$B$6:$B$41,cbo_tier_5)+SUMIFS(Scenarios!$J$6:$J$41,Scenarios!$A$6:$A$41,cbo_tier_5,Scenarios!$B$6:$B$41,cbo_tier_5)+SUMIFS(Scenarios!$P$6:$P$41,Scenarios!$A$6:$A$41,cbo_tier_5,Scenarios!$B$6:$B$41,cbo_tier_5))+(SUMIFS(Scenarios!$I$6:$I$41,Scenarios!$A$6:$A$41,cbo_tier_5,Scenarios!$B$6:$B$41,cbo_tier_5)+SUMIFS(Scenarios!$J$6:$J$41,Scenarios!$A$6:$A$41,cbo_tier_5,Scenarios!$B$6:$B$41,cbo_tier_5)+SUMIFS(Scenarios!$P$6:$P$41,Scenarios!$A$6:$A$41,cbo_tier_5,Scenarios!$B$6:$B$41,cbo_tier_5))*(sens_checkins/checkins_per_year) | D16: =SUMIFS(Scenarios!$V$6:$V$41,Scenarios!$A$6:$A$41,cbo_tier_5,Scenarios!$B$6:$B$41,cbo_tier_5)-(SUMIFS(Scenarios!$I$6:$I$41,Scenarios!$A$6:$A$41,cbo_tier_5,Scenarios!$B$6:$B$41,cbo_tier_5)+SUMIFS(Scenarios!$J$6:$J$41,Scenarios!$A$6:$A$41,cbo_tier_5,Scenarios!$B$6:$B$41,cbo_tier_5)+SUMIFS(Scenarios!$P$6:$P$41,Scenarios!$A$6:$A$41,cbo_tier_5,Scenarios!$B$6:$B$41,cbo_tier_5))+(SUMIFS(Scenarios!$I$6:$I$41,Scenarios!$A$6:$A$41,cbo_tier_5,Scenarios!$B$6:$B$41,cbo_tier_5)+SUMIFS(Scenarios!$J$6:$J$41,Scenarios!$A$6:$A$41,cbo_tier_5,Scenarios!$B$6:$B$41,cbo_tier_5)+SUMIFS(Scenarios!$P$6:$P$41,Scenarios!$A$6:$A$41,cbo_tier_5,Scenarios!$B$6:$B$41,cbo_tier_5))*(sens_subscribers/subscribers_per_cbo) | E16: =SUMIFS(Scenarios!$V$6:$V$41,Scenarios!$A$6:$A$41,cbo_tier_5,Scenarios!$B$6:$B$41,cbo_tier_5)-(SUMIFS(Scenarios!$I$6:$I$41,Scenarios!$A$6:$A$41,cbo_tier_5,Scenarios!$B$6:$B$41,cbo_tier_5)+SUMIFS(Scenarios!$J$6:$J$41,Scenarios!$A$6:$A$41,cbo_tier_5,Scenarios!$B$6:$B$41,cbo_tier_5)+SUMIFS(Scenarios!$P$6:$P$41,Scenarios!$A$6:$A$41,cbo_tier_5,Scenarios!$B$6:$B$41,cbo_tier_5))+(SUMIFS(Scenarios!$I$6:$I$41,Scenarios!$A$6:$A$41,cbo_tier_5,Scenarios!$B$6:$B$41,cbo_tier_5)+SUMIFS(Scenarios!$J$6:$J$41,Scenarios!$A$6:$A$41,cbo_tier_5,Scenarios!$B$6:$B$41,cbo_tier_5)+SUMIFS(Scenarios!$P$6:$P$41,Scenarios!$A$6:$A$41,cbo_tier_5,Scenarios!$B$6:$B$41,cbo_tier_5))*(sens_checkins/checkins_per_year)*(sens_subscribers/subscribers_per_cbo) | F16: =SUMIFS(Scenarios!$V$6:$V$41,Scenarios!$A$6:$A$41,cbo_tier_5,Scenarios!$B$6:$B$41,cbo_tier_5)-(SUMIFS(Scenarios!$I$6:$I$41,Scenarios!$A$6:$A$41,cbo_tier_5,Scenarios!$B$6:$B$41,cbo_tier_5)+SUMIFS(Scenarios!$J$6:$J$41,Scenarios!$A$6:$A$41,cbo_tier_5,Scenarios!$B$6:$B$41,cbo_tier_5))+(SUMIFS(Scenarios!$I$6:$I$41,Scenarios!$A$6:$A$41,cbo_tier_5,Scenarios!$B$6:$B$41,cbo_tier_5)+SUMIFS(Scenarios!$J$6:$J$41,Scenarios!$A$6:$A$41,cbo_tier_5,Scenarios!$B$6:$B$41,cbo_tier_5))*sens_segment_factor | G16: =SUMIFS(Scenarios!$V$6:$V$41,Scenarios!$A$6:$A$41,cbo_tier_5,Scenarios!$B$6:$B$41,cbo_tier_5)-SUMIFS(Scenarios!$T$6:$T$41,Scenarios!$A$6:$A$41,cbo_tier_5,Scenarios!$B$6:$B$41,cbo_tier_5)+MAX(0,cbo_tier_5*sens_map_loads-free_maps)/1000*price_map_1k | H16: =IF(ai_searches_per_funder=0,SUMIFS(Scenarios!$V$6:$V$41,Scenarios!$A$6:$A$41,cbo_tier_5,Scenarios!$B$6:$B$41,cbo_tier_5),SUMIFS(Scenarios!$V$6:$V$41,Scenarios!$A$6:$A$41,cbo_tier_5,Scenarios!$B$6:$B$41,cbo_tier_5)-SUMIFS(Scenarios!$N$6:$N$41,Scenarios!$A$6:$A$41,cbo_tier_5,Scenarios!$B$6:$B$41,cbo_tier_5)+SUMIFS(Scenarios!$N$6:$N$41,Scenarios!$A$6:$A$41,cbo_tier_5,Scenarios!$B$6:$B$41,cbo_tier_5)*(sens_searches/ai_searches_per_funder)) | I16: =SUMIFS(Scenarios!$V$6:$V$41,Scenarios!$A$6:$A$41,cbo_tier_5,Scenarios!$B$6:$B$41,cbo_tier_5)-(SUMIFS(Scenarios!$L$6:$L$41,Scenarios!$A$6:$A$41,cbo_tier_5,Scenarios!$B$6:$B$41,cbo_tier_5)+SUMIFS(Scenarios!$M$6:$M$41,Scenarios!$A$6:$A$41,cbo_tier_5,Scenarios!$B$6:$B$41,cbo_tier_5)+SUMIFS(Scenarios!$N$6:$N$41,Scenarios!$A$6:$A$41,cbo_tier_5,Scenarios!$B$6:$B$41,cbo_tier_5)+SUMIFS(Scenarios!$O$6:$O$41,Scenarios!$A$6:$A$41,cbo_tier_5,Scenarios!$B$6:$B$41,cbo_tier_5)+SUMIFS(Scenarios!$P$6:$P$41,Scenarios!$A$6:$A$41,cbo_tier_5,Scenarios!$B$6:$B$41,cbo_tier_5))+(SUMIFS(Scenarios!$L$6:$L$41,Scenarios!$A$6:$A$41,cbo_tier_5,Scenarios!$B$6:$B$41,cbo_tier_5)+SUMIFS(Scenarios!$M$6:$M$41,Scenarios!$A$6:$A$41,cbo_tier_5,Scenarios!$B$6:$B$41,cbo_tier_5)+SUMIFS(Scenarios!$N$6:$N$41,Scenarios!$A$6:$A$41,cbo_tier_5,Scenarios!$B$6:$B$41,cbo_tier_5)+SUMIFS(Scenarios!$O$6:$O$41,Scenarios!$A$6:$A$41,cbo_tier_5,Scenarios!$B$6:$B$41,cbo_tier_5)+SUMIFS(Scenarios!$P$6:$P$41,Scenarios!$A$6:$A$41,cbo_tier_5,Scenarios!$B$6:$B$41,cbo_tier_5))*sens_gemini_mult
A17: =cbo_tier_6 | B17: =SUMIFS(Scenarios!$V$6:$V$41,Scenarios!$A$6:$A$41,cbo_tier_6,Scenarios!$B$6:$B$41,cbo_tier_6) | C17: =SUMIFS(Scenarios!$V$6:$V$41,Scenarios!$A$6:$A$41,cbo_tier_6,Scenarios!$B$6:$B$41,cbo_tier_6)-(SUMIFS(Scenarios!$I$6:$I$41,Scenarios!$A$6:$A$41,cbo_tier_6,Scenarios!$B$6:$B$41,cbo_tier_6)+SUMIFS(Scenarios!$J$6:$J$41,Scenarios!$A$6:$A$41,cbo_tier_6,Scenarios!$B$6:$B$41,cbo_tier_6)+SUMIFS(Scenarios!$P$6:$P$41,Scenarios!$A$6:$A$41,cbo_tier_6,Scenarios!$B$6:$B$41,cbo_tier_6))+(SUMIFS(Scenarios!$I$6:$I$41,Scenarios!$A$6:$A$41,cbo_tier_6,Scenarios!$B$6:$B$41,cbo_tier_6)+SUMIFS(Scenarios!$J$6:$J$41,Scenarios!$A$6:$A$41,cbo_tier_6,Scenarios!$B$6:$B$41,cbo_tier_6)+SUMIFS(Scenarios!$P$6:$P$41,Scenarios!$A$6:$A$41,cbo_tier_6,Scenarios!$B$6:$B$41,cbo_tier_6))*(sens_checkins/checkins_per_year) | D17: =SUMIFS(Scenarios!$V$6:$V$41,Scenarios!$A$6:$A$41,cbo_tier_6,Scenarios!$B$6:$B$41,cbo_tier_6)-(SUMIFS(Scenarios!$I$6:$I$41,Scenarios!$A$6:$A$41,cbo_tier_6,Scenarios!$B$6:$B$41,cbo_tier_6)+SUMIFS(Scenarios!$J$6:$J$41,Scenarios!$A$6:$A$41,cbo_tier_6,Scenarios!$B$6:$B$41,cbo_tier_6)+SUMIFS(Scenarios!$P$6:$P$41,Scenarios!$A$6:$A$41,cbo_tier_6,Scenarios!$B$6:$B$41,cbo_tier_6))+(SUMIFS(Scenarios!$I$6:$I$41,Scenarios!$A$6:$A$41,cbo_tier_6,Scenarios!$B$6:$B$41,cbo_tier_6)+SUMIFS(Scenarios!$J$6:$J$41,Scenarios!$A$6:$A$41,cbo_tier_6,Scenarios!$B$6:$B$41,cbo_tier_6)+SUMIFS(Scenarios!$P$6:$P$41,Scenarios!$A$6:$A$41,cbo_tier_6,Scenarios!$B$6:$B$41,cbo_tier_6))*(sens_subscribers/subscribers_per_cbo) | E17: =SUMIFS(Scenarios!$V$6:$V$41,Scenarios!$A$6:$A$41,cbo_tier_6,Scenarios!$B$6:$B$41,cbo_tier_6)-(SUMIFS(Scenarios!$I$6:$I$41,Scenarios!$A$6:$A$41,cbo_tier_6,Scenarios!$B$6:$B$41,cbo_tier_6)+SUMIFS(Scenarios!$J$6:$J$41,Scenarios!$A$6:$A$41,cbo_tier_6,Scenarios!$B$6:$B$41,cbo_tier_6)+SUMIFS(Scenarios!$P$6:$P$41,Scenarios!$A$6:$A$41,cbo_tier_6,Scenarios!$B$6:$B$41,cbo_tier_6))+(SUMIFS(Scenarios!$I$6:$I$41,Scenarios!$A$6:$A$41,cbo_tier_6,Scenarios!$B$6:$B$41,cbo_tier_6)+SUMIFS(Scenarios!$J$6:$J$41,Scenarios!$A$6:$A$41,cbo_tier_6,Scenarios!$B$6:$B$41,cbo_tier_6)+SUMIFS(Scenarios!$P$6:$P$41,Scenarios!$A$6:$A$41,cbo_tier_6,Scenarios!$B$6:$B$41,cbo_tier_6))*(sens_checkins/checkins_per_year)*(sens_subscribers/subscribers_per_cbo) | F17: =SUMIFS(Scenarios!$V$6:$V$41,Scenarios!$A$6:$A$41,cbo_tier_6,Scenarios!$B$6:$B$41,cbo_tier_6)-(SUMIFS(Scenarios!$I$6:$I$41,Scenarios!$A$6:$A$41,cbo_tier_6,Scenarios!$B$6:$B$41,cbo_tier_6)+SUMIFS(Scenarios!$J$6:$J$41,Scenarios!$A$6:$A$41,cbo_tier_6,Scenarios!$B$6:$B$41,cbo_tier_6))+(SUMIFS(Scenarios!$I$6:$I$41,Scenarios!$A$6:$A$41,cbo_tier_6,Scenarios!$B$6:$B$41,cbo_tier_6)+SUMIFS(Scenarios!$J$6:$J$41,Scenarios!$A$6:$A$41,cbo_tier_6,Scenarios!$B$6:$B$41,cbo_tier_6))*sens_segment_factor | G17: =SUMIFS(Scenarios!$V$6:$V$41,Scenarios!$A$6:$A$41,cbo_tier_6,Scenarios!$B$6:$B$41,cbo_tier_6)-SUMIFS(Scenarios!$T$6:$T$41,Scenarios!$A$6:$A$41,cbo_tier_6,Scenarios!$B$6:$B$41,cbo_tier_6)+MAX(0,cbo_tier_6*sens_map_loads-free_maps)/1000*price_map_1k | H17: =IF(ai_searches_per_funder=0,SUMIFS(Scenarios!$V$6:$V$41,Scenarios!$A$6:$A$41,cbo_tier_6,Scenarios!$B$6:$B$41,cbo_tier_6),SUMIFS(Scenarios!$V$6:$V$41,Scenarios!$A$6:$A$41,cbo_tier_6,Scenarios!$B$6:$B$41,cbo_tier_6)-SUMIFS(Scenarios!$N$6:$N$41,Scenarios!$A$6:$A$41,cbo_tier_6,Scenarios!$B$6:$B$41,cbo_tier_6)+SUMIFS(Scenarios!$N$6:$N$41,Scenarios!$A$6:$A$41,cbo_tier_6,Scenarios!$B$6:$B$41,cbo_tier_6)*(sens_searches/ai_searches_per_funder)) | I17: =SUMIFS(Scenarios!$V$6:$V$41,Scenarios!$A$6:$A$41,cbo_tier_6,Scenarios!$B$6:$B$41,cbo_tier_6)-(SUMIFS(Scenarios!$L$6:$L$41,Scenarios!$A$6:$A$41,cbo_tier_6,Scenarios!$B$6:$B$41,cbo_tier_6)+SUMIFS(Scenarios!$M$6:$M$41,Scenarios!$A$6:$A$41,cbo_tier_6,Scenarios!$B$6:$B$41,cbo_tier_6)+SUMIFS(Scenarios!$N$6:$N$41,Scenarios!$A$6:$A$41,cbo_tier_6,Scenarios!$B$6:$B$41,cbo_tier_6)+SUMIFS(Scenarios!$O$6:$O$41,Scenarios!$A$6:$A$41,cbo_tier_6,Scenarios!$B$6:$B$41,cbo_tier_6)+SUMIFS(Scenarios!$P$6:$P$41,Scenarios!$A$6:$A$41,cbo_tier_6,Scenarios!$B$6:$B$41,cbo_tier_6))+(SUMIFS(Scenarios!$L$6:$L$41,Scenarios!$A$6:$A$41,cbo_tier_6,Scenarios!$B$6:$B$41,cbo_tier_6)+SUMIFS(Scenarios!$M$6:$M$41,Scenarios!$A$6:$A$41,cbo_tier_6,Scenarios!$B$6:$B$41,cbo_tier_6)+SUMIFS(Scenarios!$N$6:$N$41,Scenarios!$A$6:$A$41,cbo_tier_6,Scenarios!$B$6:$B$41,cbo_tier_6)+SUMIFS(Scenarios!$O$6:$O$41,Scenarios!$A$6:$A$41,cbo_tier_6,Scenarios!$B$6:$B$41,cbo_tier_6)+SUMIFS(Scenarios!$P$6:$P$41,Scenarios!$A$6:$A$41,cbo_tier_6,Scenarios!$B$6:$B$41,cbo_tier_6))*sens_gemini_mult
A19: What this is showing
A20: SMS is the line that compounds. Check-ins and panel size multiply. A monthly check-in with a larger panel is several times the base bill, while the same organizations cost little extra on Maps or Gemini if search stays capped and the map loads once per visit. Heavier map use stays free until a tier passes 10,000 loads. At 30 loads per funder, 200 funders are still inside the allowance and 500 funders cross it, at $7 per extra thousand loads. A higher Gemini price raises the AI columns and still leaves SMS as the larger number at community-scale texting.

Sheet One-time setup
A1: Cost to arrive at a size
A2: Signup is a Google Form or the in-app form, plus one short SMS with the link. That text is about $0.31. The form, and a QR code with no text, cost $0. These amounts are paid once per CBO. They are not in the monthly matrices. Community check-in texts are unchanged.
A4: Per new CBO, from Unit costs
A5: Onboarding SMS | B5: =onboard_sms_per_cbo
A6: First document batch | B6: =initial_docs_per_cbo
A7: First web-research pass | B7: =initial_research_per_cbo
A8: Total to join | B8: =onetime_per_cbo
A10: CBOs already on the platform | B10: New CBOs since the prior tier | C10: One-time cost of those new CBOs | D10: Cumulative one-time from zero | E10: Monthly run-rate at this size | F10: Cash in a month that also pays the one-time catch-up | G10: Of which SMS onboarding
A11: =cbo_tier_1 | B11: =A11 | C11: =B11*onetime_per_cbo | D11: =A11*onetime_per_cbo | E11: =SUMIFS(Scenarios!$V$6:$V$41,Scenarios!$A$6:$A$41,cbo_tier_1,Scenarios!$B$6:$B$41,cbo_tier_1) | F11: =C11+E11 | G11: =B11*onboard_sms_per_cbo
A12: =cbo_tier_2 | B12: =A12-A11 | C12: =B12*onetime_per_cbo | D12: =A12*onetime_per_cbo | E12: =SUMIFS(Scenarios!$V$6:$V$41,Scenarios!$A$6:$A$41,cbo_tier_2,Scenarios!$B$6:$B$41,cbo_tier_2) | F12: =C12+E12 | G12: =B12*onboard_sms_per_cbo
A13: =cbo_tier_3 | B13: =A13-A12 | C13: =B13*onetime_per_cbo | D13: =A13*onetime_per_cbo | E13: =SUMIFS(Scenarios!$V$6:$V$41,Scenarios!$A$6:$A$41,cbo_tier_3,Scenarios!$B$6:$B$41,cbo_tier_3) | F13: =C13+E13 | G13: =B13*onboard_sms_per_cbo
A14: =cbo_tier_4 | B14: =A14-A13 | C14: =B14*onetime_per_cbo | D14: =A14*onetime_per_cbo | E14: =SUMIFS(Scenarios!$V$6:$V$41,Scenarios!$A$6:$A$41,cbo_tier_4,Scenarios!$B$6:$B$41,cbo_tier_4) | F14: =C14+E14 | G14: =B14*onboard_sms_per_cbo
A15: =cbo_tier_5 | B15: =A15-A14 | C15: =B15*onetime_per_cbo | D15: =A15*onetime_per_cbo | E15: =SUMIFS(Scenarios!$V$6:$V$41,Scenarios!$A$6:$A$41,cbo_tier_5,Scenarios!$B$6:$B$41,cbo_tier_5) | F15: =C15+E15 | G15: =B15*onboard_sms_per_cbo
A16: =cbo_tier_6 | B16: =A16-A15 | C16: =B16*onetime_per_cbo | D16: =A16*onetime_per_cbo | E16: =SUMIFS(Scenarios!$V$6:$V$41,Scenarios!$A$6:$A$41,cbo_tier_6,Scenarios!$B$6:$B$41,cbo_tier_6) | F16: =C16+E16 | G16: =B16*onboard_sms_per_cbo
A18: How to use this
A19: Each new CBO is counted as one link text plus a 10-page document backlog. Google Forms and the in-app form are $0. Set onboarding texts to 0 on Assumptions when people open a QR code or a link with no SMS. The cash column is only for a month in which that whole step joins at once. A slow drip of new CBOs spreads the one-time amount across months and adds it to the rising monthly run-rate. Geocoding and the first web searches for these tiers stay inside the free quotas, so they are not given a dollar line. Public facts are confirmed on the profile page, not by a long reply-YES text.

Sheet Notes
B1: Notes and boundaries
B2: Planning rates for a live production deployment. Figures are public list prices around September 2026, in US dollars, and they move. Replace any yellow price on Assumptions with the rate in the vendor console.
B4: What is included | C4: Cloud SQL Postgres, Cloud Run, Secret Manager, container storage, a domain allowance, Firebase/Cloud Storage, Firestore mirrors, one Twilio US number, SMS to Kenya, Azure Document Intelligence layout, Gemini for documents, research, SMS parsing, and marketplace search, OpenAI for occasional funding audits, Google Custom Search, Maps JavaScript loads, and Geocoding.
B5: What is priced at zero on purpose | C5: KoboToolbox on the public server, Google Forms, Google sign-in, in-app funder–CBO messages, Claude (unless you type a per-CBO amount), DuckDuckGo as a search fallback, and GitHub Actions within the free tier. Idle Cloud Run is free because minimum instances stay at 0.
B6: SMS | C6: Kenya outbound is about $0.3134 per segment on Twilio's published rate. A segment is roughly 160 characters. Monthly SMS is the community check-in: one opening text to each panel member twice a year, then three short follow-ups only if they finish. Signup is separate and cheaper: one link text to a Google Form or the in-app form, about $0.31, or $0 if they use a QR code. The multi-step onboarding conversation and the public-facts text are not in the model. Inbound replies are priced as US messages. Community members pay their own airtime to text in.
B7: Database steps | C7: Under 200 active users on both sides: about $12 a month. Either side at 200: about $32. Either side at 500: about $65. Those are single-zone instances with disk and backups, not a hot standby. A high-availability instance is commonly close to double the database line and is excluded.
B8: Free tiers that hold through 500 × 500 | C8: At the default activity rates, Maps (10,000 loads), Custom Search (about 3,000 queries), Firestore, and Cloud Run's CPU allowance are not exhausted. The headroom columns on Scenarios show map loads, search queries, and vCPU-seconds. Sensitivity shows the map and Gemini cases that start to spend money.
B9: Why funders barely move the total | C9: Funder search ranks a shortlist, so its token cost does not grow with the full CBO count. Map pins are geocoded once. In-app conversation is just web traffic. The funder side does raise the database step when it crosses 200 or 500, even if there are few CBOs.
B10: Why CBOs move the total | C10: Each active CBO adds a predictable SMS amount every month, plus a few cents to a few dimes of document reading. That SMS amount scales with panel size, check-in frequency, completion, and whether texts stay inside one segment.
B11: Efficient choices behind the base case | C11: No always-on app server. CBO signup is a form plus at most one SMS link, not a multi-step text conversation. Document AI is Flash-class, and Azure does the table read. Marketplace ranking does not send every profile to the model. Web research is cached for 45 days and confirmed on the profile, not over SMS. Check-ins stay on the 6-month cycle. Community SMS goes to a panel of 8, not an entire beneficiary list. Claude stays off.
B12: Not a full operating budget | C12: Staff time, field travel, translation, training, phones, legal review, Kenya Data Protection Act compliance, and airtime paid by community members are outside this workbook. So are a staging environment, a second region, and premium support plans.
B13: Price sources | C13: Twilio Kenya outbound and US number rental; Azure Document Intelligence prebuilt layout at $10 per 1,000 pages; Google Maps Dynamic Maps at $7 per 1,000 after 10,000 free, Geocoding at $5 per 1,000 after 10,000 free; Custom Search JSON API at $5 per 1,000 after 100 free queries a day; Gemini Flash-class tokens at $0.30 / $2.50 per million; OpenAI GPT-4.1 class at $2 / $8 per million; Cloud Run request-based CPU, memory, and request free tier; Cloud SQL shared-core examples in the low tens of dollars; Firestore and Cloud Storage free quotas then standard rates. The large-database figure is a planning allowance, not a machine-type quote.
B14: How to refresh the model | C14: Edit yellow cells on Assumptions. Tiers, prices, panel size, and pages per CBO flow through Unit costs, Scenarios, both matrices, Matched growth, and One-time setup. Sensitivity has its own yellow alternates.
